Workbook

Sheet 📄 Завдання
A1: Домашнє завдання: RFM + Когортний аналіз
B3: КОНТЕКСТ
B4: Ви — аналітик у SaaS-продукті. Кожен користувач проходить через 7-денний безкоштовний тріал, після чого частина конвертується у платну підписку $19.99/місяць. Підписка продовжується автоматично щомісяця, поки клієнт не скасує. Юзери приходять з 5 каналів трафіку.
B6: Ваше завдання — проаналізувати базу платних клієнтів двома методами:
B7: 1. RFM — сегментувати клієнтів за їхньою поведінкою у підписці
B8: 2. Когортний аналіз — порівняти retention і LTV між когортами за місяцем реєстрації
B10: ДАНІ У ФАЙЛІ
B11: 📋 Реєстрації — список клієнтів з датою реєстрації, каналом, країною (тільки платні)
B12: 📋 Транзакції — історія усіх транзакцій клієнтів (тріал + місячна підписка), одна транзакція = один рядок
B13: 💸 Маркетинг — витрати на рекламу по каналам і місяцям (для бонусного завдання)
B15: ЩО ЗРОБИТИ
B17: КРОК 1 — Заповніть аркуш 👥 Клієнти - унікальні клієнти з інформацією по ним
B18: Для кожного клієнта порахуйте формулами:
... B59: • Загальний LTV/CAC по всьому платному маркетингу — чи інвестуємо в рекламу прибутково?

Sheet 📋 Реєстрації
A2: 📋 Реєстрації
A4: user_id | B4: signup_date | C4: country | D4: channel
A5: U0206 | B5: 45292 | C5: PL | D5: Google Ads
A6: U0209 | B6: 45292 | C6: FR | D6: Facebook Ads
A7: U0516 | B7: 45293 | C7: DE | D7: TikTok Ads
A8: U0245 | B8: 45294 | C8: UK | D8: Referral
A9: U0291 | B9: 45294 | C9: US | D9: Organic
A10: U0408 | B10: 45294 | C10: UA | D10: Google Ads
A11: U0883 | B11: 45294 | C11: US | D11: TikTok Ads
A12: U0333 | B12: 45295 | C12: UK | D12: Organic
A13: U0172 | B13: 45300 | C13: PL | D13: Organic
A14: U0641 | B14: 45300 | C14: US | D14: Facebook Ads
A15: U0879 | B15: 45300 | C15: PL | D15: Organic
A16: U0238 | B16: 45304 | C16: PL | D16: Google Ads
... A606: U0679 | B606: 45740 | C606: UK | D606: Facebook Ads

Sheet 📋 Транзакції
A2: 📋 Транзакції
A4: subscription_id | B4: user_id | C4: start_date | D4: end_date | E4: plan_type | F4: amount_usd | G4: status
A5: S00928 | B5: U0206 | C5: 45292 | D5: 45299 | E5: trial | F5: 0 | G5: ended
A6: S00947 | B6: U0209 | C6: 45292 | D6: 45299 | E6: trial | F6: 0 | G6: ended
A7: S02285 | B7: U0516 | C7: 45293 | D7: 45300 | E7: trial | F7: 0 | G7: ended
A8: S01115 | B8: U0245 | C8: 45294 | D8: 45301 | E8: trial | F8: 0 | G8: ended
A9: S01295 | B9: U0291 | C9: 45294 | D9: 45301 | E9: trial | F9: 0 | G9: ended
A10: S01820 | B10: U0408 | C10: 45294 | D10: 45301 | E10: trial | F10: 0 | G10: ended
A11: S03817 | B11: U0883 | C11: 45294 | D11: 45301 | E11: trial | F11: 0 | G11: ended
A12: S01495 | B12: U0333 | C12: 45295 | D12: 45302 | E12: trial | F12: 0 | G12: ended
A13: S00929 | B13: U0206 | C13: 45299 | D13: 45329 | E13: monthly | F13: 19.99 | G13: ended
A14: S00948 | B14: U0209 | C14: 45299 | D14: 45329 | E14: monthly | F14: 19.99 | G14: ended
A15: S00804 | B15: U0172 | C15: 45300 | D15: 45307 | E15: trial | F15: 0 | G15: ended
A16: S02286 | B16: U0516 | C16: 45300 | D16: 45330 | E16: monthly | F16: 19.99 | G16: ended
... A3623: S03788 | B3623: U0877 | C3623: 45747 | D3623: 45777 | E3623: monthly | F3623: 19.99 | G3623: active

Sheet 💸 Маркетинг
A2: 💸 Маркетингові витрати по каналах і місяцях
A4: month | B4: channel | C4: spend_usd
A5: 2024-01 | B5: Google Ads | C5: 619.89
A6: 2024-01 | B6: Facebook Ads | C6: 396.17
A7: 2024-01 | B7: TikTok Ads | C7: 554.84
A8: 2024-02 | B8: Google Ads | C8: 576.77
A9: 2024-02 | B9: Facebook Ads | C9: 523.05
A10: 2024-02 | B10: TikTok Ads | C10: 662.34
A11: 2024-03 | B11: Google Ads | C11: 741
A12: 2024-03 | B12: Facebook Ads | C12: 451.01
A13: 2024-03 | B13: TikTok Ads | C13: 647.47
A14: 2024-04 | B14: Google Ads | C14: 598.68
A15: 2024-04 | B15: Facebook Ads | C15: 495.52
A16: 2024-04 | B16: TikTok Ads | C16: 698.12
... A49: 2025-03 | B49: TikTok Ads | C49: 935.99

Sheet 👥 Клієнти
A1: 45747 | B1: ← Snapshot date
A2: 👥 Клієнти — список унікальних платящих користувачів + агрегати
G3: Активність у М+N (1 = був у підписці у цей місяць, 0 = ні) | S3: Виручка у М+N ($)
A4: User ID | B4: First Payment | C4: Cohort Month | D4: Paid Months | E4: Total Revenue ($) | F4: Recency (міс) | G4: М+0 | H4: М+1 | I4: М+2 | J4: М+3 | K4: М+4 | L4: М+5 | M4: М+6 | N4: М+7 | O4: М+8 | P4: М+9 | Q4: М+10 | R4: М+11 | S4: $M+0 | T4: $M+1 | U4: $M+2 | V4: $M+3 | W4: $M+4 | X4: $M+5 | Y4: $M+6 | Z4: $M+7 | AA4: $M+8 | AB4: $M+9 | AC4: $M+10 | AD4: $M+11
A5: ='📋 Реєстрації'!A5:A606 -> U0206 | B5: {=INDEX('📋 Транзакції'!$C$5:$C$3623,MATCH(A5,'📋 Транзакції'!$B$5:$B$3623,0))} -> 45292 | C5: =TEXT(B5,"YYYY-MM") -> 2024-01 | D5: =COUNTIF('📋 Транзакції'!$B$5:$B$3623,A5) -> 4 | E5: =SUMIF('📋 Транзакції'!$B$5:$B$3623,A5,'📋 Транзакції'!$F$5:$F$3623) -> 59.97 | F5: =INT($A$1-MAXIFS('📋 Транзакції'!$C$5:$C$3623,'📋 Транзакції'!$B$5:$B$3623,A5)) -> 388 | G5: =IF(COUNTIFS('📋 Транзакції'!$B$5:$B$3623,A5,'📋 Транзакції'!$C$5:$C$3623,">="&EDATE(DATEVALUE(C5&"-01"),0),'📋 Транзакції'!$C$5:$C$3623,"<"&EDATE(DATEVALUE(C5&"-01"),1))>0,1,0) -> 1 | H5: =IF(COUNTIFS('📋 Транзакції'!$B$5:$B$3623,A5,'📋 Транзакції'!$C$5:$C$3623,">="&EDATE(DATEVALUE(C5&"-01"),1),'📋 Транзакції'!$C$5:$C$3623,"<"&EDATE(DATEVALUE(C5&"-01"),2))>0,1,0) -> 1 | I5: =IF(COUNTIFS('📋 Транзакції'!$B$5:$B$3623,A5,'📋 Транзакції'!$C$5:$C$3623,">="&EDATE(DATEVALUE(C5&"-01"),2),'📋 Транзакції'!$C$5:$C$3623,"<"&EDATE(DATEVALUE(C5&"-01"),3))>0,1,0) -> 1 | J5: =IF(COUNTIFS('📋 Транзакції'!$B$5:$B$3623,A5,'📋 Транзакції'!$C$5:$C$3623,">="&EDATE(DATEVALUE(C5&"-01"),3),'📋 Транзакції'!$C$5:$C$3623,"<"&EDATE(DATEVALUE(C5&"-01"),4))>0,1,0) -> 0 | K5: =IF(COUNTIFS('📋 Транзакції'!$B$5:$B$3623,A5,'📋 Транзакції'!$C$5:$C$3623,">="&EDATE(DATEVALUE(C5&"-01"),4),'📋 Транзакції'!$C$5:$C$3623,"<"&EDATE(DATEVALUE(C5&"-01"),5))>0,1,0) -> 0 | L5: =IF(COUNTIFS('📋 Транзакції'!$B$5:$B$3623,A5,'📋 Транзакції'!$C$5:$C$3623,">="&EDATE(DATEVALUE(C5&"-01"),5),'📋 Транзакції'!$C$5:$C$3623,"<"&EDATE(DATEVALUE(C5&"-01"),6))>0,1,0) -> 0 | M5: =IF(COUNTIFS('📋 Транзакції'!$B$5:$B$3623,A5,'📋 Транзакції'!$C$5:$C$3623,">="&EDATE(DATEVALUE(C5&"-01"),6),'📋 Транзакції'!$C$5:$C$3623,"<"&EDATE(DATEVALUE(C5&"-01"),7))>0,1,0) -> 0 | N5: =IF(COUNTIFS('📋 Транзакції'!$B$5:$B$3623,A5,'📋 Транзакції'!$C$5:$C$3623,">="&EDATE(DATEVALUE(C5&"-01"),7),'📋 Транзакції'!$C$5:$C$3623,"<"&EDATE(DATEVALUE(C5&"-01"),8))>0,1,0) -> 0 | O5: =IF(COUNTIFS('📋 Транзакції'!$B$5:$B$3623,A5,'📋 Транзакції'!$C$5:$C$3623,">="&EDATE(DATEVALUE(C5&"-01"),8),'📋 Транзакції'!$C$5:$C$3623,"<"&EDATE(DATEVALUE(C5&"-01"),9))>0,1,0) -> 0 | P5: =IF(COUNTIFS('📋 Транзакції'!$B$5:$B$3623,A5,'📋 Транзакції'!$C$5:$C$3623,">="&EDATE(DATEVALUE(C5&"-01"),9),'📋 Транзакції'!$C$5:$C$3623,"<"&EDATE(DATEVALUE(C5&"-01"),10))>0,1,0) -> 0 | Q5: =IF(COUNTIFS('📋 Транзакції'!$B$5:$B$3623,A5,'📋 Транзакції'!$C$5:$C$3623,">="&EDATE(DATEVALUE(C5&"-01"),10),'📋 Транзакції'!$C$5:$C$3623,"<"&EDATE(DATEVALUE(C5&"-01"),11))>0,1,0) -> 0 | R5: =IF(COUNTIFS('📋 Транзакції'!$B$5:$B$3623,A5,'📋 Транзакції'!$C$5:$C$3623,">="&EDATE(DATEVALUE(C5&"-01"),11),'📋 Транзакції'!$C$5:$C$3623,"<"&EDATE(DATEVALUE(C5&"-01"),12))>0,1,0) -> 0 | S5: =SUMIFS('📋 Транзакції'!$F$5:$F$3623,'📋 Транзакції'!$B$5:$B$3623,A5,'📋 Транзакції'!$C$5:$C$3623,">="&EDATE(DATEVALUE(C5&"-01"),0),'📋 Транзакції'!$C$5:$C$3623,"<"&EDATE(DATEVALUE(C5&"-01"),1)) -> 19.99 | T5: =SUMIFS('📋 Транзакції'!$F$5:$F$3623,'📋 Транзакції'!$B$5:$B$3623,A5,'📋 Транзакції'!$C$5:$C$3623,">="&EDATE(DATEVALUE(C5&"-01"),1),'📋 Транзакції'!$C$5:$C$3623,"<"&EDATE(DATEVALUE(C5&"-01"),2)) -> 19.99 | U5: =SUMIFS('📋 Транзакції'!$F$5:$F$3623,'📋 Транзакції'!$B$5:$B$3623,A5,'📋 Транзакції'!$C$5:$C$3623,">="&EDATE(DATEVALUE(C5&"-01"),2),'📋 Транзакції'!$C$5:$C$3623,"<"&EDATE(DATEVALUE(C5&"-01"),3)) -> 19.99 | V5: =SUMIFS('📋 Транзакції'!$F$5:$F$3623,'📋 Транзакції'!$B$5:$B$3623,A5,'📋 Транзакції'!$C$5:$C$3623,">="&EDATE(DATEVALUE(C5&"-01"),3),'📋 Транзакції'!$C$5:$C$3623,"<"&EDATE(DATEVALUE(C5&"-01"),4)) -> 0 | W5: =SUMIFS('📋 Транзакції'!$F$5:$F$3623,'📋 Транзакції'!$B$5:$B$3623,A5,'📋 Транзакції'!$C$5:$C$3623,">="&EDATE(DATEVALUE(C5&"-01"),4),'📋 Транзакції'!$C$5:$C$3623,"<"&EDATE(DATEVALUE(C5&"-01"),5)) -> 0 | X5: =SUMIFS('📋 Транзакції'!$F$5:$F$3623,'📋 Транзакції'!$B$5:$B$3623,A5,'📋 Транзакції'!$C$5:$C$3623,">="&EDATE(DATEVALUE(C5&"-01"),5),'📋 Транзакції'!$C$5:$C$3623,"<"&EDATE(DATEVALUE(C5&"-01"),6)) -> 0 | Y5: =SUMIFS('📋 Транзакції'!$F$5:$F$3623,'📋 Транзакції'!$B$5:$B$3623,A5,'📋 Транзакції'!$C$5:$C$3623,">="&EDATE(DATEVALUE(C5&"-01"),6),'📋 Транзакції'!$C$5:$C$3623,"<"&EDATE(DATEVALUE(C5&"-01"),7)) -> 0 | Z5: =SUMIFS('📋 Транзакції'!$F$5:$F$3623,'📋 Транзакції'!$B$5:$B$3623,A5,'📋 Транзакції'!$C$5:$C$3623,">="&EDATE(DATEVALUE(C5&"-01"),7),'📋 Транзакції'!$C$5:$C$3623,"<"&EDATE(DATEVALUE(C5&"-01"),8)) -> 0 | AA5: =SUMIFS('📋 Транзакції'!$F$5:$F$3623,'📋 Транзакції'!$B$5:$B$3623,A5,'📋 Транзакції'!$C$5:$C$3623,">="&EDATE(DATEVALUE(C5&"-01"),8),'📋 Транзакції'!$C$5:$C$3623,"<"&EDATE(DATEVALUE(C5&"-01"),9)) -> 0 | AB5: =SUMIFS('📋 Транзакції'!$F$5:$F$3623,'📋 Транзакції'!$B$5:$B$3623,A5,'📋 Транзакції'!$C$5:$C$3623,">="&EDATE(DATEVALUE(C5&"-01"),9),'📋 Транзакції'!$C$5:$C$3623,"<"&EDATE(DATEVALUE(C5&"-01"),10)) -> 0 | AC5: =SUMIFS('📋 Транзакції'!$F$5:$F$3623,'📋 Транзакції'!$B$5:$B$3623,A5,'📋 Транзакції'!$C$5:$C$3623,">="&EDATE(DATEVALUE(C5&"-01"),10),'📋 Транзакції'!$C$5:$C$3623,"<"&EDATE(DATEVALUE(C5&"-01"),11)) -> 0 | AD5: =SUMIFS('📋 Транзакції'!$F$5:$F$3623,'📋 Транзакції'!$B$5:$B$3623,A5,'📋 Транзакції'!$C$5:$C$3623,">="&EDATE(DATEVALUE(C5&"-01"),11),'📋 Транзакції'!$C$5:$C$3623,"<"&EDATE(DATEVALUE(C5&"-01"),12)) -> 0
A6: ='📋 Реєстрації'!A6:A607 -> U0209 | B6: {=INDEX('📋 Транзакції'!$C$5:$C$3623,MATCH(A6,'📋 Транзакції'!$B$5:$B$3623,0))} -> 45292 | C6: =TEXT(B6,"YYYY-MM") -> 2024-01 | D6: =COUNTIF('📋 Транзакції'!$B$5:$B$3623,A6) -> 16 | E6: =SUMIF('📋 Транзакції'!$B$5:$B$3623,A6,'📋 Транзакції'!$F$5:$F$3623) -> 299.85 | F6: =INT($A$1-MAXIFS('📋 Транзакції'!$C$5:$C$3623,'📋 Транзакції'!$B$5:$B$3623,A6)) -> 28 | G6: =IF(COUNTIFS('📋 Транзакції'!$B$5:$B$3623,A6,'📋 Транзакції'!$C$5:$C$3623,">="&EDATE(DATEVALUE(C6&"-01"),0),'📋 Транзакції'!$C$5:$C$3623,"<"&EDATE(DATEVALUE(C6&"-01"),1))>0,1,0) -> 1 | H6: =IF(COUNTIFS('📋 Транзакції'!$B$5:$B$3623,A6,'📋 Транзакції'!$C$5:$C$3623,">="&EDATE(DATEVALUE(C6&"-01"),1),'📋 Транзакції'!$C$5:$C$3623,"<"&EDATE(DATEVALUE(C6&"-01"),2))>0,1,0) -> 1 | I6: =IF(COUNTIFS('📋 Транзакції'!$B$5:$B$3623,A6,'📋 Транзакції'!$C$5:$C$3623,">="&EDATE(DATEVALUE(C6&"-01"),2),'📋 Транзакції'!$C$5:$C$3623,"<"&EDATE(DATEVALUE(C6&"-01"),3))>0,1,0) -> 1 | J6: =IF(COUNTIFS('📋 Транзакції'!$B$5:$B$3623,A6,'📋 Транзакції'!$C$5:$C$3623,">="&EDATE(DATEVALUE(C6&"-01"),3),'📋 Транзакції'!$C$5:$C$3623,"<"&EDATE(DATEVALUE(C6&"-01"),4))>0,1,0) -> 1 | K6: =IF(COUNTIFS('📋 Транзакції'!$B$5:$B$3623,A6,'📋 Транзакції'!$C$5:$C$3623,">="&EDATE(DATEVALUE(C6&"-01"),4),'📋 Транзакції'!$C$5:$C$3623,"<"&EDATE(DATEVALUE(C6&"-01"),5))>0,1,0) -> 1 | L6: =IF(COUNTIFS('📋 Транзакції'!$B$5:$B$3623,A6,'📋 Транзакції'!$C$5:$C$3623,">="&EDATE(DATEVALUE(C6&"-01"),5),'📋 Транзакції'!$C$5:$C$3623,"<"&EDATE(DATEVALUE(C6&"-01"),6))>0,1,0) -> 1 | M6: =IF(COUNTIFS('📋 Транзакції'!$B$5:$B$3623,A6,'📋 Транзакції'!$C$5:$C$3623,">="&EDATE(DATEVALUE(C6&"-01"),6),'📋 Транзакції'!$C$5:$C$3623,"<"&EDATE(DATEVALUE(C6&"-01"),7))>0,1,0) -> 1 | N6: =IF(COUNTIFS('📋 Транзакції'!$B$5:$B$3623,A6,'📋 Транзакції'!$C$5:$C$3623,">="&EDATE(DATEVALUE(C6&"-01"),7),'📋 Транзакції'!$C$5:$C$3623,"<"&EDATE(DATEVALUE(C6&"-01"),8))>0,1,0) -> 1 | O6: =IF(COUNTIFS('📋 Транзакції'!$B$5:$B$3623,A6,'📋 Транзакції'!$C$5:$C$3623,">="&EDATE(DATEVALUE(C6&"-01"),8),'📋 Транзакції'!$C$5:$C$3623,"<"&EDATE(DATEVALUE(C6&"-01"),9))>0,1,0) -> 1 | P6: =IF(COUNTIFS('📋 Транзакції'!$B$5:$B$3623,A6,'📋 Транзакції'!$C$5:$C$3623,">="&EDATE(DATEVALUE(C6&"-01"),9),'📋 Транзакції'!$C$5:$C$3623,"<"&EDATE(DATEVALUE(C6&"-01"),10))>0,1,0) -> 1 | Q6: =IF(COUNTIFS('📋 Транзакції'!$B$5:$B$3623,A6,'📋 Транзакції'!$C$5:$C$3623,">="&EDATE(DATEVALUE(C6&"-01"),10),'📋 Транзакції'!$C$5:$C$3623,"<"&EDATE(DATEVALUE(C6&"-01"),11))>0,1,0) -> 1 | R6: =IF(COUNTIFS('📋 Транзакції'!$B$5:$B$3623,A6,'📋 Транзакції'!$C$5:$C$3623,">="&EDATE(DATEVALUE(C6&"-01"),11),'📋 Транзакції'!$C$5:$C$3623,"<"&EDATE(DATEVALUE(C6&"-01"),12))>0,1,0) -> 1 | S6: =SUMIFS('📋 Транзакції'!$F$5:$F$3623,'📋 Транзакції'!$B$5:$B$3623,A6,'📋 Транзакції'!$C$5:$C$3623,">="&EDATE(DATEVALUE(C6&"-01"),0),'📋 Транзакції'!$C$5:$C$3623,"<"&EDATE(DATEVALUE(C6&"-01"),1)) -> 19.99 | T6: =SUMIFS('📋 Транзакції'!$F$5:$F$3623,'📋 Транзакції'!$B$5:$B$3623,A6,'📋 Транзакції'!$C$5:$C$3623,">="&EDATE(DATEVALUE(C6&"-01"),1),'📋 Транзакції'!$C$5:$C$3623,"<"&EDATE(DATEVALUE(C6&"-01"),2)) -> 19.99 | U6: =SUMIFS('📋 Транзакції'!$F$5:$F$3623,'📋 Транзакції'!$B$5:$B$3623,A6,'📋 Транзакції'!$C$5:$C$3623,">="&EDATE(DATEVALUE(C6&"-01"),2),'📋 Транзакції'!$C$5:$C$3623,"<"&EDATE(DATEVALUE(C6&"-01"),3)) -> 19.99 | V6: =SUMIFS('📋 Транзакції'!$F$5:$F$3623,'📋 Транзакції'!$B$5:$B$3623,A6,'📋 Транзакції'!$C$5:$C$3623,">="&EDATE(DATEVALUE(C6&"-01"),3),'📋 Транзакції'!$C$5:$C$3623,"<"&EDATE(DATEVALUE(C6&"-01"),4)) -> 19.99 | W6: =SUMIFS('📋 Транзакції'!$F$5:$F$3623,'📋 Транзакції'!$B$5:$B$3623,A6,'📋 Транзакції'!$C$5:$C$3623,">="&EDATE(DATEVALUE(C6&"-01"),4),'📋 Транзакції'!$C$5:$C$3623,"<"&EDATE(DATEVALUE(C6&"-01"),5)) -> 19.99 | X6: =SUMIFS('📋 Транзакції'!$F$5:$F$3623,'📋 Транзакції'!$B$5:$B$3623,A6,'📋 Транзакції'!$C$5:$C$3623,">="&EDATE(DATEVALUE(C6&"-01"),5),'📋 Транзакції'!$C$5:$C$3623,"<"&EDATE(DATEVALUE(C6&"-01"),6)) -> 19.99 | Y6: =SUMIFS('📋 Транзакції'!$F$5:$F$3623,'📋 Транзакції'!$B$5:$B$3623,A6,'📋 Транзакції'!$C$5:$C$3623,">="&EDATE(DATEVALUE(C6&"-01"),6),'📋 Транзакції'!$C$5:$C$3623,"<"&EDATE(DATEVALUE(C6&"-01"),7)) -> 19.99 | Z6: =SUMIFS('📋 Транзакції'!$F$5:$F$3623,'📋 Транзакції'!$B$5:$B$3623,A6,'📋 Транзакції'!$C$5:$C$3623,">="&EDATE(DATEVALUE(C6&"-01"),7),'📋 Транзакції'!$C$5:$C$3623,"<"&EDATE(DATEVALUE(C6&"-01"),8)) -> 19.99 | AA6: =SUMIFS('📋 Транзакції'!$F$5:$F$3623,'📋 Транзакції'!$B$5:$B$3623,A6,'📋 Транзакції'!$C$5:$C$3623,">="&EDATE(DATEVALUE(C6&"-01"),8),'📋 Транзакції'!$C$5:$C$3623,"<"&EDATE(DATEVALUE(C6&"-01"),9)) -> 19.99 | AB6: =SUMIFS('📋 Транзакції'!$F$5:$F$3623,'📋 Транзакції'!$B$5:$B$3623,A6,'📋 Транзакції'!$C$5:$C$3623,">="&EDATE(DATEVALUE(C6&"-01"),9),'📋 Транзакції'!$C$5:$C$3623,"<"&EDATE(DATEVALUE(C6&"-01"),10)) -> 19.99 | AC6: =SUMIFS('📋 Транзакції'!$F$5:$F$3623,'📋 Транзакції'!$B$5:$B$3623,A6,'📋 Транзакції'!$C$5:$C$3623,">="&EDATE(DATEVALUE(C6&"-01"),10),'📋 Транзакції'!$C$5:$C$3623,"<"&EDATE(DATEVALUE(C6&"-01"),11)) -> 19.99 | AD6: =SUMIFS('📋 Транзакції'!$F$5:$F$3623,'📋 Транзакції'!$B$5:$B$3623,A6,'📋 Транзакції'!$C$5:$C$3623,">="&EDATE(DATEVALUE(C6&"-01"),11),'📋 Транзакції'!$C$5:$C$3623,"<"&EDATE(DATEVALUE(C6&"-01"),12)) -> 19.99
A7: ='📋 Реєстрації'!A7:A608 -> U0516 | B7: {=INDEX('📋 Транзакції'!$C$5:$C$3623,MATCH(A7,'📋 Транзакції'!$B$5:$B$3623,0))} -> 45293 | C7: =TEXT(B7,"YYYY-MM") -> 2024-01 | D7: =COUNTIF('📋 Транзакції'!$B$5:$B$3623,A7) -> 7 | E7: =SUMIF('📋 Транзакції'!$B$5:$B$3623,A7,'📋 Транзакції'!$F$5:$F$3623) -> 119.94 | F7: =INT($A$1-MAXIFS('📋 Транзакції'!$C$5:$C$3623,'📋 Транзакції'!$B$5:$B$3623,A7)) -> 297 | G7: =IF(COUNTIFS('📋 Транзакції'!$B$5:$B$3623,A7,'📋 Транзакції'!$C$5:$C$3623,">="&EDATE(DATEVALUE(C7&"-01"),0),'📋 Транзакції'!$C$5:$C$3623,"<"&EDATE(DATEVALUE(C7&"-01"),1))>0,1,0) -> 1 | H7: =IF(COUNTIFS('📋 Транзакції'!$B$5:$B$3623,A7,'📋 Транзакції'!$C$5:$C$3623,">="&EDATE(DATEVALUE(C7&"-01"),1),'📋 Транзакції'!$C$5:$C$3623,"<"&EDATE(DATEVALUE(C7&"-01"),2))>0,1,0) -> 1 | I7: =IF(COUNTIFS('📋 Транзакції'!$B$5:$B$3623,A7,'📋 Транзакції'!$C$5:$C$3623,">="&EDATE(DATEVALUE(C7&"-01"),2),'📋 Транзакції'!$C$5:$C$3623,"<"&EDATE(DATEVALUE(C7&"-01"),3))>0,1,0) -> 1 | J7: =IF(COUNTIFS('📋 Транзакції'!$B$5:$B$3623,A7,'📋 Транзакції'!$C$5:$C$3623,">="&EDATE(DATEVALUE(C7&"-01"),3),'📋 Транзакції'!$C$5:$C$3623,"<"&EDATE(DATEVALUE(C7&"-01"),4))>0,1,0) -> 1 | K7: =IF(COUNTIFS('📋 Транзакції'!$B$5:$B$3623,A7,'📋 Транзакції'!$C$5:$C$3623,">="&EDATE(DATEVALUE(C7&"-01"),4),'📋 Транзакції'!$C$5:$C$3623,"<"&EDATE(DATEVALUE(C7&"-01"),5))>0,1,0) -> 1 | L7: =IF(COUNTIFS('📋 Транзакції'!$B$5:$B$3623,A7,'📋 Транзакції'!$C$5:$C$3623,">="&EDATE(DATEVALUE(C7&"-01"),5),'📋 Транзакції'!$C$5:$C$3623,"<"&EDATE(DATEVALUE(C7&"-01"),6))>0,1,0) -> 1 | M7: =IF(COUNTIFS('📋 Транзакції'!$B$5:$B$3623,A7,'📋 Транзакції'!$C$5:$C$3623,">="&EDATE(DATEVALUE(C7&"-01"),6),'📋 Транзакції'!$C$5:$C$3623,"<"&EDATE(DATEVALUE(C7&"-01"),7))>0,1,0) -> 0 | N7: =IF(COUNTIFS('📋 Транзакції'!$B$5:$B$3623,A7,'📋 Транзакції'!$C$5:$C$3623,">="&EDATE(DATEVALUE(C7&"-01"),7),'📋 Транзакції'!$C$5:$C$3623,"<"&EDATE(DATEVALUE(C7&"-01"),8))>0,1,0) -> 0 | O7: =IF(COUNTIFS('📋 Транзакції'!$B$5:$B$3623,A7,'📋 Транзакції'!$C$5:$C$3623,">="&EDATE(DATEVALUE(C7&"-01"),8),'📋 Транзакції'!$C$5:$C$3623,"<"&EDATE(DATEVALUE(C7&"-01"),9))>0,1,0) -> 0 | P7: =IF(COUNTIFS('📋 Транзакції'!$B$5:$B$3623,A7,'📋 Транзакції'!$C$5:$C$3623,">="&EDATE(DATEVALUE(C7&"-01"),9),'📋 Транзакції'!$C$5:$C$3623,"<"&EDATE(DATEVALUE(C7&"-01"),10))>0,1,0) -> 0 | Q7: =IF(COUNTIFS('📋 Транзакції'!$B$5:$B$3623,A7,'📋 Транзакції'!$C$5:$C$3623,">="&EDATE(DATEVALUE(C7&"-01"),10),'📋 Транзакції'!$C$5:$C$3623,"<"&EDATE(DATEVALUE(C7&"-01"),11))>0,1,0) -> 0 | R7: =IF(COUNTIFS('📋 Транзакції'!$B$5:$B$3623,A7,'📋 Транзакції'!$C$5:$C$3623,">="&EDATE(DATEVALUE(C7&"-01"),11),'📋 Транзакції'!$C$5:$C$3623,"<"&EDATE(DATEVALUE(C7&"-01"),12))>0,1,0) -> 0 | S7: =SUMIFS('📋 Транзакції'!$F$5:$F$3623,'📋 Транзакції'!$B$5:$B$3623,A7,'📋 Транзакції'!$C$5:$C$3623,">="&EDATE(DATEVALUE(C7&"-01"),0),'📋 Транзакції'!$C$5:$C$3623,"<"&EDATE(DATEVALUE(C7&"-01"),1)) -> 19.99 | T7: =SUMIFS('📋 Транзакції'!$F$5:$F$3623,'📋 Транзакції'!$B$5:$B$3623,A7,'📋 Транзакції'!$C$5:$C$3623,">="&EDATE(DATEVALUE(C7&"-01"),1),'📋 Транзакції'!$C$5:$C$3623,"<"&EDATE(DATEVALUE(C7&"-01"),2)) -> 19.99 | U7: =SUMIFS('📋 Транзакції'!$F$5:$F$3623,'📋 Транзакції'!$B$5:$B$3623,A7,'📋 Транзакції'!$C$5:$C$3623,">="&EDATE(DATEVALUE(C7&"-01"),2),'📋 Транзакції'!$C$5:$C$3623,"<"&EDATE(DATEVALUE(C7&"-01"),3)) -> 19.99 | V7: =SUMIFS('📋 Транзакції'!$F$5:$F$3623,'📋 Транзакції'!$B$5:$B$3623,A7,'📋 Транзакції'!$C$5:$C$3623,">="&EDATE(DATEVALUE(C7&"-01"),3),'📋 Транзакції'!$C$5:$C$3623,"<"&EDATE(DATEVALUE(C7&"-01"),4)) -> 19.99 | W7: =SUMIFS('📋 Транзакції'!$F$5:$F$3623,'📋 Транзакції'!$B$5:$B$3623,A7,'📋 Транзакції'!$C$5:$C$3623,">="&EDATE(DATEVALUE(C7&"-01"),4),'📋 Транзакції'!$C$5:$C$3623,"<"&EDATE(DATEVALUE(C7&"-01"),5)) -> 19.99 | X7: =SUMIFS('📋 Транзакції'!$F$5:$F$3623,'📋 Транзакції'!$B$5:$B$3623,A7,'📋 Транзакції'!$C$5:$C$3623,">="&EDATE(DATEVALUE(C7&"-01"),5),'📋 Транзакції'!$C$5:$C$3623,"<"&EDATE(DATEVALUE(C7&"-01"),6)) -> 19.99 | Y7: =SUMIFS('📋 Транзакції'!$F$5:$F$3623,'📋 Транзакції'!$B$5:$B$3623,A7,'📋 Транзакції'!$C$5:$C$3623,">="&EDATE(DATEVALUE(C7&"-01"),6),'📋 Транзакції'!$C$5:$C$3623,"<"&EDATE(DATEVALUE(C7&"-01"),7)) -> 0 | Z7: =SUMIFS('📋 Транзакції'!$F$5:$F$3623,'📋 Транзакції'!$B$5:$B$3623,A7,'📋 Транзакції'!$C$5:$C$3623,">="&EDATE(DATEVALUE(C7&"-01"),7),'📋 Транзакції'!$C$5:$C$3623,"<"&EDATE(DATEVALUE(C7&"-01"),8)) -> 0 | AA7: =SUMIFS('📋 Транзакції'!$F$5:$F$3623,'📋 Транзакції'!$B$5:$B$3623,A7,'📋 Транзакції'!$C$5:$C$3623,">="&EDATE(DATEVALUE(C7&"-01"),8),'📋 Транзакції'!$C$5:$C$3623,"<"&EDATE(DATEVALUE(C7&"-01"),9)) -> 0 | AB7: =SUMIFS('📋 Транзакції'!$F$5:$F$3623,'📋 Транзакції'!$B$5:$B$3623,A7,'📋 Транзакції'!$C$5:$C$3623,">="&EDATE(DATEVALUE(C7&"-01"),9),'📋 Транзакції'!$C$5:$C$3623,"<"&EDATE(DATEVALUE(C7&"-01"),10)) -> 0 | AC7: =SUMIFS('📋 Транзакції'!$F$5:$F$3623,'📋 Транзакції'!$B$5:$B$3623,A7,'📋 Транзакції'!$C$5:$C$3623,">="&EDATE(DATEVALUE(C7&"-01"),10),'📋 Транзакції'!$C$5:$C$3623,"<"&EDATE(DATEVALUE(C7&"-01"),11)) -> 0 | AD7: =SUMIFS('📋 Транзакції'!$F$5:$F$3623,'📋 Транзакції'!$B$5:$B$3623,A7,'📋 Транзакції'!$C$5:$C$3623,">="&EDATE(DATEVALUE(C7&"-01"),11),'📋 Транзакції'!$C$5:$C$3623,"<"&EDATE(DATEVALUE(C7&"-01"),12)) -> 0
A8: ='📋 Реєстрації'!A8:A609 -> U0245 | B8: {=INDEX('📋 Транзакції'!$C$5:$C$3623,MATCH(A8,'📋 Транзакції'!$B$5:$B$3623,0))} -> 45294 | C8: =TEXT(B8,"YYYY-MM") -> 2024-01 | D8: =COUNTIF('📋 Транзакції'!$B$5:$B$3623,A8) -> 3 | E8: =SUMIF('📋 Транзакції'!$B$5:$B$3623,A8,'📋 Транзакції'!$F$5:$F$3623) -> 39.98 | F8: =INT($A$1-MAXIFS('📋 Транзакції'!$C$5:$C$3623,'📋 Транзакції'!$B$5:$B$3623,A8)) -> 416 | G8: =IF(COUNTIFS('📋 Транзакції'!$B$5:$B$3623,A8,'📋 Транзакції'!$C$5:$C$3623,">="&EDATE(DATEVALUE(C8&"-01"),0),'📋 Транзакції'!$C$5:$C$3623,"<"&EDATE(DATEVALUE(C8&"-01"),1))>0,1,0) -> 1 | H8: =IF(COUNTIFS('📋 Транзакції'!$B$5:$B$3623,A8,'📋 Транзакції'!$C$5:$C$3623,">="&EDATE(DATEVALUE(C8&"-01"),1),'📋 Транзакції'!$C$5:$C$3623,"<"&EDATE(DATEVALUE(C8&"-01"),2))>0,1,0) -> 1 | I8: =IF(COUNTIFS('📋 Транзакції'!$B$5:$B$3623,A8,'📋 Транзакції'!$C$5:$C$3623,">="&EDATE(DATEVALUE(C8&"-01"),2),'📋 Транзакції'!$C$5:$C$3623,"<"&EDATE(DATEVALUE(C8&"-01"),3))>0,1,0) -> 0 | J8: =IF(COUNTIFS('📋 Транзакції'!$B$5:$B$3623,A8,'📋 Транзакції'!$C$5:$C$3623,">="&EDATE(DATEVALUE(C8&"-01"),3),'📋 Транзакції'!$C$5:$C$3623,"<"&EDATE(DATEVALUE(C8&"-01"),4))>0,1,0) -> 0 | K8: =IF(COUNTIFS('📋 Транзакції'!$B$5:$B$3623,A8,'📋 Транзакції'!$C$5:$C$3623,">="&EDATE(DATEVALUE(C8&"-01"),4),'📋 Транзакції'!$C$5:$C$3623,"<"&EDATE(DATEVALUE(C8&"-01"),5))>0,1,0) -> 0 | L8: =IF(COUNTIFS('📋 Транзакції'!$B$5:$B$3623,A8,'📋 Транзакції'!$C$5:$C$3623,">="&EDATE(DATEVALUE(C8&"-01"),5),'📋 Транзакції'!$C$5:$C$3623,"<"&EDATE(DATEVALUE(C8&"-01"),6))>0,1,0) -> 0 | M8: =IF(COUNTIFS('📋 Транзакції'!$B$5:$B$3623,A8,'📋 Транзакції'!$C$5:$C$3623,">="&EDATE(DATEVALUE(C8&"-01"),6),'📋 Транзакції'!$C$5:$C$3623,"<"&EDATE(DATEVALUE(C8&"-01"),7))>0,1,0) -> 0 | N8: =IF(COUNTIFS('📋 Транзакції'!$B$5:$B$3623,A8,'📋 Транзакції'!$C$5:$C$3623,">="&EDATE(DATEVALUE(C8&"-01"),7),'📋 Транзакції'!$C$5:$C$3623,"<"&EDATE(DATEVALUE(C8&"-01"),8))>0,1,0) -> 0 | O8: =IF(COUNTIFS('📋 Транзакції'!$B$5:$B$3623,A8,'📋 Транзакції'!$C$5:$C$3623,">="&EDATE(DATEVALUE(C8&"-01"),8),'📋 Транзакції'!$C$5:$C$3623,"<"&EDATE(DATEVALUE(C8&"-01"),9))>0,1,0) -> 0 | P8: =IF(COUNTIFS('📋 Транзакції'!$B$5:$B$3623,A8,'📋 Транзакції'!$C$5:$C$3623,">="&EDATE(DATEVALUE(C8&"-01"),9),'📋 Транзакції'!$C$5:$C$3623,"<"&EDATE(DATEVALUE(C8&"-01"),10))>0,1,0) -> 0 | Q8: =IF(COUNTIFS('📋 Транзакції'!$B$5:$B$3623,A8,'📋 Транзакції'!$C$5:$C$3623,">="&EDATE(DATEVALUE(C8&"-01"),10),'📋 Транзакції'!$C$5:$C$3623,"<"&EDATE(DATEVALUE(C8&"-01"),11))>0,1,0) -> 0 | R8: =IF(COUNTIFS('📋 Транзакції'!$B$5:$B$3623,A8,'📋 Транзакції'!$C$5:$C$3623,">="&EDATE(DATEVALUE(C8&"-01"),11),'📋 Транзакції'!$C$5:$C$3623,"<"&EDATE(DATEVALUE(C8&"-01"),12))>0,1,0) -> 0 | S8: =SUMIFS('📋 Транзакції'!$F$5:$F$3623,'📋 Транзакції'!$B$5:$B$3623,A8,'📋 Транзакції'!$C$5:$C$3623,">="&EDATE(DATEVALUE(C8&"-01"),0),'📋 Транзакції'!$C$5:$C$3623,"<"&EDATE(DATEVALUE(C8&"-01"),1)) -> 19.99 | T8: =SUMIFS('📋 Транзакції'!$F$5:$F$3623,'📋 Транзакції'!$B$5:$B$3623,A8,'📋 Транзакції'!$C$5:$C$3623,">="&EDATE(DATEVALUE(C8&"-01"),1),'📋 Транзакції'!$C$5:$C$3623,"<"&EDATE(DATEVALUE(C8&"-01"),2)) -> 19.99 | U8: =SUMIFS('📋 Транзакції'!$F$5:$F$3623,'📋 Транзакції'!$B$5:$B$3623,A8,'📋 Транзакції'!$C$5:$C$3623,">="&EDATE(DATEVALUE(C8&"-01"),2),'📋 Транзакції'!$C$5:$C$3623,"<"&EDATE(DATEVALUE(C8&"-01"),3)) -> 0 | V8: =SUMIFS('📋 Транзакції'!$F$5:$F$3623,'📋 Транзакції'!$B$5:$B$3623,A8,'📋 Транзакції'!$C$5:$C$3623,">="&EDATE(DATEVALUE(C8&"-01"),3),'📋 Транзакції'!$C$5:$C$3623,"<"&EDATE(DATEVALUE(C8&"-01"),4)) -> 0 | W8: =SUMIFS('📋 Транзакції'!$F$5:$F$3623,'📋 Транзакції'!$B$5:$B$3623,A8,'📋 Транзакції'!$C$5:$C$3623,">="&EDATE(DATEVALUE(C8&"-01"),4),'📋 Транзакції'!$C$5:$C$3623,"<"&EDATE(DATEVALUE(C8&"-01"),5)) -> 0 | X8: =SUMIFS('📋 Транзакції'!$F$5:$F$3623,'📋 Транзакції'!$B$5:$B$3623,A8,'📋 Транзакції'!$C$5:$C$3623,">="&EDATE(DATEVALUE(C8&"-01"),5),'📋 Транзакції'!$C$5:$C$3623,"<"&EDATE(DATEVALUE(C8&"-01"),6)) -> 0 | Y8: =SUMIFS('📋 Транзакції'!$F$5:$F$3623,'📋 Транзакції'!$B$5:$B$3623,A8,'📋 Транзакції'!$C$5:$C$3623,">="&EDATE(DATEVALUE(C8&"-01"),6),'📋 Транзакції'!$C$5:$C$3623,"<"&EDATE(DATEVALUE(C8&"-01"),7)) -> 0 | Z8: =SUMIFS('📋 Транзакції'!$F$5:$F$3623,'📋 Транзакції'!$B$5:$B$3623,A8,'📋 Транзакції'!$C$5:$C$3623,">="&EDATE(DATEVALUE(C8&"-01"),7),'📋 Транзакції'!$C$5:$C$3623,"<"&EDATE(DATEVALUE(C8&"-01"),8)) -> 0 | AA8: =SUMIFS('📋 Транзакції'!$F$5:$F$3623,'📋 Транзакції'!$B$5:$B$3623,A8,'📋 Транзакції'!$C$5:$C$3623,">="&EDATE(DATEVALUE(C8&"-01"),8),'📋 Транзакції'!$C$5:$C$3623,"<"&EDATE(DATEVALUE(C8&"-01"),9)) -> 0 | AB8: =SUMIFS('📋 Транзакції'!$F$5:$F$3623,'📋 Транзакції'!$B$5:$B$3623,A8,'📋 Транзакції'!$C$5:$C$3623,">="&EDATE(DATEVALUE(C8&"-01"),9),'📋 Транзакції'!$C$5:$C$3623,"<"&EDATE(DATEVALUE(C8&"-01"),10)) -> 0 | AC8: =SUMIFS('📋 Транзакції'!$F$5:$F$3623,'📋 Транзакції'!$B$5:$B$3623,A8,'📋 Транзакції'!$C$5:$C$3623,">="&EDATE(DATEVALUE(C8&"-01"),10),'📋 Транзакції'!$C$5:$C$3623,"<"&EDATE(DATEVALUE(C8&"-01"),11)) -> 0 | AD8: =SUMIFS('📋 Транзакції'!$F$5:$F$3623,'📋 Транзакції'!$B$5:$B$3623,A8,'📋 Транзакції'!$C$5:$C$3623,">="&EDATE(DATEVALUE(C8&"-01"),11),'📋 Транзакції'!$C$5:$C$3623,"<"&EDATE(DATEVALUE(C8&"-01"),12)) -> 0
A9: ='📋 Реєстрації'!A9:A610 -> U0291 | B9: {=INDEX('📋 Транзакції'!$C$5:$C$3623,MATCH(A9,'📋 Транзакції'!$B$5:$B$3623,0))} -> 45294 | C9: =TEXT(B9,"YYYY-MM") -> 2024-01 | D9: =COUNTIF('📋 Транзакції'!$B$5:$B$3623,A9) -> 3 | E9: =SUMIF('📋 Транзакції'!$B$5:$B$3623,A9,'📋 Транзакції'!$F$5:$F$3623) -> 39.98 | F9: =INT($A$1-MAXIFS('📋 Транзакції'!$C$5:$C$3623,'📋 Транзакції'!$B$5:$B$3623,A9)) -> 416 | G9: =IF(COUNTIFS('📋 Транзакції'!$B$5:$B$3623,A9,'📋 Транзакції'!$C$5:$C$3623,">="&EDATE(DATEVALUE(C9&"-01"),0),'📋 Транзакції'!$C$5:$C$3623,"<"&EDATE(DATEVALUE(C9&"-01"),1))>0,1,0) -> 1 | H9: =IF(COUNTIFS('📋 Транзакції'!$B$5:$B$3623,A9,'📋 Транзакції'!$C$5:$C$3623,">="&EDATE(DATEVALUE(C9&"-01"),1),'📋 Транзакції'!$C$5:$C$3623,"<"&EDATE(DATEVALUE(C9&"-01"),2))>0,1,0) -> 1 | I9: =IF(COUNTIFS('📋 Транзакції'!$B$5:$B$3623,A9,'📋 Транзакції'!$C$5:$C$3623,">="&EDATE(DATEVALUE(C9&"-01"),2),'📋 Транзакції'!$C$5:$C$3623,"<"&EDATE(DATEVALUE(C9&"-01"),3))>0,1,0) -> 0 | J9: =IF(COUNTIFS('📋 Транзакції'!$B$5:$B$3623,A9,'📋 Транзакції'!$C$5:$C$3623,">="&EDATE(DATEVALUE(C9&"-01"),3),'📋 Транзакції'!$C$5:$C$3623,"<"&EDATE(DATEVALUE(C9&"-01"),4))>0,1,0) -> 0 | K9: =IF(COUNTIFS('📋 Транзакції'!$B$5:$B$3623,A9,'📋 Транзакції'!$C$5:$C$3623,">="&EDATE(DATEVALUE(C9&"-01"),4),'📋 Транзакції'!$C$5:$C$3623,"<"&EDATE(DATEVALUE(C9&"-01"),5))>0,1,0) -> 0 | L9: =IF(COUNTIFS('📋 Транзакції'!$B$5:$B$3623,A9,'📋 Транзакції'!$C$5:$C$3623,">="&EDATE(DATEVALUE(C9&"-01"),5),'📋 Транзакції'!$C$5:$C$3623,"<"&EDATE(DATEVALUE(C9&"-01"),6))>0,1,0) -> 0 | M9: =IF(COUNTIFS('📋 Транзакції'!$B$5:$B$3623,A9,'📋 Транзакції'!$C$5:$C$3623,">="&EDATE(DATEVALUE(C9&"-01"),6),'📋 Транзакції'!$C$5:$C$3623,"<"&EDATE(DATEVALUE(C9&"-01"),7))>0,1,0) -> 0 | N9: =IF(COUNTIFS('📋 Транзакції'!$B$5:$B$3623,A9,'📋 Транзакції'!$C$5:$C$3623,">="&EDATE(DATEVALUE(C9&"-01"),7),'📋 Транзакції'!$C$5:$C$3623,"<"&EDATE(DATEVALUE(C9&"-01"),8))>0,1,0) -> 0 | O9: =IF(COUNTIFS('📋 Транзакції'!$B$5:$B$3623,A9,'📋 Транзакції'!$C$5:$C$3623,">="&EDATE(DATEVALUE(C9&"-01"),8),'📋 Транзакції'!$C$5:$C$3623,"<"&EDATE(DATEVALUE(C9&"-01"),9))>0,1,0) -> 0 | P9: =IF(COUNTIFS('📋 Транзакції'!$B$5:$B$3623,A9,'📋 Транзакції'!$C$5:$C$3623,">="&EDATE(DATEVALUE(C9&"-01"),9),'📋 Транзакції'!$C$5:$C$3623,"<"&EDATE(DATEVALUE(C9&"-01"),10))>0,1,0) -> 0 | Q9: =IF(COUNTIFS('📋 Транзакції'!$B$5:$B$3623,A9,'📋 Транзакції'!$C$5:$C$3623,">="&EDATE(DATEVALUE(C9&"-01"),10),'📋 Транзакції'!$C$5:$C$3623,"<"&EDATE(DATEVALUE(C9&"-01"),11))>0,1,0) -> 0 | R9: =IF(COUNTIFS('📋 Транзакції'!$B$5:$B$3623,A9,'📋 Транзакції'!$C$5:$C$3623,">="&EDATE(DATEVALUE(C9&"-01"),11),'📋 Транзакції'!$C$5:$C$3623,"<"&EDATE(DATEVALUE(C9&"-01"),12))>0,1,0) -> 0 | S9: =SUMIFS('📋 Транзакції'!$F$5:$F$3623,'📋 Транзакції'!$B$5:$B$3623,A9,'📋 Транзакції'!$C$5:$C$3623,">="&EDATE(DATEVALUE(C9&"-01"),0),'📋 Транзакції'!$C$5:$C$3623,"<"&EDATE(DATEVALUE(C9&"-01"),1)) -> 19.99 | T9: =SUMIFS('📋 Транзакції'!$F$5:$F$3623,'📋 Транзакції'!$B$5:$B$3623,A9,'📋 Транзакції'!$C$5:$C$3623,">="&EDATE(DATEVALUE(C9&"-01"),1),'📋 Транзакції'!$C$5:$C$3623,"<"&EDATE(DATEVALUE(C9&"-01"),2)) -> 19.99 | U9: =SUMIFS('📋 Транзакції'!$F$5:$F$3623,'📋 Транзакції'!$B$5:$B$3623,A9,'📋 Транзакції'!$C$5:$C$3623,">="&EDATE(DATEVALUE(C9&"-01"),2),'📋 Транзакції'!$C$5:$C$3623,"<"&EDATE(DATEVALUE(C9&"-01"),3)) -> 0 | V9: =SUMIFS('📋 Транзакції'!$F$5:$F$3623,'📋 Транзакції'!$B$5:$B$3623,A9,'📋 Транзакції'!$C$5:$C$3623,">="&EDATE(DATEVALUE(C9&"-01"),3),'📋 Транзакції'!$C$5:$C$3623,"<"&EDATE(DATEVALUE(C9&"-01"),4)) -> 0 | W9: =SUMIFS('📋 Транзакції'!$F$5:$F$3623,'📋 Транзакції'!$B$5:$B$3623,A9,'📋 Транзакції'!$C$5:$C$3623,">="&EDATE(DATEVALUE(C9&"-01"),4),'📋 Транзакції'!$C$5:$C$3623,"<"&EDATE(DATEVALUE(C9&"-01"),5)) -> 0 | X9: =SUMIFS('📋 Транзакції'!$F$5:$F$3623,'📋 Транзакції'!$B$5:$B$3623,A9,'📋 Транзакції'!$C$5:$C$3623,">="&EDATE(DATEVALUE(C9&"-01"),5),'📋 Транзакції'!$C$5:$C$3623,"<"&EDATE(DATEVALUE(C9&"-01"),6)) -> 0 | Y9: =SUMIFS('📋 Транзакції'!$F$5:$F$3623,'📋 Транзакції'!$B$5:$B$3623,A9,'📋 Транзакції'!$C$5:$C$3623,">="&EDATE(DATEVALUE(C9&"-01"),6),'📋 Транзакції'!$C$5:$C$3623,"<"&EDATE(DATEVALUE(C9&"-01"),7)) -> 0 | Z9: =SUMIFS('📋 Транзакції'!$F$5:$F$3623,'📋 Транзакції'!$B$5:$B$3623,A9,'📋 Транзакції'!$C$5:$C$3623,">="&EDATE(DATEVALUE(C9&"-01"),7),'📋 Транзакції'!$C$5:$C$3623,"<"&EDATE(DATEVALUE(C9&"-01"),8)) -> 0 | AA9: =SUMIFS('📋 Транзакції'!$F$5:$F$3623,'📋 Транзакції'!$B$5:$B$3623,A9,'📋 Транзакції'!$C$5:$C$3623,">="&EDATE(DATEVALUE(C9&"-01"),8),'📋 Транзакції'!$C$5:$C$3623,"<"&EDATE(DATEVALUE(C9&"-01"),9)) -> 0 | AB9: =SUMIFS('📋 Транзакції'!$F$5:$F$3623,'📋 Транзакції'!$B$5:$B$3623,A9,'📋 Транзакції'!$C$5:$C$3623,">="&EDATE(DATEVALUE(C9&"-01"),9),'📋 Транзакції'!$C$5:$C$3623,"<"&EDATE(DATEVALUE(C9&"-01"),10)) -> 0 | AC9: =SUMIFS('📋 Транзакції'!$F$5:$F$3623,'📋 Транзакції'!$B$5:$B$3623,A9,'📋 Транзакції'!$C$5:$C$3623,">="&EDATE(DATEVALUE(C9&"-01"),10),'📋 Транзакції'!$C$5:$C$3623,"<"&EDATE(DATEVALUE(C9&"-01"),11)) -> 0 | AD9: =SUMIFS('📋 Транзакції'!$F$5:$F$3623,'📋 Транзакції'!$B$5:$B$3623,A9,'📋 Транзакції'!$C$5:$C$3623,">="&EDATE(DATEVALUE(C9&"-01"),11),'📋 Транзакції'!$C$5:$C$3623,"<"&EDATE(DATEVALUE(C9&"-01"),12)) -> 0
A10: ='📋 Реєстрації'!A10:A611 -> U0408 | B10: {=INDEX('📋 Транзакції'!$C$5:$C$3623,MATCH(A10,'📋 Транзакції'!$B$5:$B$3623,0))} -> 45294 | C10: =TEXT(B10,"YYYY-MM") -> 2024-01 | D10: =COUNTIF('📋 Транзакції'!$B$5:$B$3623,A10) -> 3 | E10: =SUMIF('📋 Транзакції'!$B$5:$B$3623,A10,'📋 Транзакції'!$F$5:$F$3623) -> 39.98 | F10: =INT($A$1-MAXIFS('📋 Транзакції'!$C$5:$C$3623,'📋 Транзакції'!$B$5:$B$3623,A10)) -> 416 | G10: =IF(COUNTIFS('📋 Транзакції'!$B$5:$B$3623,A10,'📋 Транзакції'!$C$5:$C$3623,">="&EDATE(DATEVALUE(C10&"-01"),0),'📋 Транзакції'!$C$5:$C$3623,"<"&EDATE(DATEVALUE(C10&"-01"),1))>0,1,0) -> 1 | H10: =IF(COUNTIFS('📋 Транзакції'!$B$5:$B$3623,A10,'📋 Транзакції'!$C$5:$C$3623,">="&EDATE(DATEVALUE(C10&"-01"),1),'📋 Транзакції'!$C$5:$C$3623,"<"&EDATE(DATEVALUE(C10&"-01"),2))>0,1,0) -> 1 | I10: =IF(COUNTIFS('📋 Транзакції'!$B$5:$B$3623,A10,'📋 Транзакції'!$C$5:$C$3623,">="&EDATE(DATEVALUE(C10&"-01"),2),'📋 Транзакції'!$C$5:$C$3623,"<"&EDATE(DATEVALUE(C10&"-01"),3))>0,1,0) -> 0 | J10: =IF(COUNTIFS('📋 Транзакції'!$B$5:$B$3623,A10,'📋 Транзакції'!$C$5:$C$3623,">="&EDATE(DATEVALUE(C10&"-01"),3),'📋 Транзакції'!$C$5:$C$3623,"<"&EDATE(DATEVALUE(C10&"-01"),4))>0,1,0) -> 0 | K10: =IF(COUNTIFS('📋 Транзакції'!$B$5:$B$3623,A10,'📋 Транзакції'!$C$5:$C$3623,">="&EDATE(DATEVALUE(C10&"-01"),4),'📋 Транзакції'!$C$5:$C$3623,"<"&EDATE(DATEVALUE(C10&"-01"),5))>0,1,0) -> 0 | L10: =IF(COUNTIFS('📋 Транзакції'!$B$5:$B$3623,A10,'📋 Транзакції'!$C$5:$C$3623,">="&EDATE(DATEVALUE(C10&"-01"),5),'📋 Транзакції'!$C$5:$C$3623,"<"&EDATE(DATEVALUE(C10&"-01"),6))>0,1,0) -> 0 | M10: =IF(COUNTIFS('📋 Транзакції'!$B$5:$B$3623,A10,'📋 Транзакції'!$C$5:$C$3623,">="&EDATE(DATEVALUE(C10&"-01"),6),'📋 Транзакції'!$C$5:$C$3623,"<"&EDATE(DATEVALUE(C10&"-01"),7))>0,1,0) -> 0 | N10: =IF(COUNTIFS('📋 Транзакції'!$B$5:$B$3623,A10,'📋 Транзакції'!$C$5:$C$3623,">="&EDATE(DATEVALUE(C10&"-01"),7),'📋 Транзакції'!$C$5:$C$3623,"<"&EDATE(DATEVALUE(C10&"-01"),8))>0,1,0) -> 0 | O10: =IF(COUNTIFS('📋 Транзакції'!$B$5:$B$3623,A10,'📋 Транзакції'!$C$5:$C$3623,">="&EDATE(DATEVALUE(C10&"-01"),8),'📋 Транзакції'!$C$5:$C$3623,"<"&EDATE(DATEVALUE(C10&"-01"),9))>0,1,0) -> 0 | P10: =IF(COUNTIFS('📋 Транзакції'!$B$5:$B$3623,A10,'📋 Транзакції'!$C$5:$C$3623,">="&EDATE(DATEVALUE(C10&"-01"),9),'📋 Транзакції'!$C$5:$C$3623,"<"&EDATE(DATEVALUE(C10&"-01"),10))>0,1,0) -> 0 | Q10: =IF(COUNTIFS('📋 Транзакції'!$B$5:$B$3623,A10,'📋 Транзакції'!$C$5:$C$3623,">="&EDATE(DATEVALUE(C10&"-01"),10),'📋 Транзакції'!$C$5:$C$3623,"<"&EDATE(DATEVALUE(C10&"-01"),11))>0,1,0) -> 0 | R10: =IF(COUNTIFS('📋 Транзакції'!$B$5:$B$3623,A10,'📋 Транзакції'!$C$5:$C$3623,">="&EDATE(DATEVALUE(C10&"-01"),11),'📋 Транзакції'!$C$5:$C$3623,"<"&EDATE(DATEVALUE(C10&"-01"),12))>0,1,0) -> 0 | S10: =SUMIFS('📋 Транзакції'!$F$5:$F$3623,'📋 Транзакції'!$B$5:$B$3623,A10,'📋 Транзакції'!$C$5:$C$3623,">="&EDATE(DATEVALUE(C10&"-01"),0),'📋 Транзакції'!$C$5:$C$3623,"<"&EDATE(DATEVALUE(C10&"-01"),1)) -> 19.99 | T10: =SUMIFS('📋 Транзакції'!$F$5:$F$3623,'📋 Транзакції'!$B$5:$B$3623,A10,'📋 Транзакції'!$C$5:$C$3623,">="&EDATE(DATEVALUE(C10&"-01"),1),'📋 Транзакції'!$C$5:$C$3623,"<"&EDATE(DATEVALUE(C10&"-01"),2)) -> 19.99 | U10: =SUMIFS('📋 Транзакції'!$F$5:$F$3623,'📋 Транзакції'!$B$5:$B$3623,A10,'📋 Транзакції'!$C$5:$C$3623,">="&EDATE(DATEVALUE(C10&"-01"),2),'📋 Транзакції'!$C$5:$C$3623,"<"&EDATE(DATEVALUE(C10&"-01"),3)) -> 0 | V10: =SUMIFS('📋 Транзакції'!$F$5:$F$3623,'📋 Транзакції'!$B$5:$B$3623,A10,'📋 Транзакції'!$C$5:$C$3623,">="&EDATE(DATEVALUE(C10&"-01"),3),'📋 Транзакції'!$C$5:$C$3623,"<"&EDATE(DATEVALUE(C10&"-01"),4)) -> 0 | W10: =SUMIFS('📋 Транзакції'!$F$5:$F$3623,'📋 Транзакції'!$B$5:$B$3623,A10,'📋 Транзакції'!$C$5:$C$3623,">="&EDATE(DATEVALUE(C10&"-01"),4),'📋 Транзакції'!$C$5:$C$3623,"<"&EDATE(DATEVALUE(C10&"-01"),5)) -> 0 | X10: =SUMIFS('📋 Транзакції'!$F$5:$F$3623,'📋 Транзакції'!$B$5:$B$3623,A10,'📋 Транзакції'!$C$5:$C$3623,">="&EDATE(DATEVALUE(C10&"-01"),5),'📋 Транзакції'!$C$5:$C$3623,"<"&EDATE(DATEVALUE(C10&"-01"),6)) -> 0 | Y10: =SUMIFS('📋 Транзакції'!$F$5:$F$3623,'📋 Транзакції'!$B$5:$B$3623,A10,'📋 Транзакції'!$C$5:$C$3623,">="&EDATE(DATEVALUE(C10&"-01"),6),'📋 Транзакції'!$C$5:$C$3623,"<"&EDATE(DATEVALUE(C10&"-01"),7)) -> 0 | Z10: =SUMIFS('📋 Транзакції'!$F$5:$F$3623,'📋 Транзакції'!$B$5:$B$3623,A10,'📋 Транзакції'!$C$5:$C$3623,">="&EDATE(DATEVALUE(C10&"-01"),7),'📋 Транзакції'!$C$5:$C$3623,"<"&EDATE(DATEVALUE(C10&"-01"),8)) -> 0 | AA10: =SUMIFS('📋 Транзакції'!$F$5:$F$3623,'📋 Транзакції'!$B$5:$B$3623,A10,'📋 Транзакції'!$C$5:$C$3623,">="&EDATE(DATEVALUE(C10&"-01"),8),'📋 Транзакції'!$C$5:$C$3623,"<"&EDATE(DATEVALUE(C10&"-01"),9)) -> 0 | AB10: =SUMIFS('📋 Транзакції'!$F$5:$F$3623,'📋 Транзакції'!$B$5:$B$3623,A10,'📋 Транзакції'!$C$5:$C$3623,">="&EDATE(DATEVALUE(C10&"-01"),9),'📋 Транзакції'!$C$5:$C$3623,"<"&EDATE(DATEVALUE(C10&"-01"),10)) -> 0 | AC10: =SUMIFS('📋 Транзакції'!$F$5:$F$3623,'📋 Транзакції'!$B$5:$B$3623,A10,'📋 Транзакції'!$C$5:$C$3623,">="&EDATE(DATEVALUE(C10&"-01"),10),'📋 Транзакції'!$C$5:$C$3623,"<"&EDATE(DATEVALUE(C10&"-01"),11)) -> 0 | AD10: =SUMIFS('📋 Транзакції'!$F$5:$F$3623,'📋 Транзакції'!$B$5:$B$3623,A10,'📋 Транзакції'!$C$5:$C$3623,">="&EDATE(DATEVALUE(C10&"-01"),11),'📋 Транзакції'!$C$5:$C$3623,"<"&EDATE(DATEVALUE(C10&"-01"),12)) -> 0
A11: ='📋 Реєстрації'!A11:A612 -> U0883 | B11: {=INDEX('📋 Транзакції'!$C$5:$C$3623,MATCH(A11,'📋 Транзакції'!$B$5:$B$3623,0))} -> 45294 | C11: =TEXT(B11,"YYYY-MM") -> 2024-01 | D11: =COUNTIF('📋 Транзакції'!$B$5:$B$3623,A11) -> 16 | E11: =SUMIF('📋 Транзакції'!$B$5:$B$3623,A11,'📋 Транзакції'!$F$5:$F$3623) -> 299.85 | F11: =INT($A$1-MAXIFS('📋 Транзакції'!$C$5:$C$3623,'📋 Транзакції'!$B$5:$B$3623,A11)) -> 26 | G11: =IF(COUNTIFS('📋 Транзакції'!$B$5:$B$3623,A11,'📋 Транзакції'!$C$5:$C$3623,">="&EDATE(DATEVALUE(C11&"-01"),0),'📋 Транзакції'!$C$5:$C$3623,"<"&EDATE(DATEVALUE(C11&"-01"),1))>0,1,0) -> 1 | H11: =IF(COUNTIFS('📋 Транзакції'!$B$5:$B$3623,A11,'📋 Транзакції'!$C$5:$C$3623,">="&EDATE(DATEVALUE(C11&"-01"),1),'📋 Транзакції'!$C$5:$C$3623,"<"&EDATE(DATEVALUE(C11&"-01"),2))>0,1,0) -> 1 | I11: =IF(COUNTIFS('📋 Транзакції'!$B$5:$B$3623,A11,'📋 Транзакції'!$C$5:$C$3623,">="&EDATE(DATEVALUE(C11&"-01"),2),'📋 Транзакції'!$C$5:$C$3623,"<"&EDATE(DATEVALUE(C11&"-01"),3))>0,1,0) -> 1 | J11: =IF(COUNTIFS('📋 Транзакції'!$B$5:$B$3623,A11,'📋 Транзакції'!$C$5:$C$3623,">="&EDATE(DATEVALUE(C11&"-01"),3),'📋 Транзакції'!$C$5:$C$3623,"<"&EDATE(DATEVALUE(C11&"-01"),4))>0,1,0) -> 1 | K11: =IF(COUNTIFS('📋 Транзакції'!$B$5:$B$3623,A11,'📋 Транзакції'!$C$5:$C$3623,">="&EDATE(DATEVALUE(C11&"-01"),4),'📋 Транзакції'!$C$5:$C$3623,"<"&EDATE(DATEVALUE(C11&"-01"),5))>0,1,0) -> 1 | L11: =IF(COUNTIFS('📋 Транзакції'!$B$5:$B$3623,A11,'📋 Транзакції'!$C$5:$C$3623,">="&EDATE(DATEVALUE(C11&"-01"),5),'📋 Транзакції'!$C$5:$C$3623,"<"&EDATE(DATEVALUE(C11&"-01"),6))>0,1,0) -> 1 | M11: =IF(COUNTIFS('📋 Транзакції'!$B$5:$B$3623,A11,'📋 Транзакції'!$C$5:$C$3623,">="&EDATE(DATEVALUE(C11&"-01"),6),'📋 Транзакції'!$C$5:$C$3623,"<"&EDATE(DATEVALUE(C11&"-01"),7))>0,1,0) -> 1 | N11: =IF(COUNTIFS('📋 Транзакції'!$B$5:$B$3623,A11,'📋 Транзакції'!$C$5:$C$3623,">="&EDATE(DATEVALUE(C11&"-01"),7),'📋 Транзакції'!$C$5:$C$3623,"<"&EDATE(DATEVALUE(C11&"-01"),8))>0,1,0) -> 1 | O11: =IF(COUNTIFS('📋 Транзакції'!$B$5:$B$3623,A11,'📋 Транзакції'!$C$5:$C$3623,">="&EDATE(DATEVALUE(C11&"-01"),8),'📋 Транзакції'!$C$5:$C$3623,"<"&EDATE(DATEVALUE(C11&"-01"),9))>0,1,0) -> 1 | P11: =IF(COUNTIFS('📋 Транзакції'!$B$5:$B$3623,A11,'📋 Транзакції'!$C$5:$C$3623,">="&EDATE(DATEVALUE(C11&"-01"),9),'📋 Транзакції'!$C$5:$C$3623,"<"&EDATE(DATEVALUE(C11&"-01"),10))>0,1,0) -> 1 | Q11: =IF(COUNTIFS('📋 Транзакції'!$B$5:$B$3623,A11,'📋 Транзакції'!$C$5:$C$3623,">="&EDATE(DATEVALUE(C11&"-01"),10),'📋 Транзакції'!$C$5:$C$3623,"<"&EDATE(DATEVALUE(C11&"-01"),11))>0,1,0) -> 1 | R11: =IF(COUNTIFS('📋 Транзакції'!$B$5:$B$3623,A11,'📋 Транзакції'!$C$5:$C$3623,">="&EDATE(DATEVALUE(C11&"-01"),11),'📋 Транзакції'!$C$5:$C$3623,"<"&EDATE(DATEVALUE(C11&"-01"),12))>0,1,0) -> 1 | S11: =SUMIFS('📋 Транзакції'!$F$5:$F$3623,'📋 Транзакції'!$B$5:$B$3623,A11,'📋 Транзакції'!$C$5:$C$3623,">="&EDATE(DATEVALUE(C11&"-01"),0),'📋 Транзакції'!$C$5:$C$3623,"<"&EDATE(DATEVALUE(C11&"-01"),1)) -> 19.99 | T11: =SUMIFS('📋 Транзакції'!$F$5:$F$3623,'📋 Транзакції'!$B$5:$B$3623,A11,'📋 Транзакції'!$C$5:$C$3623,">="&EDATE(DATEVALUE(C11&"-01"),1),'📋 Транзакції'!$C$5:$C$3623,"<"&EDATE(DATEVALUE(C11&"-01"),2)) -> 19.99 | U11: =SUMIFS('📋 Транзакції'!$F$5:$F$3623,'📋 Транзакції'!$B$5:$B$3623,A11,'📋 Транзакції'!$C$5:$C$3623,">="&EDATE(DATEVALUE(C11&"-01"),2),'📋 Транзакції'!$C$5:$C$3623,"<"&EDATE(DATEVALUE(C11&"-01"),3)) -> 19.99 | V11: =SUMIFS('📋 Транзакції'!$F$5:$F$3623,'📋 Транзакції'!$B$5:$B$3623,A11,'📋 Транзакції'!$C$5:$C$3623,">="&EDATE(DATEVALUE(C11&"-01"),3),'📋 Транзакції'!$C$5:$C$3623,"<"&EDATE(DATEVALUE(C11&"-01"),4)) -> 19.99 | W11: =SUMIFS('📋 Транзакції'!$F$5:$F$3623,'📋 Транзакції'!$B$5:$B$3623,A11,'📋 Транзакції'!$C$5:$C$3623,">="&EDATE(DATEVALUE(C11&"-01"),4),'📋 Транзакції'!$C$5:$C$3623,"<"&EDATE(DATEVALUE(C11&"-01"),5)) -> 19.99 | X11: =SUMIFS('📋 Транзакції'!$F$5:$F$3623,'📋 Транзакції'!$B$5:$B$3623,A11,'📋 Транзакції'!$C$5:$C$3623,">="&EDATE(DATEVALUE(C11&"-01"),5),'📋 Транзакції'!$C$5:$C$3623,"<"&EDATE(DATEVALUE(C11&"-01"),6)) -> 19.99 | Y11: =SUMIFS('📋 Транзакції'!$F$5:$F$3623,'📋 Транзакції'!$B$5:$B$3623,A11,'📋 Транзакції'!$C$5:$C$3623,">="&EDATE(DATEVALUE(C11&"-01"),6),'📋 Транзакції'!$C$5:$C$3623,"<"&EDATE(DATEVALUE(C11&"-01"),7)) -> 19.99 | Z11: =SUMIFS('📋 Транзакції'!$F$5:$F$3623,'📋 Транзакції'!$B$5:$B$3623,A11,'📋 Транзакції'!$C$5:$C$3623,">="&EDATE(DATEVALUE(C11&"-01"),7),'📋 Транзакції'!$C$5:$C$3623,"<"&EDATE(DATEVALUE(C11&"-01"),8)) -> 19.99 | AA11: =SUMIFS('📋 Транзакції'!$F$5:$F$3623,'📋 Транзакції'!$B$5:$B$3623,A11,'📋 Транзакції'!$C$5:$C$3623,">="&EDATE(DATEVALUE(C11&"-01"),8),'📋 Транзакції'!$C$5:$C$3623,"<"&EDATE(DATEVALUE(C11&"-01"),9)) -> 19.99 | AB11: =SUMIFS('📋 Транзакції'!$F$5:$F$3623,'📋 Транзакції'!$B$5:$B$3623,A11,'📋 Транзакції'!$C$5:$C$3623,">="&EDATE(DATEVALUE(C11&"-01"),9),'📋 Транзакції'!$C$5:$C$3623,"<"&EDATE(DATEVALUE(C11&"-01"),10)) -> 19.99 | AC11: =SUMIFS('📋 Транзакції'!$F$5:$F$3623,'📋 Транзакції'!$B$5:$B$3623,A11,'📋 Транзакції'!$C$5:$C$3623,">="&EDATE(DATEVALUE(C11&"-01"),10),'📋 Транзакції'!$C$5:$C$3623,"<"&EDATE(DATEVALUE(C11&"-01"),11)) -> 19.99 | AD11: =SUMIFS('📋 Транзакції'!$F$5:$F$3623,'📋 Транзакції'!$B$5:$B$3623,A11,'📋 Транзакції'!$C$5:$C$3623,">="&EDATE(DATEVALUE(C11&"-01"),11),'📋 Транзакції'!$C$5:$C$3623,"<"&EDATE(DATEVALUE(C11&"-01"),12)) -> 19.99
A12: ='📋 Реєстрації'!A12:A613 -> U0333 | B12: {=INDEX('📋 Транзакції'!$C$5:$C$3623,MATCH(A12,'📋 Транзакції'!$B$5:$B$3623,0))} -> 45295 | C12: =TEXT(B12,"YYYY-MM") -> 2024-01 | D12: =COUNTIF('📋 Транзакції'!$B$5:$B$3623,A12) -> 16 | E12: =SUMIF('📋 Транзакції'!$B$5:$B$3623,A12,'📋 Транзакції'!$F$5:$F$3623) -> 299.85 | F12: =INT($A$1-MAXIFS('📋 Транзакції'!$C$5:$C$3623,'📋 Транзакції'!$B$5:$B$3623,A12)) -> 25 | G12: =IF(COUNTIFS('📋 Транзакції'!$B$5:$B$3623,A12,'📋 Транзакції'!$C$5:$C$3623,">="&EDATE(DATEVALUE(C12&"-01"),0),'📋 Транзакції'!$C$5:$C$3623,"<"&EDATE(DATEVALUE(C12&"-01"),1))>0,1,0) -> 1 | H12: =IF(COUNTIFS('📋 Транзакції'!$B$5:$B$3623,A12,'📋 Транзакції'!$C$5:$C$3623,">="&EDATE(DATEVALUE(C12&"-01"),1),'📋 Транзакції'!$C$5:$C$3623,"<"&EDATE(DATEVALUE(C12&"-01"),2))>0,1,0) -> 1 | I12: =IF(COUNTIFS('📋 Транзакції'!$B$5:$B$3623,A12,'📋 Транзакції'!$C$5:$C$3623,">="&EDATE(DATEVALUE(C12&"-01"),2),'📋 Транзакції'!$C$5:$C$3623,"<"&EDATE(DATEVALUE(C12&"-01"),3))>0,1,0) -> 1 | J12: =IF(COUNTIFS('📋 Транзакції'!$B$5:$B$3623,A12,'📋 Транзакції'!$C$5:$C$3623,">="&EDATE(DATEVALUE(C12&"-01"),3),'📋 Транзакції'!$C$5:$C$3623,"<"&EDATE(DATEVALUE(C12&"-01"),4))>0,1,0) -> 1 | K12: =IF(COUNTIFS('📋 Транзакції'!$B$5:$B$3623,A12,'📋 Транзакції'!$C$5:$C$3623,">="&EDATE(DATEVALUE(C12&"-01"),4),'📋 Транзакції'!$C$5:$C$3623,"<"&EDATE(DATEVALUE(C12&"-01"),5))>0,1,0) -> 1 | L12: =IF(COUNTIFS('📋 Транзакції'!$B$5:$B$3623,A12,'📋 Транзакції'!$C$5:$C$3623,">="&EDATE(DATEVALUE(C12&"-01"),5),'📋 Транзакції'!$C$5:$C$3623,"<"&EDATE(DATEVALUE(C12&"-01"),6))>0,1,0) -> 1 | M12: =IF(COUNTIFS('📋 Транзакції'!$B$5:$B$3623,A12,'📋 Транзакції'!$C$5:$C$3623,">="&EDATE(DATEVALUE(C12&"-01"),6),'📋 Транзакції'!$C$5:$C$3623,"<"&EDATE(DATEVALUE(C12&"-01"),7))>0,1,0) -> 1 | N12: =IF(COUNTIFS('📋 Транзакції'!$B$5:$B$3623,A12,'📋 Транзакції'!$C$5:$C$3623,">="&EDATE(DATEVALUE(C12&"-01"),7),'📋 Транзакції'!$C$5:$C$3623,"<"&EDATE(DATEVALUE(C12&"-01"),8))>0,1,0) -> 1 | O12: =IF(COUNTIFS('📋 Транзакції'!$B$5:$B$3623,A12,'📋 Транзакції'!$C$5:$C$3623,">="&EDATE(DATEVALUE(C12&"-01"),8),'📋 Транзакції'!$C$5:$C$3623,"<"&EDATE(DATEVALUE(C12&"-01"),9))>0,1,0) -> 1 | P12: =IF(COUNTIFS('📋 Транзакції'!$B$5:$B$3623,A12,'📋 Транзакції'!$C$5:$C$3623,">="&EDATE(DATEVALUE(C12&"-01"),9),'📋 Транзакції'!$C$5:$C$3623,"<"&EDATE(DATEVALUE(C12&"-01"),10))>0,1,0) -> 1 | Q12: =IF(COUNTIFS('📋 Транзакції'!$B$5:$B$3623,A12,'📋 Транзакції'!$C$5:$C$3623,">="&EDATE(DATEVALUE(C12&"-01"),10),'📋 Транзакції'!$C$5:$C$3623,"<"&EDATE(DATEVALUE(C12&"-01"),11))>0,1,0) -> 1 | R12: =IF(COUNTIFS('📋 Транзакції'!$B$5:$B$3623,A12,'📋 Транзакції'!$C$5:$C$3623,">="&EDATE(DATEVALUE(C12&"-01"),11),'📋 Транзакції'!$C$5:$C$3623,"<"&EDATE(DATEVALUE(C12&"-01"),12))>0,1,0) -> 1 | S12: =SUMIFS('📋 Транзакції'!$F$5:$F$3623,'📋 Транзакції'!$B$5:$B$3623,A12,'📋 Транзакції'!$C$5:$C$3623,">="&EDATE(DATEVALUE(C12&"-01"),0),'📋 Транзакції'!$C$5:$C$3623,"<"&EDATE(DATEVALUE(C12&"-01"),1)) -> 19.99 | T12: =SUMIFS('📋 Транзакції'!$F$5:$F$3623,'📋 Транзакції'!$B$5:$B$3623,A12,'📋 Транзакції'!$C$5:$C$3623,">="&EDATE(DATEVALUE(C12&"-01"),1),'📋 Транзакції'!$C$5:$C$3623,"<"&EDATE(DATEVALUE(C12&"-01"),2)) -> 19.99 | U12: =SUMIFS('📋 Транзакції'!$F$5:$F$3623,'📋 Транзакції'!$B$5:$B$3623,A12,'📋 Транзакції'!$C$5:$C$3623,">="&EDATE(DATEVALUE(C12&"-01"),2),'📋 Транзакції'!$C$5:$C$3623,"<"&EDATE(DATEVALUE(C12&"-01"),3)) -> 19.99 | V12: =SUMIFS('📋 Транзакції'!$F$5:$F$3623,'📋 Транзакції'!$B$5:$B$3623,A12,'📋 Транзакції'!$C$5:$C$3623,">="&EDATE(DATEVALUE(C12&"-01"),3),'📋 Транзакції'!$C$5:$C$3623,"<"&EDATE(DATEVALUE(C12&"-01"),4)) -> 19.99 | W12: =SUMIFS('📋 Транзакції'!$F$5:$F$3623,'📋 Транзакції'!$B$5:$B$3623,A12,'📋 Транзакції'!$C$5:$C$3623,">="&EDATE(DATEVALUE(C12&"-01"),4),'📋 Транзакції'!$C$5:$C$3623,"<"&EDATE(DATEVALUE(C12&"-01"),5)) -> 19.99 | X12: =SUMIFS('📋 Транзакції'!$F$5:$F$3623,'📋 Транзакції'!$B$5:$B$3623,A12,'📋 Транзакції'!$C$5:$C$3623,">="&EDATE(DATEVALUE(C12&"-01"),5),'📋 Транзакції'!$C$5:$C$3623,"<"&EDATE(DATEVALUE(C12&"-01"),6)) -> 19.99 | Y12: =SUMIFS('📋 Транзакції'!$F$5:$F$3623,'📋 Транзакції'!$B$5:$B$3623,A12,'📋 Транзакції'!$C$5:$C$3623,">="&EDATE(DATEVALUE(C12&"-01"),6),'📋 Транзакції'!$C$5:$C$3623,"<"&EDATE(DATEVALUE(C12&"-01"),7)) -> 19.99 | Z12: =SUMIFS('📋 Транзакції'!$F$5:$F$3623,'📋 Транзакції'!$B$5:$B$3623,A12,'📋 Транзакції'!$C$5:$C$3623,">="&EDATE(DATEVALUE(C12&"-01"),7),'📋 Транзакції'!$C$5:$C$3623,"<"&EDATE(DATEVALUE(C12&"-01"),8)) -> 19.99 | AA12: =SUMIFS('📋 Транзакції'!$F$5:$F$3623,'📋 Транзакції'!$B$5:$B$3623,A12,'📋 Транзакції'!$C$5:$C$3623,">="&EDATE(DATEVALUE(C12&"-01"),8),'📋 Транзакції'!$C$5:$C$3623,"<"&EDATE(DATEVALUE(C12&"-01"),9)) -> 19.99 | AB12: =SUMIFS('📋 Транзакції'!$F$5:$F$3623,'📋 Транзакції'!$B$5:$B$3623,A12,'📋 Транзакції'!$C$5:$C$3623,">="&EDATE(DATEVALUE(C12&"-01"),9),'📋 Транзакції'!$C$5:$C$3623,"<"&EDATE(DATEVALUE(C12&"-01"),10)) -> 19.99 | AC12: =SUMIFS('📋 Транзакції'!$F$5:$F$3623,'📋 Транзакції'!$B$5:$B$3623,A12,'📋 Транзакції'!$C$5:$C$3623,">="&EDATE(DATEVALUE(C12&"-01"),10),'📋 Транзакції'!$C$5:$C$3623,"<"&EDATE(DATEVALUE(C12&"-01"),11)) -> 19.99 | AD12: =SUMIFS('📋 Транзакції'!$F$5:$F$3623,'📋 Транзакції'!$B$5:$B$3623,A12,'📋 Транзакції'!$C$5:$C$3623,">="&EDATE(DATEVALUE(C12&"-01"),11),'📋 Транзакції'!$C$5:$C$3623,"<"&EDATE(DATEVALUE(C12&"-01"),12)) -> 19.99
A13: ='📋 Реєстрації'!A13:A614 -> U0172 | B13: {=INDEX('📋 Транзакції'!$C$5:$C$3623,MATCH(A13,'📋 Транзакції'!$B$5:$B$3623,0))} -> 45300 | C13: =TEXT(B13,"YYYY-MM") -> 2024-01 | D13: =COUNTIF('📋 Транзакції'!$B$5:$B$3623,A13) -> 10 | E13: =SUMIF('📋 Транзакції'!$B$5:$B$3623,A13,'📋 Транзакції'!$F$5:$F$3623) -> 179.91 | F13: =INT($A$1-MAXIFS('📋 Транзакції'!$C$5:$C$3623,'📋 Транзакції'!$B$5:$B$3623,A13)) -> 200 | G13: =IF(COUNTIFS('📋 Транзакції'!$B$5:$B$3623,A13,'📋 Транзакції'!$C$5:$C$3623,">="&EDATE(DATEVALUE(C13&"-01"),0),'📋 Транзакції'!$C$5:$C$3623,"<"&EDATE(DATEVALUE(C13&"-01"),1))>0,1,0) -> 1 | H13: =IF(COUNTIFS('📋 Транзакції'!$B$5:$B$3623,A13,'📋 Транзакції'!$C$5:$C$3623,">="&EDATE(DATEVALUE(C13&"-01"),1),'📋 Транзакції'!$C$5:$C$3623,"<"&EDATE(DATEVALUE(C13&"-01"),2))>0,1,0) -> 1 | I13: =IF(COUNTIFS('📋 Транзакції'!$B$5:$B$3623,A13,'📋 Транзакції'!$C$5:$C$3623,">="&EDATE(DATEVALUE(C13&"-01"),2),'📋 Транзакції'!$C$5:$C$3623,"<"&EDATE(DATEVALUE(C13&"-01"),3))>0,1,0) -> 1 | J13: =IF(COUNTIFS('📋 Транзакції'!$B$5:$B$3623,A13,'📋 Транзакції'!$C$5:$C$3623,">="&EDATE(DATEVALUE(C13&"-01"),3),'📋 Транзакції'!$C$5:$C$3623,"<"&EDATE(DATEVALUE(C13&"-01"),4))>0,1,0) -> 1 | K13: =IF(COUNTIFS('📋 Транзакції'!$B$5:$B$3623,A13,'📋 Транзакції'!$C$5:$C$3623,">="&EDATE(DATEVALUE(C13&"-01"),4),'📋 Транзакції'!$C$5:$C$3623,"<"&EDATE(DATEVALUE(C13&"-01"),5))>0,1,0) -> 1 | L13: =IF(COUNTIFS('📋 Транзакції'!$B$5:$B$3623,A13,'📋 Транзакції'!$C$5:$C$3623,">="&EDATE(DATEVALUE(C13&"-01"),5),'📋 Транзакції'!$C$5:$C$3623,"<"&EDATE(DATEVALUE(C13&"-01"),6))>0,1,0) -> 1 | M13: =IF(COUNTIFS('📋 Транзакції'!$B$5:$B$3623,A13,'📋 Транзакції'!$C$5:$C$3623,">="&EDATE(DATEVALUE(C13&"-01"),6),'📋 Транзакції'!$C$5:$C$3623,"<"&EDATE(DATEVALUE(C13&"-01"),7))>0,1,0) -> 1 | N13: =IF(COUNTIFS('📋 Транзакції'!$B$5:$B$3623,A13,'📋 Транзакції'!$C$5:$C$3623,">="&EDATE(DATEVALUE(C13&"-01"),7),'📋 Транзакції'!$C$5:$C$3623,"<"&EDATE(DATEVALUE(C13&"-01"),8))>0,1,0) -> 1 | O13: =IF(COUNTIFS('📋 Транзакції'!$B$5:$B$3623,A13,'📋 Транзакції'!$C$5:$C$3623,">="&EDATE(DATEVALUE(C13&"-01"),8),'📋 Транзакції'!$C$5:$C$3623,"<"&EDATE(DATEVALUE(C13&"-01"),9))>0,1,0) -> 1 | P13: =IF(COUNTIFS('📋 Транзакції'!$B$5:$B$3623,A13,'📋 Транзакції'!$C$5:$C$3623,">="&EDATE(DATEVALUE(C13&"-01"),9),'📋 Транзакції'!$C$5:$C$3623,"<"&EDATE(DATEVALUE(C13&"-01"),10))>0,1,0) -> 0 | Q13: =IF(COUNTIFS('📋 Транзакції'!$B$5:$B$3623,A13,'📋 Транзакції'!$C$5:$C$3623,">="&EDATE(DATEVALUE(C13&"-01"),10),'📋 Транзакції'!$C$5:$C$3623,"<"&EDATE(DATEVALUE(C13&"-01"),11))>0,1,0) -> 0 | R13: =IF(COUNTIFS('📋 Транзакції'!$B$5:$B$3623,A13,'📋 Транзакції'!$C$5:$C$3623,">="&EDATE(DATEVALUE(C13&"-01"),11),'📋 Транзакції'!$C$5:$C$3623,"<"&EDATE(DATEVALUE(C13&"-01"),12))>0,1,0) -> 0 | S13: =SUMIFS('📋 Транзакції'!$F$5:$F$3623,'📋 Транзакції'!$B$5:$B$3623,A13,'📋 Транзакції'!$C$5:$C$3623,">="&EDATE(DATEVALUE(C13&"-01"),0),'📋 Транзакції'!$C$5:$C$3623,"<"&EDATE(DATEVALUE(C13&"-01"),1)) -> 19.99 | T13: =SUMIFS('📋 Транзакції'!$F$5:$F$3623,'📋 Транзакції'!$B$5:$B$3623,A13,'📋 Транзакції'!$C$5:$C$3623,">="&EDATE(DATEVALUE(C13&"-01"),1),'📋 Транзакції'!$C$5:$C$3623,"<"&EDATE(DATEVALUE(C13&"-01"),2)) -> 19.99 | U13: =SUMIFS('📋 Транзакції'!$F$5:$F$3623,'📋 Транзакції'!$B$5:$B$3623,A13,'📋 Транзакції'!$C$5:$C$3623,">="&EDATE(DATEVALUE(C13&"-01"),2),'📋 Транзакції'!$C$5:$C$3623,"<"&EDATE(DATEVALUE(C13&"-01"),3)) -> 19.99 | V13: =SUMIFS('📋 Транзакції'!$F$5:$F$3623,'📋 Транзакції'!$B$5:$B$3623,A13,'📋 Транзакції'!$C$5:$C$3623,">="&EDATE(DATEVALUE(C13&"-01"),3),'📋 Транзакції'!$C$5:$C$3623,"<"&EDATE(DATEVALUE(C13&"-01"),4)) -> 19.99 | W13: =SUMIFS('📋 Транзакції'!$F$5:$F$3623,'📋 Транзакції'!$B$5:$B$3623,A13,'📋 Транзакції'!$C$5:$C$3623,">="&EDATE(DATEVALUE(C13&"-01"),4),'📋 Транзакції'!$C$5:$C$3623,"<"&EDATE(DATEVALUE(C13&"-01"),5)) -> 19.99 | X13: =SUMIFS('📋 Транзакції'!$F$5:$F$3623,'📋 Транзакції'!$B$5:$B$3623,A13,'📋 Транзакції'!$C$5:$C$3623,">="&EDATE(DATEVALUE(C13&"-01"),5),'📋 Транзакції'!$C$5:$C$3623,"<"&EDATE(DATEVALUE(C13&"-01"),6)) -> 19.99 | Y13: =SUMIFS('📋 Транзакції'!$F$5:$F$3623,'📋 Транзакції'!$B$5:$B$3623,A13,'📋 Транзакції'!$C$5:$C$3623,">="&EDATE(DATEVALUE(C13&"-01"),6),'📋 Транзакції'!$C$5:$C$3623,"<"&EDATE(DATEVALUE(C13&"-01"),7)) -> 19.99 | Z13: =SUMIFS('📋 Транзакції'!$F$5:$F$3623,'📋 Транзакції'!$B$5:$B$3623,A13,'📋 Транзакції'!$C$5:$C$3623,">="&EDATE(DATEVALUE(C13&"-01"),7),'📋 Транзакції'!$C$5:$C$3623,"<"&EDATE(DATEVALUE(C13&"-01"),8)) -> 19.99 | AA13: =SUMIFS('📋 Транзакції'!$F$5:$F$3623,'📋 Транзакції'!$B$5:$B$3623,A13,'📋 Транзакції'!$C$5:$C$3623,">="&EDATE(DATEVALUE(C13&"-01"),8),'📋 Транзакції'!$C$5:$C$3623,"<"&EDATE(DATEVALUE(C13&"-01"),9)) -> 19.99 | AB13: =SUMIFS('📋 Транзакції'!$F$5:$F$3623,'📋 Транзакції'!$B$5:$B$3623,A13,'📋 Транзакції'!$C$5:$C$3623,">="&EDATE(DATEVALUE(C13&"-01"),9),'📋 Транзакції'!$C$5:$C$3623,"<"&EDATE(DATEVALUE(C13&"-01"),10)) -> 0 | AC13: =SUMIFS('📋 Транзакції'!$F$5:$F$3623,'📋 Транзакції'!$B$5:$B$3623,A13,'📋 Транзакції'!$C$5:$C$3623,">="&EDATE(DATEVALUE(C13&"-01"),10),'📋 Транзакції'!$C$5:$C$3623,"<"&EDATE(DATEVALUE(C13&"-01"),11)) -> 0 | AD13: =SUMIFS('📋 Транзакції'!$F$5:$F$3623,'📋 Транзакції'!$B$5:$B$3623,A13,'📋 Транзакції'!$C$5:$C$3623,">="&EDATE(DATEVALUE(C13&"-01"),11),'📋 Транзакції'!$C$5:$C$3623,"<"&EDATE(DATEVALUE(C13&"-01"),12)) -> 0
A14: ='📋 Реєстрації'!A14:A615 -> U0641 | B14: {=INDEX('📋 Транзакції'!$C$5:$C$3623,MATCH(A14,'📋 Транзакції'!$B$5:$B$3623,0))} -> 45300 | C14: =TEXT(B14,"YYYY-MM") -> 2024-01 | D14: =COUNTIF('📋 Транзакції'!$B$5:$B$3623,A14) -> 16 | E14: =SUMIF('📋 Транзакції'!$B$5:$B$3623,A14,'📋 Транзакції'!$F$5:$F$3623) -> 299.85 | F14: =INT($A$1-MAXIFS('📋 Транзакції'!$C$5:$C$3623,'📋 Транзакції'!$B$5:$B$3623,A14)) -> 20 | G14: =IF(COUNTIFS('📋 Транзакції'!$B$5:$B$3623,A14,'📋 Транзакції'!$C$5:$C$3623,">="&EDATE(DATEVALUE(C14&"-01"),0),'📋 Транзакції'!$C$5:$C$3623,"<"&EDATE(DATEVALUE(C14&"-01"),1))>0,1,0) -> 1 | H14: =IF(COUNTIFS('📋 Транзакції'!$B$5:$B$3623,A14,'📋 Транзакції'!$C$5:$C$3623,">="&EDATE(DATEVALUE(C14&"-01"),1),'📋 Транзакції'!$C$5:$C$3623,"<"&EDATE(DATEVALUE(C14&"-01"),2))>0,1,0) -> 1 | I14: =IF(COUNTIFS('📋 Транзакції'!$B$5:$B$3623,A14,'📋 Транзакції'!$C$5:$C$3623,">="&EDATE(DATEVALUE(C14&"-01"),2),'📋 Транзакції'!$C$5:$C$3623,"<"&EDATE(DATEVALUE(C14&"-01"),3))>0,1,0) -> 1 | J14: =IF(COUNTIFS('📋 Транзакції'!$B$5:$B$3623,A14,'📋 Транзакції'!$C$5:$C$3623,">="&EDATE(DATEVALUE(C14&"-01"),3),'📋 Транзакції'!$C$5:$C$3623,"<"&EDATE(DATEVALUE(C14&"-01"),4))>0,1,0) -> 1 | K14: =IF(COUNTIFS('📋 Транзакції'!$B$5:$B$3623,A14,'📋 Транзакції'!$C$5:$C$3623,">="&EDATE(DATEVALUE(C14&"-01"),4),'📋 Транзакції'!$C$5:$C$3623,"<"&EDATE(DATEVALUE(C14&"-01"),5))>0,1,0) -> 1 | L14: =IF(COUNTIFS('📋 Транзакції'!$B$5:$B$3623,A14,'📋 Транзакції'!$C$5:$C$3623,">="&EDATE(DATEVALUE(C14&"-01"),5),'📋 Транзакції'!$C$5:$C$3623,"<"&EDATE(DATEVALUE(C14&"-01"),6))>0,1,0) -> 1 | M14: =IF(COUNTIFS('📋 Транзакції'!$B$5:$B$3623,A14,'📋 Транзакції'!$C$5:$C$3623,">="&EDATE(DATEVALUE(C14&"-01"),6),'📋 Транзакції'!$C$5:$C$3623,"<"&EDATE(DATEVALUE(C14&"-01"),7))>0,1,0) -> 1 | N14: =IF(COUNTIFS('📋 Транзакції'!$B$5:$B$3623,A14,'📋 Транзакції'!$C$5:$C$3623,">="&EDATE(DATEVALUE(C14&"-01"),7),'📋 Транзакції'!$C$5:$C$3623,"<"&EDATE(DATEVALUE(C14&"-01"),8))>0,1,0) -> 1 | O14: =IF(COUNTIFS('📋 Транзакції'!$B$5:$B$3623,A14,'📋 Транзакції'!$C$5:$C$3623,">="&EDATE(DATEVALUE(C14&"-01"),8),'📋 Транзакції'!$C$5:$C$3623,"<"&EDATE(DATEVALUE(C14&"-01"),9))>0,1,0) -> 1 | P14: =IF(COUNTIFS('📋 Транзакції'!$B$5:$B$3623,A14,'📋 Транзакції'!$C$5:$C$3623,">="&EDATE(DATEVALUE(C14&"-01"),9),'📋 Транзакції'!$C$5:$C$3623,"<"&EDATE(DATEVALUE(C14&"-01"),10))>0,1,0) -> 1 | Q14: =IF(COUNTIFS('📋 Транзакції'!$B$5:$B$3623,A14,'📋 Транзакції'!$C$5:$C$3623,">="&EDATE(DATEVALUE(C14&"-01"),10),'📋 Транзакції'!$C$5:$C$3623,"<"&EDATE(DATEVALUE(C14&"-01"),11))>0,1,0) -> 1 | R14: =IF(COUNTIFS('📋 Транзакції'!$B$5:$B$3623,A14,'📋 Транзакції'!$C$5:$C$3623,">="&EDATE(DATEVALUE(C14&"-01"),11),'📋 Транзакції'!$C$5:$C$3623,"<"&EDATE(DATEVALUE(C14&"-01"),12))>0,1,0) -> 1 | S14: =SUMIFS('📋 Транзакції'!$F$5:$F$3623,'📋 Транзакції'!$B$5:$B$3623,A14,'📋 Транзакції'!$C$5:$C$3623,">="&EDATE(DATEVALUE(C14&"-01"),0),'📋 Транзакції'!$C$5:$C$3623,"<"&EDATE(DATEVALUE(C14&"-01"),1)) -> 19.99 | T14: =SUMIFS('📋 Транзакції'!$F$5:$F$3623,'📋 Транзакції'!$B$5:$B$3623,A14,'📋 Транзакції'!$C$5:$C$3623,">="&EDATE(DATEVALUE(C14&"-01"),1),'📋 Транзакції'!$C$5:$C$3623,"<"&EDATE(DATEVALUE(C14&"-01"),2)) -> 19.99 | U14: =SUMIFS('📋 Транзакції'!$F$5:$F$3623,'📋 Транзакції'!$B$5:$B$3623,A14,'📋 Транзакції'!$C$5:$C$3623,">="&EDATE(DATEVALUE(C14&"-01"),2),'📋 Транзакції'!$C$5:$C$3623,"<"&EDATE(DATEVALUE(C14&"-01"),3)) -> 19.99 | V14: =SUMIFS('📋 Транзакції'!$F$5:$F$3623,'📋 Транзакції'!$B$5:$B$3623,A14,'📋 Транзакції'!$C$5:$C$3623,">="&EDATE(DATEVALUE(C14&"-01"),3),'📋 Транзакції'!$C$5:$C$3623,"<"&EDATE(DATEVALUE(C14&"-01"),4)) -> 19.99 | W14: =SUMIFS('📋 Транзакції'!$F$5:$F$3623,'📋 Транзакції'!$B$5:$B$3623,A14,'📋 Транзакції'!$C$5:$C$3623,">="&EDATE(DATEVALUE(C14&"-01"),4),'📋 Транзакції'!$C$5:$C$3623,"<"&EDATE(DATEVALUE(C14&"-01"),5)) -> 19.99 | X14: =SUMIFS('📋 Транзакції'!$F$5:$F$3623,'📋 Транзакції'!$B$5:$B$3623,A14,'📋 Транзакції'!$C$5:$C$3623,">="&EDATE(DATEVALUE(C14&"-01"),5),'📋 Транзакції'!$C$5:$C$3623,"<"&EDATE(DATEVALUE(C14&"-01"),6)) -> 19.99 | Y14: =SUMIFS('📋 Транзакції'!$F$5:$F$3623,'📋 Транзакції'!$B$5:$B$3623,A14,'📋 Транзакції'!$C$5:$C$3623,">="&EDATE(DATEVALUE(C14&"-01"),6),'📋 Транзакції'!$C$5:$C$3623,"<"&EDATE(DATEVALUE(C14&"-01"),7)) -> 19.99 | Z14: =SUMIFS('📋 Транзакції'!$F$5:$F$3623,'📋 Транзакції'!$B$5:$B$3623,A14,'📋 Транзакції'!$C$5:$C$3623,">="&EDATE(DATEVALUE(C14&"-01"),7),'📋 Транзакції'!$C$5:$C$3623,"<"&EDATE(DATEVALUE(C14&"-01"),8)) -> 19.99 | AA14: =SUMIFS('📋 Транзакції'!$F$5:$F$3623,'📋 Транзакції'!$B$5:$B$3623,A14,'📋 Транзакції'!$C$5:$C$3623,">="&EDATE(DATEVALUE(C14&"-01"),8),'📋 Транзакції'!$C$5:$C$3623,"<"&EDATE(DATEVALUE(C14&"-01"),9)) -> 19.99 | AB14: =SUMIFS('📋 Транзакції'!$F$5:$F$3623,'📋 Транзакції'!$B$5:$B$3623,A14,'📋 Транзакції'!$C$5:$C$3623,">="&EDATE(DATEVALUE(C14&"-01"),9),'📋 Транзакції'!$C$5:$C$3623,"<"&EDATE(DATEVALUE(C14&"-01"),10)) -> 19.99 | AC14: =SUMIFS('📋 Транзакції'!$F$5:$F$3623,'📋 Транзакції'!$B$5:$B$3623,A14,'📋 Транзакції'!$C$5:$C$3623,">="&EDATE(DATEVALUE(C14&"-01"),10),'📋 Транзакції'!$C$5:$C$3623,"<"&EDATE(DATEVALUE(C14&"-01"),11)) -> 19.99 | AD14: =SUMIFS('📋 Транзакції'!$F$5:$F$3623,'📋 Транзакції'!$B$5:$B$3623,A14,'📋 Транзакції'!$C$5:$C$3623,">="&EDATE(DATEVALUE(C14&"-01"),11),'📋 Транзакції'!$C$5:$C$3623,"<"&EDATE(DATEVALUE(C14&"-01"),12)) -> 19.99
A15: ='📋 Реєстрації'!A15:A616 -> U0879 | B15: {=INDEX('📋 Транзакції'!$C$5:$C$3623,MATCH(A15,'📋 Транзакції'!$B$5:$B$3623,0))} -> 45300 | C15: =TEXT(B15,"YYYY-MM") -> 2024-01 | D15: =COUNTIF('📋 Транзакції'!$B$5:$B$3623,A15) -> 16 | E15: =SUMIF('📋 Транзакції'!$B$5:$B$3623,A15,'📋 Транзакції'!$F$5:$F$3623) -> 299.85 | F15: =INT($A$1-MAXIFS('📋 Транзакції'!$C$5:$C$3623,'📋 Транзакції'!$B$5:$B$3623,A15)) -> 20 | G15: =IF(COUNTIFS('📋 Транзакції'!$B$5:$B$3623,A15,'📋 Транзакції'!$C$5:$C$3623,">="&EDATE(DATEVALUE(C15&"-01"),0),'📋 Транзакції'!$C$5:$C$3623,"<"&EDATE(DATEVALUE(C15&"-01"),1))>0,1,0) -> 1 | H15: =IF(COUNTIFS('📋 Транзакції'!$B$5:$B$3623,A15,'📋 Транзакції'!$C$5:$C$3623,">="&EDATE(DATEVALUE(C15&"-01"),1),'📋 Транзакції'!$C$5:$C$3623,"<"&EDATE(DATEVALUE(C15&"-01"),2))>0,1,0) -> 1 | I15: =IF(COUNTIFS('📋 Транзакції'!$B$5:$B$3623,A15,'📋 Транзакції'!$C$5:$C$3623,">="&EDATE(DATEVALUE(C15&"-01"),2),'📋 Транзакції'!$C$5:$C$3623,"<"&EDATE(DATEVALUE(C15&"-01"),3))>0,1,0) -> 1 | J15: =IF(COUNTIFS('📋 Транзакції'!$B$5:$B$3623,A15,'📋 Транзакції'!$C$5:$C$3623,">="&EDATE(DATEVALUE(C15&"-01"),3),'📋 Транзакції'!$C$5:$C$3623,"<"&EDATE(DATEVALUE(C15&"-01"),4))>0,1,0) -> 1 | K15: =IF(COUNTIFS('📋 Транзакції'!$B$5:$B$3623,A15,'📋 Транзакції'!$C$5:$C$3623,">="&EDATE(DATEVALUE(C15&"-01"),4),'📋 Транзакції'!$C$5:$C$3623,"<"&EDATE(DATEVALUE(C15&"-01"),5))>0,1,0) -> 1 | L15: =IF(COUNTIFS('📋 Транзакції'!$B$5:$B$3623,A15,'📋 Транзакції'!$C$5:$C$3623,">="&EDATE(DATEVALUE(C15&"-01"),5),'📋 Транзакції'!$C$5:$C$3623,"<"&EDATE(DATEVALUE(C15&"-01"),6))>0,1,0) -> 1 | M15: =IF(COUNTIFS('📋 Транзакції'!$B$5:$B$3623,A15,'📋 Транзакції'!$C$5:$C$3623,">="&EDATE(DATEVALUE(C15&"-01"),6),'📋 Транзакції'!$C$5:$C$3623,"<"&EDATE(DATEVALUE(C15&"-01"),7))>0,1,0) -> 1 | N15: =IF(COUNTIFS('📋 Транзакції'!$B$5:$B$3623,A15,'📋 Транзакції'!$C$5:$C$3623,">="&EDATE(DATEVALUE(C15&"-01"),7),'📋 Транзакції'!$C$5:$C$3623,"<"&EDATE(DATEVALUE(C15&"-01"),8))>0,1,0) -> 1 | O15: =IF(COUNTIFS('📋 Транзакції'!$B$5:$B$3623,A15,'📋 Транзакції'!$C$5:$C$3623,">="&EDATE(DATEVALUE(C15&"-01"),8),'📋 Транзакції'!$C$5:$C$3623,"<"&EDATE(DATEVALUE(C15&"-01"),9))>0,1,0) -> 1 | P15: =IF(COUNTIFS('📋 Транзакції'!$B$5:$B$3623,A15,'📋 Транзакції'!$C$5:$C$3623,">="&EDATE(DATEVALUE(C15&"-01"),9),'📋 Транзакції'!$C$5:$C$3623,"<"&EDATE(DATEVALUE(C15&"-01"),10))>0,1,0) -> 1 | Q15: =IF(COUNTIFS('📋 Транзакції'!$B$5:$B$3623,A15,'📋 Транзакції'!$C$5:$C$3623,">="&EDATE(DATEVALUE(C15&"-01"),10),'📋 Транзакції'!$C$5:$C$3623,"<"&EDATE(DATEVALUE(C15&"-01"),11))>0,1,0) -> 1 | R15: =IF(COUNTIFS('📋 Транзакції'!$B$5:$B$3623,A15,'📋 Транзакції'!$C$5:$C$3623,">="&EDATE(DATEVALUE(C15&"-01"),11),'📋 Транзакції'!$C$5:$C$3623,"<"&EDATE(DATEVALUE(C15&"-01"),12))>0,1,0) -> 1 | S15: =SUMIFS('📋 Транзакції'!$F$5:$F$3623,'📋 Транзакції'!$B$5:$B$3623,A15,'📋 Транзакції'!$C$5:$C$3623,">="&EDATE(DATEVALUE(C15&"-01"),0),'📋 Транзакції'!$C$5:$C$3623,"<"&EDATE(DATEVALUE(C15&"-01"),1)) -> 19.99 | T15: =SUMIFS('📋 Транзакції'!$F$5:$F$3623,'📋 Транзакції'!$B$5:$B$3623,A15,'📋 Транзакції'!$C$5:$C$3623,">="&EDATE(DATEVALUE(C15&"-01"),1),'📋 Транзакції'!$C$5:$C$3623,"<"&EDATE(DATEVALUE(C15&"-01"),2)) -> 19.99 | U15: =SUMIFS('📋 Транзакції'!$F$5:$F$3623,'📋 Транзакції'!$B$5:$B$3623,A15,'📋 Транзакції'!$C$5:$C$3623,">="&EDATE(DATEVALUE(C15&"-01"),2),'📋 Транзакції'!$C$5:$C$3623,"<"&EDATE(DATEVALUE(C15&"-01"),3)) -> 19.99 | V15: =SUMIFS('📋 Транзакції'!$F$5:$F$3623,'📋 Транзакції'!$B$5:$B$3623,A15,'📋 Транзакції'!$C$5:$C$3623,">="&EDATE(DATEVALUE(C15&"-01"),3),'📋 Транзакції'!$C$5:$C$3623,"<"&EDATE(DATEVALUE(C15&"-01"),4)) -> 19.99 | W15: =SUMIFS('📋 Транзакції'!$F$5:$F$3623,'📋 Транзакції'!$B$5:$B$3623,A15,'📋 Транзакції'!$C$5:$C$3623,">="&EDATE(DATEVALUE(C15&"-01"),4),'📋 Транзакції'!$C$5:$C$3623,"<"&EDATE(DATEVALUE(C15&"-01"),5)) -> 19.99 | X15: =SUMIFS('📋 Транзакції'!$F$5:$F$3623,'📋 Транзакції'!$B$5:$B$3623,A15,'📋 Транзакції'!$C$5:$C$3623,">="&EDATE(DATEVALUE(C15&"-01"),5),'📋 Транзакції'!$C$5:$C$3623,"<"&EDATE(DATEVALUE(C15&"-01"),6)) -> 19.99 | Y15: =SUMIFS('📋 Транзакції'!$F$5:$F$3623,'📋 Транзакції'!$B$5:$B$3623,A15,'📋 Транзакції'!$C$5:$C$3623,">="&EDATE(DATEVALUE(C15&"-01"),6),'📋 Транзакції'!$C$5:$C$3623,"<"&EDATE(DATEVALUE(C15&"-01"),7)) -> 19.99 | Z15: =SUMIFS('📋 Транзакції'!$F$5:$F$3623,'📋 Транзакції'!$B$5:$B$3623,A15,'📋 Транзакції'!$C$5:$C$3623,">="&EDATE(DATEVALUE(C15&"-01"),7),'📋 Транзакції'!$C$5:$C$3623,"<"&EDATE(DATEVALUE(C15&"-01"),8)) -> 19.99 | AA15: =SUMIFS('📋 Транзакції'!$F$5:$F$3623,'📋 Транзакції'!$B$5:$B$3623,A15,'📋 Транзакції'!$C$5:$C$3623,">="&EDATE(DATEVALUE(C15&"-01"),8),'📋 Транзакції'!$C$5:$C$3623,"<"&EDATE(DATEVALUE(C15&"-01"),9)) -> 19.99 | AB15: =SUMIFS('📋 Транзакції'!$F$5:$F$3623,'📋 Транзакції'!$B$5:$B$3623,A15,'📋 Транзакції'!$C$5:$C$3623,">="&EDATE(DATEVALUE(C15&"-01"),9),'📋 Транзакції'!$C$5:$C$3623,"<"&EDATE(DATEVALUE(C15&"-01"),10)) -> 19.99 | AC15: =SUMIFS('📋 Транзакції'!$F$5:$F$3623,'📋 Транзакції'!$B$5:$B$3623,A15,'📋 Транзакції'!$C$5:$C$3623,">="&EDATE(DATEVALUE(C15&"-01"),10),'📋 Транзакції'!$C$5:$C$3623,"<"&EDATE(DATEVALUE(C15&"-01"),11)) -> 19.99 | AD15: =SUMIFS('📋 Транзакції'!$F$5:$F$3623,'📋 Транзакції'!$B$5:$B$3623,A15,'📋 Транзакції'!$C$5:$C$3623,">="&EDATE(DATEVALUE(C15&"-01"),11),'📋 Транзакції'!$C$5:$C$3623,"<"&EDATE(DATEVALUE(C15&"-01"),12)) -> 19.99
A16: ='📋 Реєстрації'!A16:A617 -> U0238 | B16: {=INDEX('📋 Транзакції'!$C$5:$C$3623,MATCH(A16,'📋 Транзакції'!$B$5:$B$3623,0))} -> 45304 | C16: =TEXT(B16,"YYYY-MM") -> 2024-01 | D16: =COUNTIF('📋 Транзакції'!$B$5:$B$3623,A16) -> 16 | E16: =SUMIF('📋 Транзакції'!$B$5:$B$3623,A16,'📋 Транзакції'!$F$5:$F$3623) -> 299.85 | F16: =INT($A$1-MAXIFS('📋 Транзакції'!$C$5:$C$3623,'📋 Транзакції'!$B$5:$B$3623,A16)) -> 16 | G16: =IF(COUNTIFS('📋 Транзакції'!$B$5:$B$3623,A16,'📋 Транзакції'!$C$5:$C$3623,">="&EDATE(DATEVALUE(C16&"-01"),0),'📋 Транзакції'!$C$5:$C$3623,"<"&EDATE(DATEVALUE(C16&"-01"),1))>0,1,0) -> 1 | H16: =IF(COUNTIFS('📋 Транзакції'!$B$5:$B$3623,A16,'📋 Транзакції'!$C$5:$C$3623,">="&EDATE(DATEVALUE(C16&"-01"),1),'📋 Транзакції'!$C$5:$C$3623,"<"&EDATE(DATEVALUE(C16&"-01"),2))>0,1,0) -> 1 | I16: =IF(COUNTIFS('📋 Транзакції'!$B$5:$B$3623,A16,'📋 Транзакції'!$C$5:$C$3623,">="&EDATE(DATEVALUE(C16&"-01"),2),'📋 Транзакції'!$C$5:$C$3623,"<"&EDATE(DATEVALUE(C16&"-01"),3))>0,1,0) -> 1 | J16: =IF(COUNTIFS('📋 Транзакції'!$B$5:$B$3623,A16,'📋 Транзакції'!$C$5:$C$3623,">="&EDATE(DATEVALUE(C16&"-01"),3),'📋 Транзакції'!$C$5:$C$3623,"<"&EDATE(DATEVALUE(C16&"-01"),4))>0,1,0) -> 1 | K16: =IF(COUNTIFS('📋 Транзакції'!$B$5:$B$3623,A16,'📋 Транзакції'!$C$5:$C$3623,">="&EDATE(DATEVALUE(C16&"-01"),4),'📋 Транзакції'!$C$5:$C$3623,"<"&EDATE(DATEVALUE(C16&"-01"),5))>0,1,0) -> 1 | L16: =IF(COUNTIFS('📋 Транзакції'!$B$5:$B$3623,A16,'📋 Транзакції'!$C$5:$C$3623,">="&EDATE(DATEVALUE(C16&"-01"),5),'📋 Транзакції'!$C$5:$C$3623,"<"&EDATE(DATEVALUE(C16&"-01"),6))>0,1,0) -> 1 | M16: =IF(COUNTIFS('📋 Транзакції'!$B$5:$B$3623,A16,'📋 Транзакції'!$C$5:$C$3623,">="&EDATE(DATEVALUE(C16&"-01"),6),'📋 Транзакції'!$C$5:$C$3623,"<"&EDATE(DATEVALUE(C16&"-01"),7))>0,1,0) -> 1 | N16: =IF(COUNTIFS('📋 Транзакції'!$B$5:$B$3623,A16,'📋 Транзакції'!$C$5:$C$3623,">="&EDATE(DATEVALUE(C16&"-01"),7),'📋 Транзакції'!$C$5:$C$3623,"<"&EDATE(DATEVALUE(C16&"-01"),8))>0,1,0) -> 1 | O16: =IF(COUNTIFS('📋 Транзакції'!$B$5:$B$3623,A16,'📋 Транзакції'!$C$5:$C$3623,">="&EDATE(DATEVALUE(C16&"-01"),8),'📋 Транзакції'!$C$5:$C$3623,"<"&EDATE(DATEVALUE(C16&"-01"),9))>0,1,0) -> 1 | P16: =IF(COUNTIFS('📋 Транзакції'!$B$5:$B$3623,A16,'📋 Транзакції'!$C$5:$C$3623,">="&EDATE(DATEVALUE(C16&"-01"),9),'📋 Транзакції'!$C$5:$C$3623,"<"&EDATE(DATEVALUE(C16&"-01"),10))>0,1,0) -> 1 | Q16: =IF(COUNTIFS('📋 Транзакції'!$B$5:$B$3623,A16,'📋 Транзакції'!$C$5:$C$3623,">="&EDATE(DATEVALUE(C16&"-01"),10),'📋 Транзакції'!$C$5:$C$3623,"<"&EDATE(DATEVALUE(C16&"-01"),11))>0,1,0) -> 1 | R16: =IF(COUNTIFS('📋 Транзакції'!$B$5:$B$3623,A16,'📋 Транзакції'!$C$5:$C$3623,">="&EDATE(DATEVALUE(C16&"-01"),11),'📋 Транзакції'!$C$5:$C$3623,"<"&EDATE(DATEVALUE(C16&"-01"),12))>0,1,0) -> 1 | S16: =SUMIFS('📋 Транзакції'!$F$5:$F$3623,'📋 Транзакції'!$B$5:$B$3623,A16,'📋 Транзакції'!$C$5:$C$3623,">="&EDATE(DATEVALUE(C16&"-01"),0),'📋 Транзакції'!$C$5:$C$3623,"<"&EDATE(DATEVALUE(C16&"-01"),1)) -> 19.99 | T16: =SUMIFS('📋 Транзакції'!$F$5:$F$3623,'📋 Транзакції'!$B$5:$B$3623,A16,'📋 Транзакції'!$C$5:$C$3623,">="&EDATE(DATEVALUE(C16&"-01"),1),'📋 Транзакції'!$C$5:$C$3623,"<"&EDATE(DATEVALUE(C16&"-01"),2)) -> 19.99 | U16: =SUMIFS('📋 Транзакції'!$F$5:$F$3623,'📋 Транзакції'!$B$5:$B$3623,A16,'📋 Транзакції'!$C$5:$C$3623,">="&EDATE(DATEVALUE(C16&"-01"),2),'📋 Транзакції'!$C$5:$C$3623,"<"&EDATE(DATEVALUE(C16&"-01"),3)) -> 19.99 | V16: =SUMIFS('📋 Транзакції'!$F$5:$F$3623,'📋 Транзакції'!$B$5:$B$3623,A16,'📋 Транзакції'!$C$5:$C$3623,">="&EDATE(DATEVALUE(C16&"-01"),3),'📋 Транзакції'!$C$5:$C$3623,"<"&EDATE(DATEVALUE(C16&"-01"),4)) -> 19.99 | W16: =SUMIFS('📋 Транзакції'!$F$5:$F$3623,'📋 Транзакції'!$B$5:$B$3623,A16,'📋 Транзакції'!$C$5:$C$3623,">="&EDATE(DATEVALUE(C16&"-01"),4),'📋 Транзакції'!$C$5:$C$3623,"<"&EDATE(DATEVALUE(C16&"-01"),5)) -> 19.99 | X16: =SUMIFS('📋 Транзакції'!$F$5:$F$3623,'📋 Транзакції'!$B$5:$B$3623,A16,'📋 Транзакції'!$C$5:$C$3623,">="&EDATE(DATEVALUE(C16&"-01"),5),'📋 Транзакції'!$C$5:$C$3623,"<"&EDATE(DATEVALUE(C16&"-01"),6)) -> 19.99 | Y16: =SUMIFS('📋 Транзакції'!$F$5:$F$3623,'📋 Транзакції'!$B$5:$B$3623,A16,'📋 Транзакції'!$C$5:$C$3623,">="&EDATE(DATEVALUE(C16&"-01"),6),'📋 Транзакції'!$C$5:$C$3623,"<"&EDATE(DATEVALUE(C16&"-01"),7)) -> 19.99 | Z16: =SUMIFS('📋 Транзакції'!$F$5:$F$3623,'📋 Транзакції'!$B$5:$B$3623,A16,'📋 Транзакції'!$C$5:$C$3623,">="&EDATE(DATEVALUE(C16&"-01"),7),'📋 Транзакції'!$C$5:$C$3623,"<"&EDATE(DATEVALUE(C16&"-01"),8)) -> 19.99 | AA16: =SUMIFS('📋 Транзакції'!$F$5:$F$3623,'📋 Транзакції'!$B$5:$B$3623,A16,'📋 Транзакції'!$C$5:$C$3623,">="&EDATE(DATEVALUE(C16&"-01"),8),'📋 Транзакції'!$C$5:$C$3623,"<"&EDATE(DATEVALUE(C16&"-01"),9)) -> 19.99 | AB16: =SUMIFS('📋 Транзакції'!$F$5:$F$3623,'📋 Транзакції'!$B$5:$B$3623,A16,'📋 Транзакції'!$C$5:$C$3623,">="&EDATE(DATEVALUE(C16&"-01"),9),'📋 Транзакції'!$C$5:$C$3623,"<"&EDATE(DATEVALUE(C16&"-01"),10)) -> 19.99 | AC16: =SUMIFS('📋 Транзакції'!$F$5:$F$3623,'📋 Транзакції'!$B$5:$B$3623,A16,'📋 Транзакції'!$C$5:$C$3623,">="&EDATE(DATEVALUE(C16&"-01"),10),'📋 Транзакції'!$C$5:$C$3623,"<"&EDATE(DATEVALUE(C16&"-01"),11)) -> 19.99 | AD16: =SUMIFS('📋 Транзакції'!$F$5:$F$3623,'📋 Транзакції'!$B$5:$B$3623,A16,'📋 Транзакції'!$C$5:$C$3623,">="&EDATE(DATEVALUE(C16&"-01"),11),'📋 Транзакції'!$C$5:$C$3623,"<"&EDATE(DATEVALUE(C16&"-01"),12)) -> 19.99
... A606: ='📋 Реєстрації'!A606:A1207 -> U0679 | B606: {=INDEX('📋 Транзакції'!$C$5:$C$3623,MATCH(A606,'📋 Транзакції'!$B$5:$B$3623,0))} -> 45740 | C606: =TEXT(B606,"YYYY-MM") -> 2025-03 | D606: =COUNTIF('📋 Транзакції'!$B$5:$B$3623,A606) -> 2 | E606: =SUMIF('📋 Транзакції'!$B$5:$B$3623,A606,'📋 Транзакції'!$F$5:$F$3623) -> 19.99 | F606: =INT($A$1-MAXIFS('📋 Транзакції'!$C$5:$C$3623,'📋 Транзакції'!$B$5:$B$3623,A606)) -> 0 | G606: =IF(COUNTIFS('📋 Транзакції'!$B$5:$B$3623,A606,'📋 Транзакції'!$C$5:$C$3623,">="&EDATE(DATEVALUE(C606&"-01"),0),'📋 Транзакції'!$C$5:$C$3623,"<"&EDATE(DATEVALUE(C606&"-01"),1))>0,1,0) -> 1 | H606: =IF(COUNTIFS('📋 Транзакції'!$B$5:$B$3623,A606,'📋 Транзакції'!$C$5:$C$3623,">="&EDATE(DATEVALUE(C606&"-01"),1),'📋 Транзакції'!$C$5:$C$3623,"<"&EDATE(DATEVALUE(C606&"-01"),2))>0,1,0) -> 0 | I606: =IF(COUNTIFS('📋 Транзакції'!$B$5:$B$3623,A606,'📋 Транзакції'!$C$5:$C$3623,">="&EDATE(DATEVALUE(C606&"-01"),2),'📋 Транзакції'!$C$5:$C$3623,"<"&EDATE(DATEVALUE(C606&"-01"),3))>0,1,0) -> 0 | J606: =IF(COUNTIFS('📋 Транзакції'!$B$5:$B$3623,A606,'📋 Транзакції'!$C$5:$C$3623,">="&EDATE(DATEVALUE(C606&"-01"),3),'📋 Транзакції'!$C$5:$C$3623,"<"&EDATE(DATEVALUE(C606&"-01"),4))>0,1,0) -> 0 | K606: =IF(COUNTIFS('📋 Транзакції'!$B$5:$B$3623,A606,'📋 Транзакції'!$C$5:$C$3623,">="&EDATE(DATEVALUE(C606&"-01"),4),'📋 Транзакції'!$C$5:$C$3623,"<"&EDATE(DATEVALUE(C606&"-01"),5))>0,1,0) -> 0 | L606: =IF(COUNTIFS('📋 Транзакції'!$B$5:$B$3623,A606,'📋 Транзакції'!$C$5:$C$3623,">="&EDATE(DATEVALUE(C606&"-01"),5),'📋 Транзакції'!$C$5:$C$3623,"<"&EDATE(DATEVALUE(C606&"-01"),6))>0,1,0) -> 0 | M606: =IF(COUNTIFS('📋 Транзакції'!$B$5:$B$3623,A606,'📋 Транзакції'!$C$5:$C$3623,">="&EDATE(DATEVALUE(C606&"-01"),6),'📋 Транзакції'!$C$5:$C$3623,"<"&EDATE(DATEVALUE(C606&"-01"),7))>0,1,0) -> 0 | N606: =IF(COUNTIFS('📋 Транзакції'!$B$5:$B$3623,A606,'📋 Транзакції'!$C$5:$C$3623,">="&EDATE(DATEVALUE(C606&"-01"),7),'📋 Транзакції'!$C$5:$C$3623,"<"&EDATE(DATEVALUE(C606&"-01"),8))>0,1,0) -> 0 | O606: =IF(COUNTIFS('📋 Транзакції'!$B$5:$B$3623,A606,'📋 Транзакції'!$C$5:$C$3623,">="&EDATE(DATEVALUE(C606&"-01"),8),'📋 Транзакції'!$C$5:$C$3623,"<"&EDATE(DATEVALUE(C606&"-01"),9))>0,1,0) -> 0 | P606: =IF(COUNTIFS('📋 Транзакції'!$B$5:$B$3623,A606,'📋 Транзакції'!$C$5:$C$3623,">="&EDATE(DATEVALUE(C606&"-01"),9),'📋 Транзакції'!$C$5:$C$3623,"<"&EDATE(DATEVALUE(C606&"-01"),10))>0,1,0) -> 0 | Q606: =IF(COUNTIFS('📋 Транзакції'!$B$5:$B$3623,A606,'📋 Транзакції'!$C$5:$C$3623,">="&EDATE(DATEVALUE(C606&"-01"),10),'📋 Транзакції'!$C$5:$C$3623,"<"&EDATE(DATEVALUE(C606&"-01"),11))>0,1,0) -> 0 | R606: =IF(COUNTIFS('📋 Транзакції'!$B$5:$B$3623,A606,'📋 Транзакції'!$C$5:$C$3623,">="&EDATE(DATEVALUE(C606&"-01"),11),'📋 Транзакції'!$C$5:$C$3623,"<"&EDATE(DATEVALUE(C606&"-01"),12))>0,1,0) -> 0 | S606: =SUMIFS('📋 Транзакції'!$F$5:$F$3623,'📋 Транзакції'!$B$5:$B$3623,A606,'📋 Транзакції'!$C$5:$C$3623,">="&EDATE(DATEVALUE(C606&"-01"),0),'📋 Транзакції'!$C$5:$C$3623,"<"&EDATE(DATEVALUE(C606&"-01"),1)) -> 19.99 | T606: =SUMIFS('📋 Транзакції'!$F$5:$F$3623,'📋 Транзакції'!$B$5:$B$3623,A606,'📋 Транзакції'!$C$5:$C$3623,">="&EDATE(DATEVALUE(C606&"-01"),1),'📋 Транзакції'!$C$5:$C$3623,"<"&EDATE(DATEVALUE(C606&"-01"),2)) -> 0 | U606: =SUMIFS('📋 Транзакції'!$F$5:$F$3623,'📋 Транзакції'!$B$5:$B$3623,A606,'📋 Транзакції'!$C$5:$C$3623,">="&EDATE(DATEVALUE(C606&"-01"),2),'📋 Транзакції'!$C$5:$C$3623,"<"&EDATE(DATEVALUE(C606&"-01"),3)) -> 0 | V606: =SUMIFS('📋 Транзакції'!$F$5:$F$3623,'📋 Транзакції'!$B$5:$B$3623,A606,'📋 Транзакції'!$C$5:$C$3623,">="&EDATE(DATEVALUE(C606&"-01"),3),'📋 Транзакції'!$C$5:$C$3623,"<"&EDATE(DATEVALUE(C606&"-01"),4)) -> 0 | W606: =SUMIFS('📋 Транзакції'!$F$5:$F$3623,'📋 Транзакції'!$B$5:$B$3623,A606,'📋 Транзакції'!$C$5:$C$3623,">="&EDATE(DATEVALUE(C606&"-01"),4),'📋 Транзакції'!$C$5:$C$3623,"<"&EDATE(DATEVALUE(C606&"-01"),5)) -> 0 | X606: =SUMIFS('📋 Транзакції'!$F$5:$F$3623,'📋 Транзакції'!$B$5:$B$3623,A606,'📋 Транзакції'!$C$5:$C$3623,">="&EDATE(DATEVALUE(C606&"-01"),5),'📋 Транзакції'!$C$5:$C$3623,"<"&EDATE(DATEVALUE(C606&"-01"),6)) -> 0 | Y606: =SUMIFS('📋 Транзакції'!$F$5:$F$3623,'📋 Транзакції'!$B$5:$B$3623,A606,'📋 Транзакції'!$C$5:$C$3623,">="&EDATE(DATEVALUE(C606&"-01"),6),'📋 Транзакції'!$C$5:$C$3623,"<"&EDATE(DATEVALUE(C606&"-01"),7)) -> 0 | Z606: =SUMIFS('📋 Транзакції'!$F$5:$F$3623,'📋 Транзакції'!$B$5:$B$3623,A606,'📋 Транзакції'!$C$5:$C$3623,">="&EDATE(DATEVALUE(C606&"-01"),7),'📋 Транзакції'!$C$5:$C$3623,"<"&EDATE(DATEVALUE(C606&"-01"),8)) -> 0 | AA606: =SUMIFS('📋 Транзакції'!$F$5:$F$3623,'📋 Транзакції'!$B$5:$B$3623,A606,'📋 Транзакції'!$C$5:$C$3623,">="&EDATE(DATEVALUE(C606&"-01"),8),'📋 Транзакції'!$C$5:$C$3623,"<"&EDATE(DATEVALUE(C606&"-01"),9)) -> 0 | AB606: =SUMIFS('📋 Транзакції'!$F$5:$F$3623,'📋 Транзакції'!$B$5:$B$3623,A606,'📋 Транзакції'!$C$5:$C$3623,">="&EDATE(DATEVALUE(C606&"-01"),9),'📋 Транзакції'!$C$5:$C$3623,"<"&EDATE(DATEVALUE(C606&"-01"),10)) -> 0 | AC606: =SUMIFS('📋 Транзакції'!$F$5:$F$3623,'📋 Транзакції'!$B$5:$B$3623,A606,'📋 Транзакції'!$C$5:$C$3623,">="&EDATE(DATEVALUE(C606&"-01"),10),'📋 Транзакції'!$C$5:$C$3623,"<"&EDATE(DATEVALUE(C606&"-01"),11)) -> 0 | AD606: =SUMIFS('📋 Транзакції'!$F$5:$F$3623,'📋 Транзакції'!$B$5:$B$3623,A606,'📋 Транзакції'!$C$5:$C$3623,">="&EDATE(DATEVALUE(C606&"-01"),11),'📋 Транзакції'!$C$5:$C$3623,"<"&EDATE(DATEVALUE(C606&"-01"),12)) -> 0
A607: ='📋 Реєстрації'!A607:A1208
A608: ='📋 Реєстрації'!A608:A1209
A609: ='📋 Реєстрації'!A609:A1210
A610: ='📋 Реєстрації'!A610:A1211
A611: ='📋 Реєстрації'!A611:A1212
A612: ='📋 Реєстрації'!A612:A1213
A613: ='📋 Реєстрації'!A613:A1214
A614: ='📋 Реєстрації'!A614:A1215
A615: ='📋 Реєстрації'!A615:A1216
A616: ='📋 Реєстрації'!A616:A1217
A617: ='📋 Реєстрації'!A617:A1218
A618: ='📋 Реєстрації'!A618:A1219
... A657: ='📋 Реєстрації'!A657:A1258

Sheet 🧮 RFM
A2: 🧮 RFM — сегментація клієнтів
A4: 🟢 Champions (R≥4,F≥4,M≥4) 🟩 Loyal (R≥3,F≥3) 🔵 New Customers (R≥4,F≤2) 🟡 Promising 🟠 At Risk (R≤2,F≥3) 🔴 Lost (R≤2,F≤2)
A5: User ID | B5: Recency (міс) | C5: Paid Months | D5: Monetary ($) | E5: R | F5: F | G5: M | H5: RFM-код | I5: Сегмент | M5: 1. Який найбільший сегмент у RFM? Яка частка Champions?
A6: ='👥 Клієнти'!A5 -> U0206 | B6: ='👥 Клієнти'!F5 -> 388 | C6: ='👥 Клієнти'!D5 -> 4 | D6: ='👥 Клієнти'!E5 -> 59.97 | E6: =MAX(1,ROUNDUP((1-PERCENTRANK($B$6:$B$607, B6))*5, 0)) -> 1 | F6: =MAX(1,ROUNDUP(PERCENTRANK($C$6:$C$607,C6)*5,0)) -> 2 | G6: =MAX(1,ROUNDUP(PERCENTRANK($D$6:$D$607,D6)*5,0)) -> 2 | H6: =E6&F6&G6 -> 122 | I6: =IFS(AND(E6>=4,F6>=4,G6>=4),"Champions",AND(E6>=4,F6<=2),"New Customers",AND(E6<=2,F6>=3),"At Risk",AND(E6<=2,F6<=2),"Lost",AND(E6>=3,F6>=3),"Loyal",TRUE(),"Promising") -> Lost | M6: Champions | N6: =COUNTIF($I$6:$I$607, "Champions") -> 119 | O6: =N6 / COUNTA($I$6:$I$607) -> 0.19767442
A7: ='👥 Клієнти'!A6 -> U0209 | B7: ='👥 Клієнти'!F6 -> 28 | C7: ='👥 Клієнти'!D6 -> 16 | D7: ='👥 Клієнти'!E6 -> 299.85 | E7: =MAX(1,ROUNDUP((1-PERCENTRANK($B$6:$B$607, B7))*5, 0)) -> 2 | F7: =MAX(1,ROUNDUP(PERCENTRANK($C$6:$C$607,C7)*5,0)) -> 5 | G7: =MAX(1,ROUNDUP(PERCENTRANK($D$6:$D$607,D7)*5,0)) -> 5 | H7: =E7&F7&G7 -> 255 | I7: =IFS(AND(E7>=4,F7>=4,G7>=4),"Champions",AND(E7>=4,F7<=2),"New Customers",AND(E7<=2,F7>=3),"At Risk",AND(E7<=2,F7<=2),"Lost",AND(E7>=3,F7>=3),"Loyal",TRUE(),"Promising") -> At Risk | M7: Loyal | N7: =COUNTIF($I$6:$I$607, "Loyal") -> 120 | O7: =N7 / COUNTA($I$6:$I$607) -> 0.19933555
A8: ='👥 Клієнти'!A7 -> U0516 | B8: ='👥 Клієнти'!F7 -> 297 | C8: ='👥 Клієнти'!D7 -> 7 | D8: ='👥 Клієнти'!E7 -> 119.94 | E8: =MAX(1,ROUNDUP((1-PERCENTRANK($B$6:$B$607, B8))*5, 0)) -> 1 | F8: =MAX(1,ROUNDUP(PERCENTRANK($C$6:$C$607,C8)*5,0)) -> 4 | G8: =MAX(1,ROUNDUP(PERCENTRANK($D$6:$D$607,D8)*5,0)) -> 4 | H8: =E8&F8&G8 -> 144 | I8: =IFS(AND(E8>=4,F8>=4,G8>=4),"Champions",AND(E8>=4,F8<=2),"New Customers",AND(E8<=2,F8>=3),"At Risk",AND(E8<=2,F8<=2),"Lost",AND(E8>=3,F8>=3),"Loyal",TRUE(),"Promising") -> At Risk | M8: New Customers | N8: =COUNTIF($I$6:$I$607, "New Customers") -> 88 | O8: =N8 / COUNTA($I$6:$I$607) -> 0.1461794
A9: ='👥 Клієнти'!A8 -> U0245 | B9: ='👥 Клієнти'!F8 -> 416 | C9: ='👥 Клієнти'!D8 -> 3 | D9: ='👥 Клієнти'!E8 -> 39.98 | E9: =MAX(1,ROUNDUP((1-PERCENTRANK($B$6:$B$607, B9))*5, 0)) -> 1 | F9: =MAX(1,ROUNDUP(PERCENTRANK($C$6:$C$607,C9)*5,0)) -> 2 | G9: =MAX(1,ROUNDUP(PERCENTRANK($D$6:$D$607,D9)*5,0)) -> 2 | H9: =E9&F9&G9 -> 122 | I9: =IFS(AND(E9>=4,F9>=4,G9>=4),"Champions",AND(E9>=4,F9<=2),"New Customers",AND(E9<=2,F9>=3),"At Risk",AND(E9<=2,F9<=2),"Lost",AND(E9>=3,F9>=3),"Loyal",TRUE(),"Promising") -> Lost | M9: Promising | N9: =COUNTIF($I$6:$I$607, "Promising") -> 40 | O9: =N9 / COUNTA($I$6:$I$607) -> 0.066445183
A10: ='👥 Клієнти'!A9 -> U0291 | B10: ='👥 Клієнти'!F9 -> 416 | C10: ='👥 Клієнти'!D9 -> 3 | D10: ='👥 Клієнти'!E9 -> 39.98 | E10: =MAX(1,ROUNDUP((1-PERCENTRANK($B$6:$B$607, B10))*5, 0)) -> 1 | F10: =MAX(1,ROUNDUP(PERCENTRANK($C$6:$C$607,C10)*5,0)) -> 2 | G10: =MAX(1,ROUNDUP(PERCENTRANK($D$6:$D$607,D10)*5,0)) -> 2 | H10: =E10&F10&G10 -> 122 | I10: =IFS(AND(E10>=4,F10>=4,G10>=4),"Champions",AND(E10>=4,F10<=2),"New Customers",AND(E10<=2,F10>=3),"At Risk",AND(E10<=2,F10<=2),"Lost",AND(E10>=3,F10>=3),"Loyal",TRUE(),"Promising") -> Lost | M10: At Risk | N10: =COUNTIF($I$6:$I$607, "At Risk") -> 71 | O10: =N10 / COUNTA($I$6:$I$607) -> 0.1179402
A11: ='👥 Клієнти'!A10 -> U0408 | B11: ='👥 Клієнти'!F10 -> 416 | C11: ='👥 Клієнти'!D10 -> 3 | D11: ='👥 Клієнти'!E10 -> 39.98 | E11: =MAX(1,ROUNDUP((1-PERCENTRANK($B$6:$B$607, B11))*5, 0)) -> 1 | F11: =MAX(1,ROUNDUP(PERCENTRANK($C$6:$C$607,C11)*5,0)) -> 2 | G11: =MAX(1,ROUNDUP(PERCENTRANK($D$6:$D$607,D11)*5,0)) -> 2 | H11: =E11&F11&G11 -> 122 | I11: =IFS(AND(E11>=4,F11>=4,G11>=4),"Champions",AND(E11>=4,F11<=2),"New Customers",AND(E11<=2,F11>=3),"At Risk",AND(E11<=2,F11<=2),"Lost",AND(E11>=3,F11>=3),"Loyal",TRUE(),"Promising") -> Lost | M11: Lost | N11: =COUNTIF($I$6:$I$607, "Lost") -> 164 | O11: =N11 / COUNTA($I$6:$I$607) -> 0.27242525
A12: ='👥 Клієнти'!A11 -> U0883 | B12: ='👥 Клієнти'!F11 -> 26 | C12: ='👥 Клієнти'!D11 -> 16 | D12: ='👥 Клієнти'!E11 -> 299.85 | E12: =MAX(1,ROUNDUP((1-PERCENTRANK($B$6:$B$607, B12))*5, 0)) -> 2 | F12: =MAX(1,ROUNDUP(PERCENTRANK($C$6:$C$607,C12)*5,0)) -> 5 | G12: =MAX(1,ROUNDUP(PERCENTRANK($D$6:$D$607,D12)*5,0)) -> 5 | H12: =E12&F12&G12 -> 255 | I12: =IFS(AND(E12>=4,F12>=4,G12>=4),"Champions",AND(E12>=4,F12<=2),"New Customers",AND(E12<=2,F12>=3),"At Risk",AND(E12<=2,F12<=2),"Lost",AND(E12>=3,F12>=3),"Loyal",TRUE(),"Promising") -> At Risk | M12: Найбільшим є сегмент Lost (27%). Швидше за все це історично накопичений результат. А от Loyal та Champions тримаються на рівних і показують цілком хорошу картину - 40% лояльних клієнтів. Ще й New Customers додають 15% нарощення.
A13: ='👥 Клієнти'!A12 -> U0333 | B13: ='👥 Клієнти'!F12 -> 25 | C13: ='👥 Клієнти'!D12 -> 16 | D13: ='👥 Клієнти'!E12 -> 299.85 | E13: =MAX(1,ROUNDUP((1-PERCENTRANK($B$6:$B$607, B13))*5, 0)) -> 3 | F13: =MAX(1,ROUNDUP(PERCENTRANK($C$6:$C$607,C13)*5,0)) -> 5 | G13: =MAX(1,ROUNDUP(PERCENTRANK($D$6:$D$607,D13)*5,0)) -> 5 | H13: =E13&F13&G13 -> 355 | I13: =IFS(AND(E13>=4,F13>=4,G13>=4),"Champions",AND(E13>=4,F13<=2),"New Customers",AND(E13<=2,F13>=3),"At Risk",AND(E13<=2,F13<=2),"Lost",AND(E13>=3,F13>=3),"Loyal",TRUE(),"Promising") -> Loyal
A14: ='👥 Клієнти'!A13 -> U0172 | B14: ='👥 Клієнти'!F13 -> 200 | C14: ='👥 Клієнти'!D13 -> 10 | D14: ='👥 Клієнти'!E13 -> 179.91 | E14: =MAX(1,ROUNDUP((1-PERCENTRANK($B$6:$B$607, B14))*5, 0)) -> 1 | F14: =MAX(1,ROUNDUP(PERCENTRANK($C$6:$C$607,C14)*5,0)) -> 4 | G14: =MAX(1,ROUNDUP(PERCENTRANK($D$6:$D$607,D14)*5,0)) -> 4 | H14: =E14&F14&G14 -> 144 | I14: =IFS(AND(E14>=4,F14>=4,G14>=4),"Champions",AND(E14>=4,F14<=2),"New Customers",AND(E14<=2,F14>=3),"At Risk",AND(E14<=2,F14<=2),"Lost",AND(E14>=3,F14>=3),"Loyal",TRUE(),"Promising") -> At Risk
A15: ='👥 Клієнти'!A14 -> U0641 | B15: ='👥 Клієнти'!F14 -> 20 | C15: ='👥 Клієнти'!D14 -> 16 | D15: ='👥 Клієнти'!E14 -> 299.85 | E15: =MAX(1,ROUNDUP((1-PERCENTRANK($B$6:$B$607, B15))*5, 0)) -> 3 | F15: =MAX(1,ROUNDUP(PERCENTRANK($C$6:$C$607,C15)*5,0)) -> 5 | G15: =MAX(1,ROUNDUP(PERCENTRANK($D$6:$D$607,D15)*5,0)) -> 5 | H15: =E15&F15&G15 -> 355 | I15: =IFS(AND(E15>=4,F15>=4,G15>=4),"Champions",AND(E15>=4,F15<=2),"New Customers",AND(E15<=2,F15>=3),"At Risk",AND(E15<=2,F15<=2),"Lost",AND(E15>=3,F15>=3),"Loyal",TRUE(),"Promising") -> Loyal
A16: ='👥 Клієнти'!A15 -> U0879 | B16: ='👥 Клієнти'!F15 -> 20 | C16: ='👥 Клієнти'!D15 -> 16 | D16: ='👥 Клієнти'!E15 -> 299.85 | E16: =MAX(1,ROUNDUP((1-PERCENTRANK($B$6:$B$607, B16))*5, 0)) -> 3 | F16: =MAX(1,ROUNDUP(PERCENTRANK($C$6:$C$607,C16)*5,0)) -> 5 | G16: =MAX(1,ROUNDUP(PERCENTRANK($D$6:$D$607,D16)*5,0)) -> 5 | H16: =E16&F16&G16 -> 355 | I16: =IFS(AND(E16>=4,F16>=4,G16>=4),"Champions",AND(E16>=4,F16<=2),"New Customers",AND(E16<=2,F16>=3),"At Risk",AND(E16<=2,F16<=2),"Lost",AND(E16>=3,F16>=3),"Loyal",TRUE(),"Promising") -> Loyal
A17: ='👥 Клієнти'!A16 -> U0238 | B17: ='👥 Клієнти'!F16 -> 16 | C17: ='👥 Клієнти'!D16 -> 16 | D17: ='👥 Клієнти'!E16 -> 299.85 | E17: =MAX(1,ROUNDUP((1-PERCENTRANK($B$6:$B$607, B17))*5, 0)) -> 3 | F17: =MAX(1,ROUNDUP(PERCENTRANK($C$6:$C$607,C17)*5,0)) -> 5 | G17: =MAX(1,ROUNDUP(PERCENTRANK($D$6:$D$607,D17)*5,0)) -> 5 | H17: =E17&F17&G17 -> 355 | I17: =IFS(AND(E17>=4,F17>=4,G17>=4),"Champions",AND(E17>=4,F17<=2),"New Customers",AND(E17<=2,F17>=3),"At Risk",AND(E17<=2,F17<=2),"Lost",AND(E17>=3,F17>=3),"Loyal",TRUE(),"Promising") -> Loyal
A18: ='👥 Клієнти'!A17 -> U0357 | B18: ='👥 Клієнти'!F17 -> 15 | C18: ='👥 Клієнти'!D17 -> 16 | D18: ='👥 Клієнти'!E17 -> 299.85 | E18: =MAX(1,ROUNDUP((1-PERCENTRANK($B$6:$B$607, B18))*5, 0)) -> 4 | F18: =MAX(1,ROUNDUP(PERCENTRANK($C$6:$C$607,C18)*5,0)) -> 5 | G18: =MAX(1,ROUNDUP(PERCENTRANK($D$6:$D$607,D18)*5,0)) -> 5 | H18: =E18&F18&G18 -> 455 | I18: =IFS(AND(E18>=4,F18>=4,G18>=4),"Champions",AND(E18>=4,F18<=2),"New Customers",AND(E18<=2,F18>=3),"At Risk",AND(E18<=2,F18<=2),"Lost",AND(E18>=3,F18>=3),"Loyal",TRUE(),"Promising") -> Champions
A19: ='👥 Клієнти'!A18 -> U0378 | B19: ='👥 Клієнти'!F18 -> 404 | C19: ='👥 Клієнти'!D18 -> 3 | D19: ='👥 Клієнти'!E18 -> 39.98 | E19: =MAX(1,ROUNDUP((1-PERCENTRANK($B$6:$B$607, B19))*5, 0)) -> 1 | F19: =MAX(1,ROUNDUP(PERCENTRANK($C$6:$C$607,C19)*5,0)) -> 2 | G19: =MAX(1,ROUNDUP(PERCENTRANK($D$6:$D$607,D19)*5,0)) -> 2 | H19: =E19&F19&G19 -> 122 | I19: =IFS(AND(E19>=4,F19>=4,G19>=4),"Champions",AND(E19>=4,F19<=2),"New Customers",AND(E19<=2,F19>=3),"At Risk",AND(E19<=2,F19<=2),"Lost",AND(E19>=3,F19>=3),"Loyal",TRUE(),"Promising") -> Lost
A20: ='👥 Клієнти'!A19 -> U0795 | B20: ='👥 Клієнти'!F19 -> 374 | C20: ='👥 Клієнти'!D19 -> 4 | D20: ='👥 Клієнти'!E19 -> 59.97 | E20: =MAX(1,ROUNDUP((1-PERCENTRANK($B$6:$B$607, B20))*5, 0)) -> 1 | F20: =MAX(1,ROUNDUP(PERCENTRANK($C$6:$C$607,C20)*5,0)) -> 2 | G20: =MAX(1,ROUNDUP(PERCENTRANK($D$6:$D$607,D20)*5,0)) -> 2 | H20: =E20&F20&G20 -> 122 | I20: =IFS(AND(E20>=4,F20>=4,G20>=4),"Champions",AND(E20>=4,F20<=2),"New Customers",AND(E20<=2,F20>=3),"At Risk",AND(E20<=2,F20<=2),"Lost",AND(E20>=3,F20>=3),"Loyal",TRUE(),"Promising") -> Lost
A21: ='👥 Клієнти'!A20 -> U0011 | B21: ='👥 Клієнти'!F20 -> 11 | C21: ='👥 Клієнти'!D20 -> 16 | D21: ='👥 Клієнти'!E20 -> 299.85 | E21: =MAX(1,ROUNDUP((1-PERCENTRANK($B$6:$B$607, B21))*5, 0)) -> 4 | F21: =MAX(1,ROUNDUP(PERCENTRANK($C$6:$C$607,C21)*5,0)) -> 5 | G21: =MAX(1,ROUNDUP(PERCENTRANK($D$6:$D$607,D21)*5,0)) -> 5 | H21: =E21&F21&G21 -> 455 | I21: =IFS(AND(E21>=4,F21>=4,G21>=4),"Champions",AND(E21>=4,F21<=2),"New Customers",AND(E21<=2,F21>=3),"At Risk",AND(E21<=2,F21<=2),"Lost",AND(E21>=3,F21>=3),"Loyal",TRUE(),"Promising") -> Champions
A22: ='👥 Клієнти'!A21 -> U0099 | B22: ='👥 Клієнти'!F21 -> 430 | C22: ='👥 Клієнти'!D21 -> 2 | D22: ='👥 Клієнти'!E21 -> 19.99 | E22: =MAX(1,ROUNDUP((1-PERCENTRANK($B$6:$B$607, B22))*5, 0)) -> 1 | F22: =MAX(1,ROUNDUP(PERCENTRANK($C$6:$C$607,C22)*5,0)) -> 1 | G22: =MAX(1,ROUNDUP(PERCENTRANK($D$6:$D$607,D22)*5,0)) -> 1 | H22: =E22&F22&G22 -> 111 | I22: =IFS(AND(E22>=4,F22>=4,G22>=4),"Champions",AND(E22>=4,F22<=2),"New Customers",AND(E22<=2,F22>=3),"At Risk",AND(E22<=2,F22<=2),"Lost",AND(E22>=3,F22>=3),"Loyal",TRUE(),"Promising") -> Lost
A23: ='👥 Клієнти'!A22 -> U0457 | B23: ='👥 Клієнти'!F22 -> 340 | C23: ='👥 Клієнти'!D22 -> 5 | D23: ='👥 Клієнти'!E22 -> 79.96 | E23: =MAX(1,ROUNDUP((1-PERCENTRANK($B$6:$B$607, B23))*5, 0)) -> 1 | F23: =MAX(1,ROUNDUP(PERCENTRANK($C$6:$C$607,C23)*5,0)) -> 3 | G23: =MAX(1,ROUNDUP(PERCENTRANK($D$6:$D$607,D23)*5,0)) -> 3 | H23: =E23&F23&G23 -> 133 | I23: =IFS(AND(E23>=4,F23>=4,G23>=4),"Champions",AND(E23>=4,F23<=2),"New Customers",AND(E23<=2,F23>=3),"At Risk",AND(E23<=2,F23<=2),"Lost",AND(E23>=3,F23>=3),"Loyal",TRUE(),"Promising") -> At Risk
A24: ='👥 Клієнти'!A23 -> U0372 | B24: ='👥 Клієнти'!F23 -> 8 | C24: ='👥 Клієнти'!D23 -> 16 | D24: ='👥 Клієнти'!E23 -> 299.85 | E24: =MAX(1,ROUNDUP((1-PERCENTRANK($B$6:$B$607, B24))*5, 0)) -> 4 | F24: =MAX(1,ROUNDUP(PERCENTRANK($C$6:$C$607,C24)*5,0)) -> 5 | G24: =MAX(1,ROUNDUP(PERCENTRANK($D$6:$D$607,D24)*5,0)) -> 5 | H24: =E24&F24&G24 -> 455 | I24: =IFS(AND(E24>=4,F24>=4,G24>=4),"Champions",AND(E24>=4,F24<=2),"New Customers",AND(E24<=2,F24>=3),"At Risk",AND(E24<=2,F24<=2),"Lost",AND(E24>=3,F24>=3),"Loyal",TRUE(),"Promising") -> Champions
... A607: ='👥 Клієнти'!A606 -> U0679 | B607: ='👥 Клієнти'!F606 -> 0 | C607: ='👥 Клієнти'!D606 -> 2 | D607: ='👥 Клієнти'!E606 -> 19.99 | E607: =MAX(1,ROUNDUP((1-PERCENTRANK($B$6:$B$607, B607))*5, 0)) -> 5 | F607: =MAX(1,ROUNDUP(PERCENTRANK($C$6:$C$607,C607)*5,0)) -> 1 | G607: =MAX(1,ROUNDUP(PERCENTRANK($D$6:$D$607,D607)*5,0)) -> 1 | H607: =E607&F607&G607 -> 511 | I607: =IFS(AND(E607>=4,F607>=4,G607>=4),"Champions",AND(E607>=4,F607<=2),"New Customers",AND(E607<=2,F607>=3),"At Risk",AND(E607<=2,F607<=2),"Lost",AND(E607>=3,F607>=3),"Loyal",TRUE(),"Promising") -> New Customers

Sheet 📊 Retention
A2: 📊 Retention-трикутник
A4: Когорта | B4: Клієнтів | C4: М+0 | D4: М+1 | E4: М+2 | F4: М+3 | G4: М+4 | H4: М+5 | I4: М+6 | J4: М+7 | K4: М+8 | L4: М+9 | M4: М+10 | N4: М+11
A5: 45292 | B5: =COUNTIF('👥 Клієнти'!$C$5:$C$606,$A5) -> 25 | C5: =SUMIFS('👥 Клієнти'!$G$5:$G$606,'👥 Клієнти'!$C$5:$C$606,$A5) -> 25 | D5: =SUMIFS('👥 Клієнти'!$H$5:$H$606,'👥 Клієнти'!$C$5:$C$606,$A5) -> 24 | E5: =SUMIFS('👥 Клієнти'!$I$5:$I$606,'👥 Клієнти'!$C$5:$C$606,$A5) -> 19 | F5: =SUMIFS('👥 Клієнти'!$J$5:$J$606,'👥 Клієнти'!$C$5:$C$606,$A5) -> 17 | G5: =SUMIFS('👥 Клієнти'!$K$5:$K$606,'👥 Клієнти'!$C$5:$C$606,$A5) -> 15 | H5: =SUMIFS('👥 Клієнти'!$L$5:$L$606,'👥 Клієнти'!$C$5:$C$606,$A5) -> 15 | I5: =SUMIFS('👥 Клієнти'!$M$5:$M$606,'👥 Клієнти'!$C$5:$C$606,$A5) -> 13 | J5: =SUMIFS('👥 Клієнти'!$N$5:$N$606,'👥 Клієнти'!$C$5:$C$606,$A5) -> 13 | K5: =SUMIFS('👥 Клієнти'!$O$5:$O$606,'👥 Клієнти'!$C$5:$C$606,$A5) -> 13 | L5: =SUMIFS('👥 Клієнти'!$P$5:$P$606,'👥 Клієнти'!$C$5:$C$606,$A5) -> 12 | M5: =SUMIFS('👥 Клієнти'!$Q$5:$Q$606,'👥 Клієнти'!$C$5:$C$606,$A5) -> 12 | N5: =SUMIFS('👥 Клієнти'!$R$5:$R$606,'👥 Клієнти'!$C$5:$C$606,$A5) -> 12
A6: 45323 | B6: =COUNTIF('👥 Клієнти'!$C$5:$C$606,$A6) -> 27 | C6: =SUMIFS('👥 Клієнти'!$G$5:$G$606,'👥 Клієнти'!$C$5:$C$606,$A6) -> 27 | D6: =SUMIFS('👥 Клієнти'!$H$5:$H$606,'👥 Клієнти'!$C$5:$C$606,$A6) -> 26 | E6: =SUMIFS('👥 Клієнти'!$I$5:$I$606,'👥 Клієнти'!$C$5:$C$606,$A6) -> 23 | F6: =SUMIFS('👥 Клієнти'!$J$5:$J$606,'👥 Клієнти'!$C$5:$C$606,$A6) -> 21 | G6: =SUMIFS('👥 Клієнти'!$K$5:$K$606,'👥 Клієнти'!$C$5:$C$606,$A6) -> 18 | H6: =SUMIFS('👥 Клієнти'!$L$5:$L$606,'👥 Клієнти'!$C$5:$C$606,$A6) -> 18 | I6: =SUMIFS('👥 Клієнти'!$M$5:$M$606,'👥 Клієнти'!$C$5:$C$606,$A6) -> 17 | J6: =SUMIFS('👥 Клієнти'!$N$5:$N$606,'👥 Клієнти'!$C$5:$C$606,$A6) -> 15 | K6: =SUMIFS('👥 Клієнти'!$O$5:$O$606,'👥 Клієнти'!$C$5:$C$606,$A6) -> 15 | L6: =SUMIFS('👥 Клієнти'!$P$5:$P$606,'👥 Клієнти'!$C$5:$C$606,$A6) -> 14 | M6: =SUMIFS('👥 Клієнти'!$Q$5:$Q$606,'👥 Клієнти'!$C$5:$C$606,$A6) -> 14 | N6: =SUMIFS('👥 Клієнти'!$R$5:$R$606,'👥 Клієнти'!$C$5:$C$606,$A6) -> 14
A7: 45352 | B7: =COUNTIF('👥 Клієнти'!$C$5:$C$606,$A7) -> 32 | C7: =SUMIFS('👥 Клієнти'!$G$5:$G$606,'👥 Клієнти'!$C$5:$C$606,$A7) -> 32 | D7: =SUMIFS('👥 Клієнти'!$H$5:$H$606,'👥 Клієнти'!$C$5:$C$606,$A7) -> 29 | E7: =SUMIFS('👥 Клієнти'!$I$5:$I$606,'👥 Клієнти'!$C$5:$C$606,$A7) -> 28 | F7: =SUMIFS('👥 Клієнти'!$J$5:$J$606,'👥 Клієнти'!$C$5:$C$606,$A7) -> 23 | G7: =SUMIFS('👥 Клієнти'!$K$5:$K$606,'👥 Клієнти'!$C$5:$C$606,$A7) -> 23 | H7: =SUMIFS('👥 Клієнти'!$L$5:$L$606,'👥 Клієнти'!$C$5:$C$606,$A7) -> 22 | I7: =SUMIFS('👥 Клієнти'!$M$5:$M$606,'👥 Клієнти'!$C$5:$C$606,$A7) -> 19 | J7: =SUMIFS('👥 Клієнти'!$N$5:$N$606,'👥 Клієнти'!$C$5:$C$606,$A7) -> 18 | K7: =SUMIFS('👥 Клієнти'!$O$5:$O$606,'👥 Клієнти'!$C$5:$C$606,$A7) -> 18 | L7: =SUMIFS('👥 Клієнти'!$P$5:$P$606,'👥 Клієнти'!$C$5:$C$606,$A7) -> 18 | M7: =SUMIFS('👥 Клієнти'!$Q$5:$Q$606,'👥 Клієнти'!$C$5:$C$606,$A7) -> 18 | N7: =SUMIFS('👥 Клієнти'!$R$5:$R$606,'👥 Клієнти'!$C$5:$C$606,$A7) -> 17
A8: 45383 | B8: =COUNTIF('👥 Клієнти'!$C$5:$C$606,$A8) -> 36 | C8: =SUMIFS('👥 Клієнти'!$G$5:$G$606,'👥 Клієнти'!$C$5:$C$606,$A8) -> 36 | D8: =SUMIFS('👥 Клієнти'!$H$5:$H$606,'👥 Клієнти'!$C$5:$C$606,$A8) -> 33 | E8: =SUMIFS('👥 Клієнти'!$I$5:$I$606,'👥 Клієнти'!$C$5:$C$606,$A8) -> 30 | F8: =SUMIFS('👥 Клієнти'!$J$5:$J$606,'👥 Клієнти'!$C$5:$C$606,$A8) -> 28 | G8: =SUMIFS('👥 Клієнти'!$K$5:$K$606,'👥 Клієнти'!$C$5:$C$606,$A8) -> 28 | H8: =SUMIFS('👥 Клієнти'!$L$5:$L$606,'👥 Клієнти'!$C$5:$C$606,$A8) -> 27 | I8: =SUMIFS('👥 Клієнти'!$M$5:$M$606,'👥 Клієнти'!$C$5:$C$606,$A8) -> 25 | J8: =SUMIFS('👥 Клієнти'!$N$5:$N$606,'👥 Клієнти'!$C$5:$C$606,$A8) -> 25 | K8: =SUMIFS('👥 Клієнти'!$O$5:$O$606,'👥 Клієнти'!$C$5:$C$606,$A8) -> 23 | L8: =SUMIFS('👥 Клієнти'!$P$5:$P$606,'👥 Клієнти'!$C$5:$C$606,$A8) -> 23 | M8: =SUMIFS('👥 Клієнти'!$Q$5:$Q$606,'👥 Клієнти'!$C$5:$C$606,$A8) -> 22 | N8: =SUMIFS('👥 Клієнти'!$R$5:$R$606,'👥 Клієнти'!$C$5:$C$606,$A8) -> 23
A9: 45413 | B9: =COUNTIF('👥 Клієнти'!$C$5:$C$606,$A9) -> 32 | C9: =SUMIFS('👥 Клієнти'!$G$5:$G$606,'👥 Клієнти'!$C$5:$C$606,$A9) -> 32 | D9: =SUMIFS('👥 Клієнти'!$H$5:$H$606,'👥 Клієнти'!$C$5:$C$606,$A9) -> 25 | E9: =SUMIFS('👥 Клієнти'!$I$5:$I$606,'👥 Клієнти'!$C$5:$C$606,$A9) -> 23 | F9: =SUMIFS('👥 Клієнти'!$J$5:$J$606,'👥 Клієнти'!$C$5:$C$606,$A9) -> 21 | G9: =SUMIFS('👥 Клієнти'!$K$5:$K$606,'👥 Клієнти'!$C$5:$C$606,$A9) -> 20 | H9: =SUMIFS('👥 Клієнти'!$L$5:$L$606,'👥 Клієнти'!$C$5:$C$606,$A9) -> 19 | I9: =SUMIFS('👥 Клієнти'!$M$5:$M$606,'👥 Клієнти'!$C$5:$C$606,$A9) -> 18 | J9: =SUMIFS('👥 Клієнти'!$N$5:$N$606,'👥 Клієнти'!$C$5:$C$606,$A9) -> 18 | K9: =SUMIFS('👥 Клієнти'!$O$5:$O$606,'👥 Клієнти'!$C$5:$C$606,$A9) -> 18 | L9: =SUMIFS('👥 Клієнти'!$P$5:$P$606,'👥 Клієнти'!$C$5:$C$606,$A9) -> 16 | M9: =SUMIFS('👥 Клієнти'!$Q$5:$Q$606,'👥 Клієнти'!$C$5:$C$606,$A9) -> 18 | N9: —
A10: 45444 | B10: =COUNTIF('👥 Клієнти'!$C$5:$C$606,$A10) -> 27 | C10: =SUMIFS('👥 Клієнти'!$G$5:$G$606,'👥 Клієнти'!$C$5:$C$606,$A10) -> 27 | D10: =SUMIFS('👥 Клієнти'!$H$5:$H$606,'👥 Клієнти'!$C$5:$C$606,$A10) -> 23 | E10: =SUMIFS('👥 Клієнти'!$I$5:$I$606,'👥 Клієнти'!$C$5:$C$606,$A10) -> 20 | F10: =SUMIFS('👥 Клієнти'!$J$5:$J$606,'👥 Клієнти'!$C$5:$C$606,$A10) -> 17 | G10: =SUMIFS('👥 Клієнти'!$K$5:$K$606,'👥 Клієнти'!$C$5:$C$606,$A10) -> 17 | H10: =SUMIFS('👥 Клієнти'!$L$5:$L$606,'👥 Клієнти'!$C$5:$C$606,$A10) -> 16 | I10: =SUMIFS('👥 Клієнти'!$M$5:$M$606,'👥 Клієнти'!$C$5:$C$606,$A10) -> 16 | J10: =SUMIFS('👥 Клієнти'!$N$5:$N$606,'👥 Клієнти'!$C$5:$C$606,$A10) -> 16 | K10: =SUMIFS('👥 Клієнти'!$O$5:$O$606,'👥 Клієнти'!$C$5:$C$606,$A10) -> 13 | L10: =SUMIFS('👥 Клієнти'!$P$5:$P$606,'👥 Клієнти'!$C$5:$C$606,$A10) -> 15 | M10: — | N10: —
A11: 45474 | B11: =COUNTIF('👥 Клієнти'!$C$5:$C$606,$A11) -> 40 | C11: =SUMIFS('👥 Клієнти'!$G$5:$G$606,'👥 Клієнти'!$C$5:$C$606,$A11) -> 40 | D11: =SUMIFS('👥 Клієнти'!$H$5:$H$606,'👥 Клієнти'!$C$5:$C$606,$A11) -> 36 | E11: =SUMIFS('👥 Клієнти'!$I$5:$I$606,'👥 Клієнти'!$C$5:$C$606,$A11) -> 32 | F11: =SUMIFS('👥 Клієнти'!$J$5:$J$606,'👥 Клієнти'!$C$5:$C$606,$A11) -> 30 | G11: =SUMIFS('👥 Клієнти'!$K$5:$K$606,'👥 Клієнти'!$C$5:$C$606,$A11) -> 29 | H11: =SUMIFS('👥 Клієнти'!$L$5:$L$606,'👥 Клієнти'!$C$5:$C$606,$A11) -> 27 | I11: =SUMIFS('👥 Клієнти'!$M$5:$M$606,'👥 Клієнти'!$C$5:$C$606,$A11) -> 25 | J11: =SUMIFS('👥 Клієнти'!$N$5:$N$606,'👥 Клієнти'!$C$5:$C$606,$A11) -> 22 | K11: =SUMIFS('👥 Клієнти'!$O$5:$O$606,'👥 Клієнти'!$C$5:$C$606,$A11) -> 25 | L11: — | M11: — | N11: —
A12: 45505 | B12: =COUNTIF('👥 Клієнти'!$C$5:$C$606,$A12) -> 47 | C12: =SUMIFS('👥 Клієнти'!$G$5:$G$606,'👥 Клієнти'!$C$5:$C$606,$A12) -> 47 | D12: =SUMIFS('👥 Клієнти'!$H$5:$H$606,'👥 Клієнти'!$C$5:$C$606,$A12) -> 40 | E12: =SUMIFS('👥 Клієнти'!$I$5:$I$606,'👥 Клієнти'!$C$5:$C$606,$A12) -> 35 | F12: =SUMIFS('👥 Клієнти'!$J$5:$J$606,'👥 Клієнти'!$C$5:$C$606,$A12) -> 30 | G12: =SUMIFS('👥 Клієнти'!$K$5:$K$606,'👥 Клієнти'!$C$5:$C$606,$A12) -> 26 | H12: =SUMIFS('👥 Клієнти'!$L$5:$L$606,'👥 Клієнти'!$C$5:$C$606,$A12) -> 26 | I12: =SUMIFS('👥 Клієнти'!$M$5:$M$606,'👥 Клієнти'!$C$5:$C$606,$A12) -> 22 | J12: =SUMIFS('👥 Клієнти'!$N$5:$N$606,'👥 Клієнти'!$C$5:$C$606,$A12) -> 23 | K12: — | L12: — | M12: — | N12: —
A13: 45536 | B13: =COUNTIF('👥 Клієнти'!$C$5:$C$606,$A13) -> 34 | C13: =SUMIFS('👥 Клієнти'!$G$5:$G$606,'👥 Клієнти'!$C$5:$C$606,$A13) -> 34 | D13: =SUMIFS('👥 Клієнти'!$H$5:$H$606,'👥 Клієнти'!$C$5:$C$606,$A13) -> 31 | E13: =SUMIFS('👥 Клієнти'!$I$5:$I$606,'👥 Клієнти'!$C$5:$C$606,$A13) -> 29 | F13: =SUMIFS('👥 Клієнти'!$J$5:$J$606,'👥 Клієнти'!$C$5:$C$606,$A13) -> 25 | G13: =SUMIFS('👥 Клієнти'!$K$5:$K$606,'👥 Клієнти'!$C$5:$C$606,$A13) -> 22 | H13: =SUMIFS('👥 Клієнти'!$L$5:$L$606,'👥 Клієнти'!$C$5:$C$606,$A13) -> 21 | I13: =SUMIFS('👥 Клієнти'!$M$5:$M$606,'👥 Клієнти'!$C$5:$C$606,$A13) -> 20 | J13: — | K13: — | L13: — | M13: — | N13: —
A14: 45566 | B14: =COUNTIF('👥 Клієнти'!$C$5:$C$606,$A14) -> 53 | C14: =SUMIFS('👥 Клієнти'!$G$5:$G$606,'👥 Клієнти'!$C$5:$C$606,$A14) -> 53 | D14: =SUMIFS('👥 Клієнти'!$H$5:$H$606,'👥 Клієнти'!$C$5:$C$606,$A14) -> 48 | E14: =SUMIFS('👥 Клієнти'!$I$5:$I$606,'👥 Клієнти'!$C$5:$C$606,$A14) -> 44 | F14: =SUMIFS('👥 Клієнти'!$J$5:$J$606,'👥 Клієнти'!$C$5:$C$606,$A14) -> 41 | G14: =SUMIFS('👥 Клієнти'!$K$5:$K$606,'👥 Клієнти'!$C$5:$C$606,$A14) -> 40 | H14: =SUMIFS('👥 Клієнти'!$L$5:$L$606,'👥 Клієнти'!$C$5:$C$606,$A14) -> 38 | I14: — | J14: — | K14: — | L14: — | M14: — | N14: —
A15: 45597 | B15: =COUNTIF('👥 Клієнти'!$C$5:$C$606,$A15) -> 52 | C15: =SUMIFS('👥 Клієнти'!$G$5:$G$606,'👥 Клієнти'!$C$5:$C$606,$A15) -> 52 | D15: =SUMIFS('👥 Клієнти'!$H$5:$H$606,'👥 Клієнти'!$C$5:$C$606,$A15) -> 46 | E15: =SUMIFS('👥 Клієнти'!$I$5:$I$606,'👥 Клієнти'!$C$5:$C$606,$A15) -> 39 | F15: =SUMIFS('👥 Клієнти'!$J$5:$J$606,'👥 Клієнти'!$C$5:$C$606,$A15) -> 34 | G15: =SUMIFS('👥 Клієнти'!$K$5:$K$606,'👥 Клієнти'!$C$5:$C$606,$A15) -> 33 | H15: — | I15: — | J15: — | K15: — | L15: — | M15: — | N15: —
A16: 45627 | B16: =COUNTIF('👥 Клієнти'!$C$5:$C$606,$A16) -> 48 | C16: =SUMIFS('👥 Клієнти'!$G$5:$G$606,'👥 Клієнти'!$C$5:$C$606,$A16) -> 48 | D16: =SUMIFS('👥 Клієнти'!$H$5:$H$606,'👥 Клієнти'!$C$5:$C$606,$A16) -> 43 | E16: =SUMIFS('👥 Клієнти'!$I$5:$I$606,'👥 Клієнти'!$C$5:$C$606,$A16) -> 36 | F16: =SUMIFS('👥 Клієнти'!$J$5:$J$606,'👥 Клієнти'!$C$5:$C$606,$A16) -> 33 | G16: — | H16: — | I16: — | J16: — | K16: — | L16: — | M16: — | N16: —
A17: 45658 | B17: =COUNTIF('👥 Клієнти'!$C$5:$C$606,$A17) -> 45 | C17: =SUMIFS('👥 Клієнти'!$G$5:$G$606,'👥 Клієнти'!$C$5:$C$606,$A17) -> 45 | D17: =SUMIFS('👥 Клієнти'!$H$5:$H$606,'👥 Клієнти'!$C$5:$C$606,$A17) -> 36 | E17: =SUMIFS('👥 Клієнти'!$I$5:$I$606,'👥 Клієнти'!$C$5:$C$606,$A17) -> 38 | F17: — | G17: — | H17: — | I17: — | J17: — | K17: — | L17: — | M17: — | N17: —
A18: 45689 | B18: =COUNTIF('👥 Клієнти'!$C$5:$C$606,$A18) -> 53 | C18: =SUMIFS('👥 Клієнти'!$G$5:$G$606,'👥 Клієнти'!$C$5:$C$606,$A18) -> 53 | D18: =SUMIFS('👥 Клієнти'!$H$5:$H$606,'👥 Клієнти'!$C$5:$C$606,$A18) -> 52 | E18: — | F18: — | G18: — | H18: — | I18: — | J18: — | K18: — | L18: — | M18: — | N18: —
A19: 45717 | B19: =COUNTIF('👥 Клієнти'!$C$5:$C$606,$A19) -> 51 | C19: =SUMIFS('👥 Клієнти'!$G$5:$G$606,'👥 Клієнти'!$C$5:$C$606,$A19) -> 51 | D19: — | E19: — | F19: — | G19: — | H19: — | I19: — | J19: — | K19: — | L19: — | M19: — | N19: —

Sheet 🌡️ Retention %
A2: 🌡️ Retention % — заповни формулами
A4: Когорта | C4: М+0 | D4: М+1 | E4: М+2 | F4: М+3 | G4: М+4 | H4: М+5 | I4: М+6 | J4: М+7 | K4: М+8 | L4: М+9 | M4: М+10 | N4: М+11
A5: ='📊 Retention'!A5:A19 -> 45292 | C5: =IFERROR('📊 Retention'!C5/'📊 Retention'!$C5,"") -> 1 | D5: =IFERROR('📊 Retention'!D5/'📊 Retention'!$C5,"") -> 0.96 | E5: =IFERROR('📊 Retention'!E5/'📊 Retention'!$C5,"") -> 0.76 | F5: =IFERROR('📊 Retention'!F5/'📊 Retention'!$C5,"") -> 0.68 | G5: =IFERROR('📊 Retention'!G5/'📊 Retention'!$C5,"") -> 0.6 | H5: =IFERROR('📊 Retention'!H5/'📊 Retention'!$C5,"") -> 0.6 | I5: =IFERROR('📊 Retention'!I5/'📊 Retention'!$C5,"") -> 0.52 | J5: =IFERROR('📊 Retention'!J5/'📊 Retention'!$C5,"") -> 0.52 | ... N5: =IFERROR('📊 Retention'!N5/'📊 Retention'!$C5,"") -> 0.48
A6: ='📊 Retention'!A6:A20 -> 45323 | C6: =IFERROR('📊 Retention'!C6/'📊 Retention'!$C6,"") -> 1 | D6: =IFERROR('📊 Retention'!D6/'📊 Retention'!$C6,"") -> 0.96296296 | E6: =IFERROR('📊 Retention'!E6/'📊 Retention'!$C6,"") -> 0.85185185 | F6: =IFERROR('📊 Retention'!F6/'📊 Retention'!$C6,"") -> 0.77777778 | G6: =IFERROR('📊 Retention'!G6/'📊 Retention'!$C6,"") -> 0.66666667 | H6: =IFERROR('📊 Retention'!H6/'📊 Retention'!$C6,"") -> 0.66666667 | I6: =IFERROR('📊 Retention'!I6/'📊 Retention'!$C6,"") -> 0.62962963 | J6: =IFERROR('📊 Retention'!J6/'📊 Retention'!$C6,"") -> 0.55555556 | ... N6: =IFERROR('📊 Retention'!N6/'📊 Retention'!$C6,"") -> 0.51851852
A7: ='📊 Retention'!A7:A21 -> 45352 | C7: =IFERROR('📊 Retention'!C7/'📊 Retention'!$C7,"") -> 1 | D7: =IFERROR('📊 Retention'!D7/'📊 Retention'!$C7,"") -> 0.90625 | E7: =IFERROR('📊 Retention'!E7/'📊 Retention'!$C7,"") -> 0.875 | F7: =IFERROR('📊 Retention'!F7/'📊 Retention'!$C7,"") -> 0.71875 | G7: =IFERROR('📊 Retention'!G7/'📊 Retention'!$C7,"") -> 0.71875 | H7: =IFERROR('📊 Retention'!H7/'📊 Retention'!$C7,"") -> 0.6875 | I7: =IFERROR('📊 Retention'!I7/'📊 Retention'!$C7,"") -> 0.59375 | J7: =IFERROR('📊 Retention'!J7/'📊 Retention'!$C7,"") -> 0.5625 | ... N7: =IFERROR('📊 Retention'!N7/'📊 Retention'!$C7,"") -> 0.53125
A8: ='📊 Retention'!A8:A22 -> 45383 | C8: =IFERROR('📊 Retention'!C8/'📊 Retention'!$C8,"") -> 1 | D8: =IFERROR('📊 Retention'!D8/'📊 Retention'!$C8,"") -> 0.91666667 | E8: =IFERROR('📊 Retention'!E8/'📊 Retention'!$C8,"") -> 0.83333333 | F8: =IFERROR('📊 Retention'!F8/'📊 Retention'!$C8,"") -> 0.77777778 | G8: =IFERROR('📊 Retention'!G8/'📊 Retention'!$C8,"") -> 0.77777778 | H8: =IFERROR('📊 Retention'!H8/'📊 Retention'!$C8,"") -> 0.75 | I8: =IFERROR('📊 Retention'!I8/'📊 Retention'!$C8,"") -> 0.69444444 | J8: =IFERROR('📊 Retention'!J8/'📊 Retention'!$C8,"") -> 0.69444444 | ... N8: =IFERROR('📊 Retention'!N8/'📊 Retention'!$C8,"") -> 0.63888889
A9: ='📊 Retention'!A9:A23 -> 45413 | C9: =IFERROR('📊 Retention'!C9/'📊 Retention'!$C9,"") -> 1 | D9: =IFERROR('📊 Retention'!D9/'📊 Retention'!$C9,"") -> 0.78125 | E9: =IFERROR('📊 Retention'!E9/'📊 Retention'!$C9,"") -> 0.71875 | F9: =IFERROR('📊 Retention'!F9/'📊 Retention'!$C9,"") -> 0.65625 | G9: =IFERROR('📊 Retention'!G9/'📊 Retention'!$C9,"") -> 0.625 | H9: =IFERROR('📊 Retention'!H9/'📊 Retention'!$C9,"") -> 0.59375 | I9: =IFERROR('📊 Retention'!I9/'📊 Retention'!$C9,"") -> 0.5625 | J9: =IFERROR('📊 Retention'!J9/'📊 Retention'!$C9,"") -> 0.5625 | ... M9: =IFERROR('📊 Retention'!M9/'📊 Retention'!$C9,"") -> 0.5625 | N9: —
A10: ='📊 Retention'!A10:A24 -> 45444 | C10: =IFERROR('📊 Retention'!C10/'📊 Retention'!$C10,"") -> 1 | D10: =IFERROR('📊 Retention'!D10/'📊 Retention'!$C10,"") -> 0.85185185 | E10: =IFERROR('📊 Retention'!E10/'📊 Retention'!$C10,"") -> 0.74074074 | F10: =IFERROR('📊 Retention'!F10/'📊 Retention'!$C10,"") -> 0.62962963 | G10: =IFERROR('📊 Retention'!G10/'📊 Retention'!$C10,"") -> 0.62962963 | H10: =IFERROR('📊 Retention'!H10/'📊 Retention'!$C10,"") -> 0.59259259 | I10: =IFERROR('📊 Retention'!I10/'📊 Retention'!$C10,"") -> 0.59259259 | J10: =IFERROR('📊 Retention'!J10/'📊 Retention'!$C10,"") -> 0.59259259 | ... L10: =IFERROR('📊 Retention'!L10/'📊 Retention'!$C10,"") -> 0.55555556 | M10: — | N10: —
A11: ='📊 Retention'!A11:A25 -> 45474 | C11: =IFERROR('📊 Retention'!C11/'📊 Retention'!$C11,"") -> 1 | D11: =IFERROR('📊 Retention'!D11/'📊 Retention'!$C11,"") -> 0.9 | E11: =IFERROR('📊 Retention'!E11/'📊 Retention'!$C11,"") -> 0.8 | F11: =IFERROR('📊 Retention'!F11/'📊 Retention'!$C11,"") -> 0.75 | G11: =IFERROR('📊 Retention'!G11/'📊 Retention'!$C11,"") -> 0.725 | H11: =IFERROR('📊 Retention'!H11/'📊 Retention'!$C11,"") -> 0.675 | I11: =IFERROR('📊 Retention'!I11/'📊 Retention'!$C11,"") -> 0.625 | J11: =IFERROR('📊 Retention'!J11/'📊 Retention'!$C11,"") -> 0.55 | K11: =IFERROR('📊 Retention'!K11/'📊 Retention'!$C11,"") -> 0.625 | L11: — | M11: — | N11: —
A12: ='📊 Retention'!A12:A26 -> 45505 | C12: =IFERROR('📊 Retention'!C12/'📊 Retention'!$C12,"") -> 1 | D12: =IFERROR('📊 Retention'!D12/'📊 Retention'!$C12,"") -> 0.85106383 | E12: =IFERROR('📊 Retention'!E12/'📊 Retention'!$C12,"") -> 0.74468085 | F12: =IFERROR('📊 Retention'!F12/'📊 Retention'!$C12,"") -> 0.63829787 | G12: =IFERROR('📊 Retention'!G12/'📊 Retention'!$C12,"") -> 0.55319149 | H12: =IFERROR('📊 Retention'!H12/'📊 Retention'!$C12,"") -> 0.55319149 | I12: =IFERROR('📊 Retention'!I12/'📊 Retention'!$C12,"") -> 0.46808511 | J12: =IFERROR('📊 Retention'!J12/'📊 Retention'!$C12,"") -> 0.4893617 | K12: — | L12: — | M12: — | N12: —
A13: ='📊 Retention'!A13:A27 -> 45536 | C13: =IFERROR('📊 Retention'!C13/'📊 Retention'!$C13,"") -> 1 | D13: =IFERROR('📊 Retention'!D13/'📊 Retention'!$C13,"") -> 0.91176471 | E13: =IFERROR('📊 Retention'!E13/'📊 Retention'!$C13,"") -> 0.85294118 | F13: =IFERROR('📊 Retention'!F13/'📊 Retention'!$C13,"") -> 0.73529412 | G13: =IFERROR('📊 Retention'!G13/'📊 Retention'!$C13,"") -> 0.64705882 | H13: =IFERROR('📊 Retention'!H13/'📊 Retention'!$C13,"") -> 0.61764706 | I13: =IFERROR('📊 Retention'!I13/'📊 Retention'!$C13,"") -> 0.58823529 | J13: — | K13: — | L13: — | M13: — | N13: —
A14: ='📊 Retention'!A14:A28 -> 45566 | C14: =IFERROR('📊 Retention'!C14/'📊 Retention'!$C14,"") -> 1 | D14: =IFERROR('📊 Retention'!D14/'📊 Retention'!$C14,"") -> 0.90566038 | E14: =IFERROR('📊 Retention'!E14/'📊 Retention'!$C14,"") -> 0.83018868 | F14: =IFERROR('📊 Retention'!F14/'📊 Retention'!$C14,"") -> 0.77358491 | G14: =IFERROR('📊 Retention'!G14/'📊 Retention'!$C14,"") -> 0.75471698 | H14: =IFERROR('📊 Retention'!H14/'📊 Retention'!$C14,"") -> 0.71698113 | I14: — | J14: — | K14: — | L14: — | M14: — | N14: —
A15: ='📊 Retention'!A15:A29 -> 45597 | C15: =IFERROR('📊 Retention'!C15/'📊 Retention'!$C15,"") -> 1 | D15: =IFERROR('📊 Retention'!D15/'📊 Retention'!$C15,"") -> 0.88461538 | E15: =IFERROR('📊 Retention'!E15/'📊 Retention'!$C15,"") -> 0.75 | F15: =IFERROR('📊 Retention'!F15/'📊 Retention'!$C15,"") -> 0.65384615 | G15: =IFERROR('📊 Retention'!G15/'📊 Retention'!$C15,"") -> 0.63461538 | H15: — | I15: — | J15: — | K15: — | L15: — | M15: — | N15: —
A16: ='📊 Retention'!A16:A30 -> 45627 | C16: =IFERROR('📊 Retention'!C16/'📊 Retention'!$C16,"") -> 1 | D16: =IFERROR('📊 Retention'!D16/'📊 Retention'!$C16,"") -> 0.89583333 | E16: =IFERROR('📊 Retention'!E16/'📊 Retention'!$C16,"") -> 0.75 | F16: =IFERROR('📊 Retention'!F16/'📊 Retention'!$C16,"") -> 0.6875 | G16: — | H16: — | I16: — | J16: — | K16: — | L16: — | M16: — | N16: —
A17: ='📊 Retention'!A17:A31 -> 45658 | C17: =IFERROR('📊 Retention'!C17/'📊 Retention'!$C17,"") -> 1 | D17: =IFERROR('📊 Retention'!D17/'📊 Retention'!$C17,"") -> 0.8 | E17: =IFERROR('📊 Retention'!E17/'📊 Retention'!$C17,"") -> 0.84444444 | F17: — | G17: — | H17: — | I17: — | J17: — | K17: — | L17: — | M17: — | N17: —
A18: ='📊 Retention'!A18:A32 -> 45689 | C18: =IFERROR('📊 Retention'!C18/'📊 Retention'!$C18,"") -> 1 | D18: =IFERROR('📊 Retention'!D18/'📊 Retention'!$C18,"") -> 0.98113208 | E18: — | F18: — | G18: — | H18: — | I18: — | J18: — | K18: — | L18: — | M18: — | N18: —
A19: ='📊 Retention'!A19:A33 -> 45717 | C19: =IFERROR('📊 Retention'!C19/'📊 Retention'!$C19,"") -> 1 | D19: — | E19: — | F19: — | G19: — | H19: — | I19: — | J19: — | K19: — | L19: — | M19: — | N19: —
A20: Середнє | C20: =IFERROR(AVERAGEIF(C5:C19,"<>"),"") -> 1 | D20: =IFERROR(AVERAGEIF(D5:D19,"<>"),"") -> 0.89350366 | E20: =IFERROR(AVERAGEIF(E5:E19,"<>"),"") -> 0.79630239 | F20: =IFERROR(AVERAGEIF(F5:F19,"<>"),"") -> 0.70655902 | G20: =IFERROR(AVERAGEIF(G5:G19,"<>"),"") -> 0.66658243 | H20: =IFERROR(AVERAGEIF(H5:H19,"<>"),"") -> 0.64533289 | I20: =IFERROR(AVERAGEIF(I5:I19,"<>"),"") -> 0.58602634 | J20: =IFERROR(AVERAGEIF(J5:J19,"<>"),"") -> 0.56586929 | ... N20: =IFERROR(AVERAGEIF(N5:N19,"<>"),"") -> 0.54216435
A23: 2. Яка когорта має найвищий retention на 6-му місяці?
A24: Найвищий retention на 6-му місяці (M+5) спостерігається для когорти 2024-04 = 75%. LTV цієї когорти становить $98.28, що також є найвищим показником для 6го місяця. Це був вдалий період для залучення клієнтів, або сталисьпевні якісні зміни в продукті на початку 2024 року.

Sheet 💰 LTV
A2: 💰 Revenue per User та LTV — заповни формулами
A4: Блок 1: ARPU — виручка на одного клієнта за окремий місяць
A5: Когорта | B5: Size | C5: ARPU М+0 | D5: ARPU М+1 | E5: ARPU М+2 | F5: ARPU М+3 | G5: ARPU М+4 | H5: ARPU М+5 | I5: ARPU М+6 | J5: ARPU М+7 | K5: ARPU М+8 | L5: ARPU М+9 | M5: ARPU М+10 | N5: ARPU М+11 | O5: Середнє
A6: ='📊 Retention'!A5 -> 45292 | B6: ='📊 Retention'!$B5 -> 25 | C6: =IFERROR(SUMIFS('👥 Клієнти'!$S$5:$S$606,'👥 Клієнти'!$C$5:$C$606,$A6)/$B6,"") -> 16.7916 | D6: =IFERROR(SUMIFS('👥 Клієнти'!$T$5:$T$606,'👥 Клієнти'!$C$5:$C$606,$A6)/$B6,"") -> 19.1904 | E6: =IFERROR(SUMIFS('👥 Клієнти'!$U$5:$U$606,'👥 Клієнти'!$C$5:$C$606,$A6)/$B6,"") -> 15.1924 | F6: =IFERROR(SUMIFS('👥 Клієнти'!$V$5:$V$606,'👥 Клієнти'!$C$5:$C$606,$A6)/$B6,"") -> 13.5932 | G6: =IFERROR(SUMIFS('👥 Клієнти'!$W$5:$W$606,'👥 Клієнти'!$C$5:$C$606,$A6)/$B6,"") -> 12.7936 | H6: =IFERROR(SUMIFS('👥 Клієнти'!$X$5:$X$606,'👥 Клієнти'!$C$5:$C$606,$A6)/$B6,"") -> 11.994 | I6: =IFERROR(SUMIFS('👥 Клієнти'!$Y$5:$Y$606,'👥 Клієнти'!$C$5:$C$606,$A6)/$B6,"") -> 10.3948 | J6: =IFERROR(SUMIFS('👥 Клієнти'!$Z$5:$Z$606,'👥 Клієнти'!$C$5:$C$606,$A6)/$B6,"") -> 10.3948 | K6: =IFERROR(SUMIFS('👥 Клієнти'!$AA$5:$AA$606,'👥 Клієнти'!$C$5:$C$606,$A6)/$B6,"") -> 10.3948 | L6: =IFERROR(SUMIFS('👥 Клієнти'!$AB$5:$AB$606,'👥 Клієнти'!$C$5:$C$606,$A6)/$B6,"") -> 9.5952 | M6: =IFERROR(SUMIFS('👥 Клієнти'!$AC$5:$AC$606,'👥 Клієнти'!$C$5:$C$606,$A6)/$B6,"") -> 9.5952 | N6: =IFERROR(SUMIFS('👥 Клієнти'!$AD$5:$AD$606,'👥 Клієнти'!$C$5:$C$606,$A6)/$B6,"") -> 9.5952 | O6: =IFERROR(AVERAGE(C6:N6),"") -> 12.460433
A7: ='📊 Retention'!A6 -> 45323 | B7: ='📊 Retention'!$B6 -> 27 | C7: =IFERROR(SUMIFS('👥 Клієнти'!$S$5:$S$606,'👥 Клієнти'!$C$5:$C$606,$A7)/$B7,"") -> 11.105556 | D7: =IFERROR(SUMIFS('👥 Клієнти'!$T$5:$T$606,'👥 Клієнти'!$C$5:$C$606,$A7)/$B7,"") -> 19.99 | E7: =IFERROR(SUMIFS('👥 Клієнти'!$U$5:$U$606,'👥 Клієнти'!$C$5:$C$606,$A7)/$B7,"") -> 17.028519 | F7: =IFERROR(SUMIFS('👥 Клієнти'!$V$5:$V$606,'👥 Клієнти'!$C$5:$C$606,$A7)/$B7,"") -> 15.547778 | G7: =IFERROR(SUMIFS('👥 Клієнти'!$W$5:$W$606,'👥 Клієнти'!$C$5:$C$606,$A7)/$B7,"") -> 13.326667 | H7: =IFERROR(SUMIFS('👥 Клієнти'!$X$5:$X$606,'👥 Клієнти'!$C$5:$C$606,$A7)/$B7,"") -> 13.326667 | I7: =IFERROR(SUMIFS('👥 Клієнти'!$Y$5:$Y$606,'👥 Клієнти'!$C$5:$C$606,$A7)/$B7,"") -> 13.326667 | J7: =IFERROR(SUMIFS('👥 Клієнти'!$Z$5:$Z$606,'👥 Клієнти'!$C$5:$C$606,$A7)/$B7,"") -> 11.105556 | K7: =IFERROR(SUMIFS('👥 Клієнти'!$AA$5:$AA$606,'👥 Клієнти'!$C$5:$C$606,$A7)/$B7,"") -> 14.067037 | L7: =IFERROR(SUMIFS('👥 Клієнти'!$AB$5:$AB$606,'👥 Клієнти'!$C$5:$C$606,$A7)/$B7,"") -> 10.365185 | M7: =IFERROR(SUMIFS('👥 Клієнти'!$AC$5:$AC$606,'👥 Клієнти'!$C$5:$C$606,$A7)/$B7,"") -> 11.105556 | N7: =IFERROR(SUMIFS('👥 Клієнти'!$AD$5:$AD$606,'👥 Клієнти'!$C$5:$C$606,$A7)/$B7,"") -> 10.365185 | O7: =IFERROR(AVERAGE(C7:N7),"") -> 13.388364
A8: ='📊 Retention'!A7 -> 45352 | B8: ='📊 Retention'!$B7 -> 32 | C8: =IFERROR(SUMIFS('👥 Клієнти'!$S$5:$S$606,'👥 Клієнти'!$C$5:$C$606,$A8)/$B8,"") -> 16.241875 | D8: =IFERROR(SUMIFS('👥 Клієнти'!$T$5:$T$606,'👥 Клієнти'!$C$5:$C$606,$A8)/$B8,"") -> 18.115938 | E8: =IFERROR(SUMIFS('👥 Клієнти'!$U$5:$U$606,'👥 Клієнти'!$C$5:$C$606,$A8)/$B8,"") -> 18.115938 | F8: =IFERROR(SUMIFS('👥 Клієнти'!$V$5:$V$606,'👥 Клієнти'!$C$5:$C$606,$A8)/$B8,"") -> 14.367812 | G8: =IFERROR(SUMIFS('👥 Клієнти'!$W$5:$W$606,'👥 Клієнти'!$C$5:$C$606,$A8)/$B8,"") -> 14.9925 | H8: =IFERROR(SUMIFS('👥 Клієнти'!$X$5:$X$606,'👥 Клієнти'!$C$5:$C$606,$A8)/$B8,"") -> 13.743125 | I8: =IFERROR(SUMIFS('👥 Клієнти'!$Y$5:$Y$606,'👥 Клієнти'!$C$5:$C$606,$A8)/$B8,"") -> 11.869063 | J8: =IFERROR(SUMIFS('👥 Клієнти'!$Z$5:$Z$606,'👥 Клієнти'!$C$5:$C$606,$A8)/$B8,"") -> 11.869063 | K8: =IFERROR(SUMIFS('👥 Клієнти'!$AA$5:$AA$606,'👥 Клієнти'!$C$5:$C$606,$A8)/$B8,"") -> 11.244375 | L8: =IFERROR(SUMIFS('👥 Клієнти'!$AB$5:$AB$606,'👥 Клієнти'!$C$5:$C$606,$A8)/$B8,"") -> 11.244375 | M8: =IFERROR(SUMIFS('👥 Клієнти'!$AC$5:$AC$606,'👥 Клієнти'!$C$5:$C$606,$A8)/$B8,"") -> 11.244375 | N8: =IFERROR(SUMIFS('👥 Клієнти'!$AD$5:$AD$606,'👥 Клієнти'!$C$5:$C$606,$A8)/$B8,"") -> 10.619687 | O8: =IFERROR(AVERAGE(C8:N8),"") -> 13.63901
A9: ='📊 Retention'!A8 -> 45383 | B9: ='📊 Retention'!$B8 -> 36 | C9: =IFERROR(SUMIFS('👥 Клієнти'!$S$5:$S$606,'👥 Клієнти'!$C$5:$C$606,$A9)/$B9,"") -> 13.881944 | D9: =IFERROR(SUMIFS('👥 Клієнти'!$T$5:$T$606,'👥 Клієнти'!$C$5:$C$606,$A9)/$B9,"") -> 19.434722 | E9: =IFERROR(SUMIFS('👥 Клієнти'!$U$5:$U$606,'👥 Клієнти'!$C$5:$C$606,$A9)/$B9,"") -> 16.658333 | F9: =IFERROR(SUMIFS('👥 Клієнти'!$V$5:$V$606,'👥 Клієнти'!$C$5:$C$606,$A9)/$B9,"") -> 16.103056 | G9: =IFERROR(SUMIFS('👥 Клієнти'!$W$5:$W$606,'👥 Клієнти'!$C$5:$C$606,$A9)/$B9,"") -> 17.213611 | H9: =IFERROR(SUMIFS('👥 Клієнти'!$X$5:$X$606,'👥 Клієнти'!$C$5:$C$606,$A9)/$B9,"") -> 14.9925 | I9: =IFERROR(SUMIFS('👥 Клієнти'!$Y$5:$Y$606,'👥 Клієнти'!$C$5:$C$606,$A9)/$B9,"") -> 14.437222 | J9: =IFERROR(SUMIFS('👥 Клієнти'!$Z$5:$Z$606,'👥 Клієнти'!$C$5:$C$606,$A9)/$B9,"") -> 13.881944 | K9: =IFERROR(SUMIFS('👥 Клієнти'!$AA$5:$AA$606,'👥 Клієнти'!$C$5:$C$606,$A9)/$B9,"") -> 13.326667 | L9: =IFERROR(SUMIFS('👥 Клієнти'!$AB$5:$AB$606,'👥 Клієнти'!$C$5:$C$606,$A9)/$B9,"") -> 12.771389 | M9: =IFERROR(SUMIFS('👥 Клієнти'!$AC$5:$AC$606,'👥 Клієнти'!$C$5:$C$606,$A9)/$B9,"") -> 12.216111 | N9: =IFERROR(SUMIFS('👥 Клієнти'!$AD$5:$AD$606,'👥 Клієнти'!$C$5:$C$606,$A9)/$B9,"") -> 13.326667 | O9: =IFERROR(AVERAGE(C9:N9),"") -> 14.853681
A10: ='📊 Retention'!A9 -> 45413 | B10: ='📊 Retention'!$B9 -> 32 | C10: =IFERROR(SUMIFS('👥 Клієнти'!$S$5:$S$606,'👥 Клієнти'!$C$5:$C$606,$A10)/$B10,"") -> 17.49125 | D10: =IFERROR(SUMIFS('👥 Клієнти'!$T$5:$T$606,'👥 Клієнти'!$C$5:$C$606,$A10)/$B10,"") -> 15.617188 | E10: =IFERROR(SUMIFS('👥 Клієнти'!$U$5:$U$606,'👥 Клієнти'!$C$5:$C$606,$A10)/$B10,"") -> 14.367812 | F10: =IFERROR(SUMIFS('👥 Клієнти'!$V$5:$V$606,'👥 Клієнти'!$C$5:$C$606,$A10)/$B10,"") -> 13.118438 | G10: =IFERROR(SUMIFS('👥 Клієнти'!$W$5:$W$606,'👥 Клієнти'!$C$5:$C$606,$A10)/$B10,"") -> 12.49375 | H10: =IFERROR(SUMIFS('👥 Клієнти'!$X$5:$X$606,'👥 Клієнти'!$C$5:$C$606,$A10)/$B10,"") -> 12.49375 | I10: =IFERROR(SUMIFS('👥 Клієнти'!$Y$5:$Y$606,'👥 Клієнти'!$C$5:$C$606,$A10)/$B10,"") -> 11.244375 | J10: =IFERROR(SUMIFS('👥 Клієнти'!$Z$5:$Z$606,'👥 Клієнти'!$C$5:$C$606,$A10)/$B10,"") -> 11.244375 | K10: =IFERROR(SUMIFS('👥 Клієнти'!$AA$5:$AA$606,'👥 Клієнти'!$C$5:$C$606,$A10)/$B10,"") -> 12.49375 | L10: =IFERROR(SUMIFS('👥 Клієнти'!$AB$5:$AB$606,'👥 Клієнти'!$C$5:$C$606,$A10)/$B10,"") -> 9.995 | M10: =IFERROR(SUMIFS('👥 Клієнти'!$AC$5:$AC$606,'👥 Клієнти'!$C$5:$C$606,$A10)/$B10,"") -> 11.244375 | N10: — | O10: =IFERROR(AVERAGE(C10:N10),"") -> 12.891278
A11: ='📊 Retention'!A10 -> 45444 | B11: ='📊 Retention'!$B10 -> 27 | C11: =IFERROR(SUMIFS('👥 Клієнти'!$S$5:$S$606,'👥 Клієнти'!$C$5:$C$606,$A11)/$B11,"") -> 14.067037 | D11: =IFERROR(SUMIFS('👥 Клієнти'!$T$5:$T$606,'👥 Клієнти'!$C$5:$C$606,$A11)/$B11,"") -> 19.24963 | E11: =IFERROR(SUMIFS('👥 Клієнти'!$U$5:$U$606,'👥 Клієнти'!$C$5:$C$606,$A11)/$B11,"") -> 14.807407 | F11: =IFERROR(SUMIFS('👥 Клієнти'!$V$5:$V$606,'👥 Клієнти'!$C$5:$C$606,$A11)/$B11,"") -> 12.586296 | G11: =IFERROR(SUMIFS('👥 Клієнти'!$W$5:$W$606,'👥 Клієнти'!$C$5:$C$606,$A11)/$B11,"") -> 12.586296 | H11: =IFERROR(SUMIFS('👥 Клієнти'!$X$5:$X$606,'👥 Клієнти'!$C$5:$C$606,$A11)/$B11,"") -> 11.845926 | I11: =IFERROR(SUMIFS('👥 Клієнти'!$Y$5:$Y$606,'👥 Клієнти'!$C$5:$C$606,$A11)/$B11,"") -> 13.326667 | J11: =IFERROR(SUMIFS('👥 Клієнти'!$Z$5:$Z$606,'👥 Клієнти'!$C$5:$C$606,$A11)/$B11,"") -> 12.586296 | K11: =IFERROR(SUMIFS('👥 Клієнти'!$AA$5:$AA$606,'👥 Клієнти'!$C$5:$C$606,$A11)/$B11,"") -> 9.6248148 | L11: =IFERROR(SUMIFS('👥 Клієнти'!$AB$5:$AB$606,'👥 Клієнти'!$C$5:$C$606,$A11)/$B11,"") -> 12.586296 | M11: — | N11: — | O11: =IFERROR(AVERAGE(C11:N11),"") -> 13.326667
A12: ='📊 Retention'!A11 -> 45474 | B12: ='📊 Retention'!$B11 -> 40 | C12: =IFERROR(SUMIFS('👥 Клієнти'!$S$5:$S$606,'👥 Клієнти'!$C$5:$C$606,$A12)/$B12,"") -> 13.993 | D12: =IFERROR(SUMIFS('👥 Клієнти'!$T$5:$T$606,'👥 Клієнти'!$C$5:$C$606,$A12)/$B12,"") -> 18.9905 | E12: =IFERROR(SUMIFS('👥 Клієнти'!$U$5:$U$606,'👥 Клієнти'!$C$5:$C$606,$A12)/$B12,"") -> 15.992 | F12: =IFERROR(SUMIFS('👥 Клієнти'!$V$5:$V$606,'👥 Клієнти'!$C$5:$C$606,$A12)/$B12,"") -> 15.49225 | G12: =IFERROR(SUMIFS('👥 Клієнти'!$W$5:$W$606,'👥 Клієнти'!$C$5:$C$606,$A12)/$B12,"") -> 14.49275 | H12: =IFERROR(SUMIFS('👥 Клієнти'!$X$5:$X$606,'👥 Клієнти'!$C$5:$C$606,$A12)/$B12,"") -> 13.993 | I12: =IFERROR(SUMIFS('👥 Клієнти'!$Y$5:$Y$606,'👥 Клієнти'!$C$5:$C$606,$A12)/$B12,"") -> 13.49325 | J12: =IFERROR(SUMIFS('👥 Клієнти'!$Z$5:$Z$606,'👥 Клієнти'!$C$5:$C$606,$A12)/$B12,"") -> 10.9945 | K12: =IFERROR(SUMIFS('👥 Клієнти'!$AA$5:$AA$606,'👥 Клієнти'!$C$5:$C$606,$A12)/$B12,"") -> 12.9935 | L12: — | M12: — | N12: — | O12: =IFERROR(AVERAGE(C12:N12),"") -> 14.49275
A13: ='📊 Retention'!A12 -> 45505 | B13: ='📊 Retention'!$B12 -> 47 | C13: =IFERROR(SUMIFS('👥 Клієнти'!$S$5:$S$606,'👥 Клієнти'!$C$5:$C$606,$A13)/$B13,"") -> 16.587447 | D13: =IFERROR(SUMIFS('👥 Клієнти'!$T$5:$T$606,'👥 Клієнти'!$C$5:$C$606,$A13)/$B13,"") -> 17.012766 | E13: =IFERROR(SUMIFS('👥 Клієнти'!$U$5:$U$606,'👥 Клієнти'!$C$5:$C$606,$A13)/$B13,"") -> 14.88617 | F13: =IFERROR(SUMIFS('👥 Клієнти'!$V$5:$V$606,'👥 Клієнти'!$C$5:$C$606,$A13)/$B13,"") -> 12.759574 | G13: =IFERROR(SUMIFS('👥 Клієнти'!$W$5:$W$606,'👥 Клієнти'!$C$5:$C$606,$A13)/$B13,"") -> 11.908936 | H13: =IFERROR(SUMIFS('👥 Клієнти'!$X$5:$X$606,'👥 Клієнти'!$C$5:$C$606,$A13)/$B13,"") -> 11.483617 | I13: =IFERROR(SUMIFS('👥 Клієнти'!$Y$5:$Y$606,'👥 Клієнти'!$C$5:$C$606,$A13)/$B13,"") -> 9.3570213 | J13: =IFERROR(SUMIFS('👥 Клієнти'!$Z$5:$Z$606,'👥 Клієнти'!$C$5:$C$606,$A13)/$B13,"") -> 10.20766 | K13: — | L13: — | M13: — | N13: — | O13: =IFERROR(AVERAGE(C13:N13),"") -> 13.025399
A14: ='📊 Retention'!A13 -> 45536 | B14: ='📊 Retention'!$B13 -> 34 | C14: =IFERROR(SUMIFS('👥 Клієнти'!$S$5:$S$606,'👥 Клієнти'!$C$5:$C$606,$A14)/$B14,"") -> 17.050294 | D14: =IFERROR(SUMIFS('👥 Клієнти'!$T$5:$T$606,'👥 Клієнти'!$C$5:$C$606,$A14)/$B14,"") -> 18.814118 | E14: =IFERROR(SUMIFS('👥 Клієнти'!$U$5:$U$606,'👥 Клієнти'!$C$5:$C$606,$A14)/$B14,"") -> 17.050294 | F14: =IFERROR(SUMIFS('👥 Клієнти'!$V$5:$V$606,'👥 Клієнти'!$C$5:$C$606,$A14)/$B14,"") -> 14.698529 | G14: =IFERROR(SUMIFS('👥 Клієнти'!$W$5:$W$606,'👥 Клієнти'!$C$5:$C$606,$A14)/$B14,"") -> 12.934706 | H14: =IFERROR(SUMIFS('👥 Клієнти'!$X$5:$X$606,'👥 Клієнти'!$C$5:$C$606,$A14)/$B14,"") -> 12.346765 | I14: =IFERROR(SUMIFS('👥 Клієнти'!$Y$5:$Y$606,'👥 Клієнти'!$C$5:$C$606,$A14)/$B14,"") -> 11.758824 | J14: — | K14: — | L14: — | M14: — | N14: — | O14: =IFERROR(AVERAGE(C14:N14),"") -> 14.950504
A15: ='📊 Retention'!A14 -> 45566 | B15: ='📊 Retention'!$B14 -> 53 | C15: =IFERROR(SUMIFS('👥 Клієнти'!$S$5:$S$606,'👥 Клієнти'!$C$5:$C$606,$A15)/$B15,"") -> 16.595472 | D15: =IFERROR(SUMIFS('👥 Клієнти'!$T$5:$T$606,'👥 Клієнти'!$C$5:$C$606,$A15)/$B15,"") -> 18.104151 | E15: =IFERROR(SUMIFS('👥 Клієнти'!$U$5:$U$606,'👥 Клієнти'!$C$5:$C$606,$A15)/$B15,"") -> 16.595472 | F15: =IFERROR(SUMIFS('👥 Клієнти'!$V$5:$V$606,'👥 Клієнти'!$C$5:$C$606,$A15)/$B15,"") -> 15.463962 | G15: =IFERROR(SUMIFS('👥 Клієнти'!$W$5:$W$606,'👥 Клієнти'!$C$5:$C$606,$A15)/$B15,"") -> 15.086792 | H15: =IFERROR(SUMIFS('👥 Клієнти'!$X$5:$X$606,'👥 Клієнти'!$C$5:$C$606,$A15)/$B15,"") -> 14.332453 | I15: — | J15: — | K15: — | L15: — | M15: — | N15: — | O15: =IFERROR(AVERAGE(C15:N15),"") -> 16.029717
A16: ='📊 Retention'!A15 -> 45597 | B16: ='📊 Retention'!$B15 -> 52 | C16: =IFERROR(SUMIFS('👥 Клієнти'!$S$5:$S$606,'👥 Клієнти'!$C$5:$C$606,$A16)/$B16,"") -> 16.145769 | D16: =IFERROR(SUMIFS('👥 Клієнти'!$T$5:$T$606,'👥 Клієнти'!$C$5:$C$606,$A16)/$B16,"") -> 18.067885 | E16: =IFERROR(SUMIFS('👥 Клієнти'!$U$5:$U$606,'👥 Клієнти'!$C$5:$C$606,$A16)/$B16,"") -> 14.9925 | F16: =IFERROR(SUMIFS('👥 Клієнти'!$V$5:$V$606,'👥 Клієнти'!$C$5:$C$606,$A16)/$B16,"") -> 13.070385 | G16: =IFERROR(SUMIFS('👥 Клієнти'!$W$5:$W$606,'👥 Клієнти'!$C$5:$C$606,$A16)/$B16,"") -> 13.070385 | H16: — | I16: — | J16: — | K16: — | L16: — | M16: — | N16: — | O16: =IFERROR(AVERAGE(C16:N16),"") -> 15.069385
A17: ='📊 Retention'!A16 -> 45627 | B17: ='📊 Retention'!$B16 -> 48 | C17: =IFERROR(SUMIFS('👥 Клієнти'!$S$5:$S$606,'👥 Клієнти'!$C$5:$C$606,$A17)/$B17,"") -> 16.241875 | D17: =IFERROR(SUMIFS('👥 Клієнти'!$T$5:$T$606,'👥 Клієнти'!$C$5:$C$606,$A17)/$B17,"") -> 19.157083 | E17: =IFERROR(SUMIFS('👥 Клієнти'!$U$5:$U$606,'👥 Клієнти'!$C$5:$C$606,$A17)/$B17,"") -> 14.9925 | F17: =IFERROR(SUMIFS('👥 Клієнти'!$V$5:$V$606,'👥 Клієнти'!$C$5:$C$606,$A17)/$B17,"") -> 13.743125 | G17: — | H17: — | I17: — | J17: — | K17: — | L17: — | M17: — | N17: — | O17: =IFERROR(AVERAGE(C17:N17),"") -> 16.033646
A18: ='📊 Retention'!A17 -> 45658 | B18: ='📊 Retention'!$B17 -> 45 | C18: =IFERROR(SUMIFS('👥 Клієнти'!$S$5:$S$606,'👥 Клієнти'!$C$5:$C$606,$A18)/$B18,"") -> 14.659333 | D18: =IFERROR(SUMIFS('👥 Клієнти'!$T$5:$T$606,'👥 Клієнти'!$C$5:$C$606,$A18)/$B18,"") -> 15.992 | E18: =IFERROR(SUMIFS('👥 Клієнти'!$U$5:$U$606,'👥 Клієнти'!$C$5:$C$606,$A18)/$B18,"") -> 18.213111 | F18: — | G18: — | H18: — | I18: — | J18: — | K18: — | L18: — | M18: — | N18: — | O18: =IFERROR(AVERAGE(C18:N18),"") -> 16.288148
A19: ='📊 Retention'!A18 -> 45689 | B19: ='📊 Retention'!$B18 -> 53 | C19: =IFERROR(SUMIFS('👥 Клієнти'!$S$5:$S$606,'👥 Клієнти'!$C$5:$C$606,$A19)/$B19,"") -> 15.463962 | D19: =IFERROR(SUMIFS('👥 Клієнти'!$T$5:$T$606,'👥 Клієнти'!$C$5:$C$606,$A19)/$B19,"") -> 19.99 | E19: — | F19: — | G19: — | H19: — | I19: — | J19: — | K19: — | L19: — | M19: — | N19: — | O19: =IFERROR(AVERAGE(C19:N19),"") -> 17.726981
A20: ='📊 Retention'!A19 -> 45717 | B20: ='📊 Retention'!$B19 -> 51 | C20: =IFERROR(SUMIFS('👥 Клієнти'!$S$5:$S$606,'👥 Клієнти'!$C$5:$C$606,$A20)/$B20,"") -> 19.99 | D20: — | E20: — | F20: — | G20: — | H20: — | I20: — | J20: — | K20: — | L20: — | M20: — | N20: — | O20: =IFERROR(AVERAGE(C20:N20),"") -> 19.99
A21: Середнє | C21: =IFERROR(AVERAGEIF(C6:C20,"<>"),"") -> 15.753761 | D21: =IFERROR(AVERAGEIF(D6:D20,"<>"),"") -> 18.409027 | E21: =IFERROR(AVERAGEIF(E6:E20,"<>"),"") -> 16.06865 | F21: =IFERROR(AVERAGEIF(F6:F20,"<>"),"") -> 14.212034 | G21: =IFERROR(AVERAGEIF(G6:G20,"<>"),"") -> 13.718181 | H21: =IFERROR(AVERAGEIF(H6:H20,"<>"),"") -> 13.05518 | I21: =IFERROR(AVERAGEIF(I6:I20,"<>"),"") -> 12.13421 | J21: =IFERROR(AVERAGEIF(J6:J20,"<>"),"") -> 11.535524 | ... O21: =IFERROR(AVERAGEIF(O6:O20,"<>"),"") -> 14.944398
A24: Блок 2: LTV — кумулятивна сума ARPU за М+0..М+N | Q24: 3. Який LTV М+6 у середньому по когортах?
A25: Когорта | B25: Size | C25: LTV М+0 | D25: LTV М+1 | E25: LTV М+2 | F25: LTV М+3 | G25: LTV М+4 | H25: LTV М+5 | I25: LTV М+6 | J25: LTV М+7 | K25: LTV М+8 | L25: LTV М+9 | M25: LTV М+10 | N25: LTV М+11 | O25: LTV Total | Q25: Середній LTV для М+6 становить $102,68. Для Google Ads і Facebook Ads це перевищує CAC, тому виходть що клієнт за цей час себе встигає окупити.
A26: =A6 -> 45292 | B26: ='📊 Retention'!$B5 -> 25 | C26: =IFERROR(C6,"") -> 16.7916 | D26: =IFERROR(C26+D6,"") -> 35.982 | E26: =IFERROR(D26+E6,"") -> 51.1744 | F26: =IFERROR(E26+F6,"") -> 64.7676 | G26: =IFERROR(F26+G6,"") -> 77.5612 | H26: =IFERROR(G26+H6,"") -> 89.5552 | I26: =IFERROR(H26+I6,"") -> 99.95 | J26: =IFERROR(I26+J6,"") -> 110.3448 | K26: =IFERROR(J26+K6,"") -> 120.7396 | ... N26: =IFERROR(M26+N6,"") -> 149.5252 | O26: =IFERROR(SUM(C6:N6),"") -> 149.5252
A27: =A7 -> 45323 | B27: ='📊 Retention'!$B6 -> 27 | C27: =IFERROR(C7,"") -> 11.105556 | D27: =IFERROR(C27+D7,"") -> 31.095556 | E27: =IFERROR(D27+E7,"") -> 48.124074 | F27: =IFERROR(E27+F7,"") -> 63.671852 | G27: =IFERROR(F27+G7,"") -> 76.998519 | H27: =IFERROR(G27+H7,"") -> 90.325185 | I27: =IFERROR(H27+I7,"") -> 103.65185 | J27: =IFERROR(I27+J7,"") -> 114.75741 | K27: =IFERROR(J27+K7,"") -> 128.82444 | ... N27: =IFERROR(M27+N7,"") -> 160.66037 | O27: =IFERROR(SUM(C7:N7),"") -> 160.66037
A28: =A8 -> 45352 | B28: ='📊 Retention'!$B7 -> 32 | C28: =IFERROR(C8,"") -> 16.241875 | D28: =IFERROR(C28+D8,"") -> 34.357813 | E28: =IFERROR(D28+E8,"") -> 52.47375 | F28: =IFERROR(E28+F8,"") -> 66.841562 | G28: =IFERROR(F28+G8,"") -> 81.834063 | H28: =IFERROR(G28+H8,"") -> 95.577187 | I28: =IFERROR(H28+I8,"") -> 107.44625 | J28: =IFERROR(I28+J8,"") -> 119.31531 | K28: =IFERROR(J28+K8,"") -> 130.55969 | ... N28: =IFERROR(M28+N8,"") -> 163.66813 | O28: =IFERROR(SUM(C8:N8),"") -> 163.66813
A29: =A9 -> 45383 | B29: ='📊 Retention'!$B8 -> 36 | C29: =IFERROR(C9,"") -> 13.881944 | D29: =IFERROR(C29+D9,"") -> 33.316667 | E29: =IFERROR(D29+E9,"") -> 49.975 | F29: =IFERROR(E29+F9,"") -> 66.078056 | G29: =IFERROR(F29+G9,"") -> 83.291667 | H29: =IFERROR(G29+H9,"") -> 98.284167 | I29: =IFERROR(H29+I9,"") -> 112.72139 | J29: =IFERROR(I29+J9,"") -> 126.60333 | K29: =IFERROR(J29+K9,"") -> 139.93 | ... N29: =IFERROR(M29+N9,"") -> 178.24417 | O29: =IFERROR(SUM(C9:N9),"") -> 178.24417
A30: =A10 -> 45413 | B30: ='📊 Retention'!$B9 -> 32 | C30: =IFERROR(C10,"") -> 17.49125 | D30: =IFERROR(C30+D10,"") -> 33.108438 | E30: =IFERROR(D30+E10,"") -> 47.47625 | F30: =IFERROR(E30+F10,"") -> 60.594687 | G30: =IFERROR(F30+G10,"") -> 73.088437 | H30: =IFERROR(G30+H10,"") -> 85.582188 | I30: =IFERROR(H30+I10,"") -> 96.826562 | J30: =IFERROR(I30+J10,"") -> 108.07094 | K30: =IFERROR(J30+K10,"") -> 120.56469 | ... N30: =IFERROR(M30+N10,"") | O30: =IFERROR(SUM(C10:N10),"") -> 141.80406
A31: =A11 -> 45444 | B31: ='📊 Retention'!$B10 -> 27 | C31: =IFERROR(C11,"") -> 14.067037 | D31: =IFERROR(C31+D11,"") -> 33.316667 | E31: =IFERROR(D31+E11,"") -> 48.124074 | F31: =IFERROR(E31+F11,"") -> 60.71037 | G31: =IFERROR(F31+G11,"") -> 73.296667 | H31: =IFERROR(G31+H11,"") -> 85.142593 | I31: =IFERROR(H31+I11,"") -> 98.469259 | J31: =IFERROR(I31+J11,"") -> 111.05556 | K31: =IFERROR(J31+K11,"") -> 120.68037 | ... N31: =IFERROR(M31+N11,"") | O31: =IFERROR(SUM(C11:N11),"") -> 133.26667
A32: =A12 -> 45474 | B32: ='📊 Retention'!$B11 -> 40 | C32: =IFERROR(C12,"") -> 13.993 | D32: =IFERROR(C32+D12,"") -> 32.9835 | E32: =IFERROR(D32+E12,"") -> 48.9755 | F32: =IFERROR(E32+F12,"") -> 64.46775 | G32: =IFERROR(F32+G12,"") -> 78.9605 | H32: =IFERROR(G32+H12,"") -> 92.9535 | I32: =IFERROR(H32+I12,"") -> 106.44675 | J32: =IFERROR(I32+J12,"") -> 117.44125 | K32: =IFERROR(J32+K12,"") -> 130.43475 | ... N32: =IFERROR(M32+N12,"") | O32: =IFERROR(SUM(C12:N12),"") -> 130.43475
A33: =A13 -> 45505 | B33: ='📊 Retention'!$B12 -> 47 | C33: =IFERROR(C13,"") -> 16.587447 | D33: =IFERROR(C33+D13,"") -> 33.600213 | E33: =IFERROR(D33+E13,"") -> 48.486383 | F33: =IFERROR(E33+F13,"") -> 61.245957 | G33: =IFERROR(F33+G13,"") -> 73.154894 | H33: =IFERROR(G33+H13,"") -> 84.638511 | I33: =IFERROR(H33+I13,"") -> 93.995532 | J33: =IFERROR(I33+J13,"") -> 104.20319 | K33: =IFERROR(J33+K13,"") | ... N33: =IFERROR(M33+N13,"") | O33: =IFERROR(SUM(C13:N13),"") -> 104.20319
A34: =A14 -> 45536 | B34: ='📊 Retention'!$B13 -> 34 | C34: =IFERROR(C14,"") -> 17.050294 | D34: =IFERROR(C34+D14,"") -> 35.864412 | E34: =IFERROR(D34+E14,"") -> 52.914706 | F34: =IFERROR(E34+F14,"") -> 67.613235 | G34: =IFERROR(F34+G14,"") -> 80.547941 | H34: =IFERROR(G34+H14,"") -> 92.894706 | I34: =IFERROR(H34+I14,"") -> 104.65353 | J34: =IFERROR(I34+J14,"") | K34: =IFERROR(J34+K14,"") | ... N34: =IFERROR(M34+N14,"") | O34: =IFERROR(SUM(C14:N14),"") -> 104.65353
A35: =A15 -> 45566 | B35: ='📊 Retention'!$B14 -> 53 | C35: =IFERROR(C15,"") -> 16.595472 | D35: =IFERROR(C35+D15,"") -> 34.699623 | E35: =IFERROR(D35+E15,"") -> 51.295094 | F35: =IFERROR(E35+F15,"") -> 66.759057 | G35: =IFERROR(F35+G15,"") -> 81.845849 | H35: =IFERROR(G35+H15,"") -> 96.178302 | I35: =IFERROR(H35+I15,"") | J35: =IFERROR(I35+J15,"") | K35: =IFERROR(J35+K15,"") | ... N35: =IFERROR(M35+N15,"") | O35: =IFERROR(SUM(C15:N15),"") -> 96.178302
A36: =A16 -> 45597 | B36: ='📊 Retention'!$B15 -> 52 | C36: =IFERROR(C16,"") -> 16.145769 | D36: =IFERROR(C36+D16,"") -> 34.213654 | E36: =IFERROR(D36+E16,"") -> 49.206154 | F36: =IFERROR(E36+F16,"") -> 62.276538 | G36: =IFERROR(F36+G16,"") -> 75.346923 | H36: =IFERROR(G36+H16,"") | I36: =IFERROR(H36+I16,"") | J36: =IFERROR(I36+J16,"") | K36: =IFERROR(J36+K16,"") | ... N36: =IFERROR(M36+N16,"") | O36: =IFERROR(SUM(C16:N16),"") -> 75.346923
A37: =A17 -> 45627 | B37: ='📊 Retention'!$B16 -> 48 | C37: =IFERROR(C17,"") -> 16.241875 | D37: =IFERROR(C37+D17,"") -> 35.398958 | E37: =IFERROR(D37+E17,"") -> 50.391458 | F37: =IFERROR(E37+F17,"") -> 64.134583 | G37: =IFERROR(F37+G17,"") | H37: =IFERROR(G37+H17,"") | I37: =IFERROR(H37+I17,"") | J37: =IFERROR(I37+J17,"") | K37: =IFERROR(J37+K17,"") | ... N37: =IFERROR(M37+N17,"") | O37: =IFERROR(SUM(C17:N17),"") -> 64.134583
... A40: =A20 -> 45717 | B40: ='📊 Retention'!$B19 -> 51 | C40: =IFERROR(C20,"") -> 19.99 | D40: =IFERROR(C40+D20,"") | E40: =IFERROR(D40+E20,"") | F40: =IFERROR(E40+F20,"") | G40: =IFERROR(F40+G20,"") | H40: =IFERROR(G40+H20,"") | I40: =IFERROR(H40+I20,"") | J40: =IFERROR(I40+J20,"") | K40: =IFERROR(J40+K20,"") | ... N40: =IFERROR(M40+N20,"") | O40: =IFERROR(SUM(C20:N20),"") -> 19.99
A41: Середнє | C41: =IFERROR(AVERAGEIF(C26:C40,"<>"),"") -> 15.753761 | D41: =IFERROR(AVERAGEIF(D26:D40,"<>"),"") -> 33.8602 | E41: =IFERROR(AVERAGEIF(E26:E40,"<>"),"") -> 49.806253 | F41: =IFERROR(AVERAGEIF(F26:F40,"<>"),"") -> 64.096771 | G41: =IFERROR(AVERAGEIF(G26:G40,"<>"),"") -> 77.811514 | H41: =IFERROR(AVERAGEIF(H26:H40,"<>"),"") -> 91.113154 | I41: =IFERROR(AVERAGEIF(I26:I40,"<>"),"") -> 102.68457 | J41: =IFERROR(AVERAGEIF(J26:J40,"<>"),"") -> 113.97397 | ... O41: =IFERROR(AVERAGEIF(O26:O40,"<>"),"") -> 107.09522

Sheet ⭐ Бонус
L1: LTV (Lifetime Value) — середня виручка з 1го клієнта за весь час
A2: ⭐ Бонус — LTV vs CAC по каналах трафіку — заповніть формулами | L2: CAC (Customer Acquisition Cost) — скільки коштує залучити 1го клієнта
A3: LTV = середня виручка на клієнта по каналу. CAC = витрати на канал / кількість платних клієнтів. LTV/CAC - визначення чи окупається реклама (ROI) | L3: LTV/CAC — чи окупається реклама.
M4: ,= 1.0 = виходимо в нуль
A5: Канал | B5: Юзерів | C5: Total Revenue ($) | D5: LTV = Rev/N ($) | E5: Spend total ($) | F5: CAC ($) | G5: LTV / CAC | M5: > 1.0 = заробляємо
A6: Google Ads | B6: =COUNTIF('📋 Реєстрації'!$D$5:$D$606, $A6) -> 209 | C6: =SUMIF('📋 Реєстрації'!$D$5:$D$606, $A6, '👥 Клієнти'!$E$5:$E$606) -> 20429.78 | D6: =C6/B6 -> 97.750144 | E6: =SUMIF('💸 Маркетинг'!$B$5:$B$49, A6, '💸 Маркетинг'!$C$5:$C$49) -> 12746.85 | F6: =E6/B6 -> 60.989713 | G6: =D6/F6 -> 1.6027317 | M6: > 3.0 = канал треба масштабувати
A7: Facebook Ads | B7: =COUNTIF('📋 Реєстрації'!$D$5:$D$606, $A7) -> 124 | C7: =SUMIF('📋 Реєстрації'!$D$5:$D$606, $A7, '👥 Клієнти'!$E$5:$E$606) -> 10914.54 | D7: =C7/B7 -> 88.020484 | E7: =SUMIF('💸 Маркетинг'!$B$5:$B$49, A7, '💸 Маркетинг'!$C$5:$C$49) -> 9424.52 | F7: =E7/B7 -> 76.004194 | G7: =D7/F7 -> 1.1581004 | M7: < 1.0 = витрачаємо більше ніж заробляємо
A8: TikTok Ads | B8: =COUNTIF('📋 Реєстрації'!$D$5:$D$606, $A8) -> 90 | C8: =SUMIF('📋 Реєстрації'!$D$5:$D$606, $A8, '👥 Клієнти'!$E$5:$E$606) -> 8955.52 | D8: =C8/B8 -> 99.505778 | E8: =SUMIF('💸 Маркетинг'!$B$5:$B$49, A8, '💸 Маркетинг'!$C$5:$C$49) -> 12294.27 | F8: =E8/B8 -> 136.603 | G8: =D8/F8 -> 0.7284304
A9: Organic | B9: =COUNTIF('📋 Реєстрації'!$D$5:$D$606, $A9) -> 111 | C9: =SUMIF('📋 Реєстрації'!$D$5:$D$606, $A9, '👥 Клієнти'!$E$5:$E$606) -> 12993.5 | D9: =C9/B9 -> 117.05856 | E9: — | F9: — | G9: —
A10: Referral | B10: =COUNTIF('📋 Реєстрації'!$D$5:$D$606, $A10) -> 68 | C10: =SUMIF('📋 Реєстрації'!$D$5:$D$606, $A10, '👥 Клієнти'!$E$5:$E$606) -> 7016.49 | D10: =C10/B10 -> 103.18368 | E10: — | F10: — | G10: —
A12: Який канал рекомендуєте масштабувати? чи інвестуємо в рекламу прибутково?
A13: Тепер видно, що залучити 1го клієнта через Google Ads нам коштує $61, а приносить він нам $98. По Facebook Ads - залучення нам обходиться $76, а приносить 1 клієнт $88. Тобто Google Ads окупається (LTV / CAC = 1.6), а от Facebook Ads - ледь окупається (1.16). Що ж до TikTok Ads - це взагалі збитковий канал (LTV / CAC = 0.73). Organic та Referral є безкоштовними і при цьому приносять гарну виручку - це дуже цінно!
A20: 4. Що Ви запропонуєте маркетингу та продукту на основі висновків?
A21: Для маркетингу важливо відмовитись від збиткового TikTok Ads (LTV/CAC 0.73), продовжити масштабувати добре окупний Google Ads (LTV/CAC 1.6). Звернути увагу на сегмент Lost (27%) - він досить великий, можливо когось з втрачених клієнтів вдасться повернути завдяки продуманій кампанії. Для продукту важливо розібратись що саме тримає наших постійних клієнтів сегменту Champions та Loyal (разом 40% ) аби це не втратити. Згадати що саме відбулось в 2024-04 - когорта що показала найвищий retention на M+5 (75%) аби могли це повторити. Тримати увагу на тому, що окупається клієнт десь на M+6 (середній LTV = $102.68) тому надважливо втримати клієнта до цього моменту.
